Workbook

Sheet 2017 Stats
A1: Rk | B1: Player | C1: Tm | D1: FantPos | E1: Age | F1: Games G | G1: Games GS | H1: Passing Cmp | I1: Passing Att | J1: Passing Yds | K1: Passing TD | L1: Passing Int | M1: Rushing Att | N1: Rushing Yds | O1: Rushing Y/A | P1: Rushing TD | Q1: Receiving Tgt | R1: Receiving Rec | S1: Receiving Yds | T1: Receiving Y/R | U1: Receiving TD | V1: Fumbles Fmb | W1: Fumbles FL | X1: Scoring TD | Y1: Scoring 2PM | Z1: Scoring 2PP | AA1: Fantasy FantPt | AB1: Fantasy PPR | AC1: Fantasy DKPt | AD1: Fantasy FDPt | AE1: Fantasy VBD | AF1: Fantasy PosRank | AG1: Fantasy OvRank | AH1: Custom
A2: 1 | B2: Todd Gurley | C2: LAR | D2: RB | E2: 23 | F2: 15 | G2: 15 | H2: 0 | I2: 0 | J2: 0 | K2: 0 | L2: 0 | M2: 279 | N2: 1305 | O2: 4.68 | P2: 13 | Q2: 87 | R2: 64 | S2: 788 | T2: 12.31 | U2: 6 | V2: 5 | W2: 2 | X2: 19 | Y2: 0 | Z2: 0 | AA2: 319 | AB2: 383.3 | AC2: 391.3 | AD2: 351.3 | AE2: 192 | AF2: 1 | AG2: 1 | AH2: N
A3: 2 | B3: Le'Veon Bell | C3: PIT | D3: RB | E3: 25 | F3: 15 | G3: 15 | H3: 0 | I3: 0 | J3: 0 | K3: 0 | L3: 0 | M3: 321 | N3: 1291 | O3: 4.02 | P3: 9 | Q3: 106 | R3: 85 | S3: 655 | T3: 7.71 | U3: 2 | V3: 3 | W3: 2 | X3: 11 | Y3: 0 | Z3: 0 | AA3: 257 | AB3: 341.6 | AC3: 349.6 | AD3: 299.1 | AE3: 130 | AF3: 2 | AG3: 2 | AH3: N
A4: 3 | B4: Kareem Hunt | C4: KAN | D4: RB | E4: 22 | F4: 16 | G4: 16 | H4: 0 | I4: 0 | J4: 0 | K4: 0 | L4: 0 | M4: 272 | N4: 1327 | O4: 4.88 | P4: 8 | Q4: 63 | R4: 53 | S4: 455 | T4: 8.58 | U4: 3 | V4: 1 | W4: 1 | X4: 11 | Y4: 0 | Z4: 0 | AA4: 242 | AB4: 295.2 | AC4: 302.2 | AD4: 268.7 | AE4: 115 | AF4: 3 | AG4: 3 | AH4: N
A5: 4 | B5: Alvin Kamara | C5: NOR | D5: RB | E5: 22 | F5: 16 | G5: 3 | H5: 0 | I5: 0 | J5: 0 | K5: 0 | L5: 0 | M5: 120 | N5: 728 | O5: 6.07 | P5: 8 | Q5: 100 | R5: 81 | S5: 826 | T5: 10.2 | U5: 5 | V5: 1 | W5: 1 | X5: 14 | Y5: 1 | Z5: 0 | AA5: 239 | AB5: 320.4 | AC5: 327.4 | AD5: 279.9 | AE5: 112 | AF5: 4 | AG5: 4 | AH5: N
A6: 5 | B6: Melvin Gordon | C6: LAC | D6: RB | E6: 24 | F6: 16 | G6: 16 | H6: 0 | I6: 0 | J6: 0 | K6: 0 | L6: 0 | M6: 284 | N6: 1105 | O6: 3.89 | P6: 8 | Q6: 83 | R6: 58 | S6: 476 | T6: 8.21 | U6: 4 | V6: 1 | W6: 0 | X6: 12 | Y6: 0 | Z6: 0 | AA6: 230 | AB6: 288.1 | AC6: 294.1 | AD6: 259.1 | AE6: 103 | AF6: 5 | AG6: 5 | AH6: N
A7: 6 | B7: DeAndre Hopkins | C7: HOU | D7: WR | E7: 25 | F7: 15 | G7: 15 | H7: 0 | I7: 0 | J7: 0 | K7: 0 | L7: 0 | M7: 0 | N7: 0 | O7: 0 | P7: 0 | Q7: 174 | R7: 96 | S7: 1378 | T7: 14.35 | U7: 13 | V7: 1 | W7: 1 | X7: 13 | Y7: 0 | Z7: 0 | AA7: 214 | AB7: 309.8 | AC7: 313.8 | AD7: 261.8 | AE7: 103 | AF7: 1 | AG7: 6 | AH7: N
A8: 7 | B8: Antonio Brown | C8: PIT | D8: WR | E8: 29 | F8: 14 | G8: 14 | H8: 0 | I8: 0 | J8: 0 | K8: 0 | L8: 0 | M8: 0 | N8: 0 | O8: 0 | P8: 0 | Q8: 163 | R8: 101 | S8: 1533 | T8: 15.18 | U8: 9 | V8: 4 | W8: 0 | X8: 9 | Y8: 1 | Z8: 0 | AA8: 209 | AB8: 310.3 | AC8: 313.3 | AD8: 259.8 | AE8: 98 | AF8: 2 | AG8: 7 | AH8: N
A9: 8 | B9: Mark Ingram | C9: NOR | D9: RB | E9: 28 | F9: 16 | G9: 12 | H9: 0 | I9: 0 | J9: 0 | K9: 0 | L9: 0 | M9: 230 | N9: 1124 | O9: 4.89 | P9: 12 | Q9: 71 | R9: 58 | S9: 416 | T9: 7.17 | U9: 0 | V9: 3 | W9: 3 | X9: 12 | Y9: 0 | Z9: 0 | AA9: 220 | AB9: 278 | AC9: 287 | AD9: 249 | AE9: 93 | AF9: 6 | AG9: 8 | AH9: N
A10: 9 | B10: Russell Wilson | C10: SEA | D10: QB | E10: 29 | F10: 16 | G10: 16 | H10: 339 | I10: 553 | J10: 3983 | K10: 34 | L10: 11 | M10: 95 | N10: 586 | O10: 6.17 | P10: 3 | Q10: 0 | R10: 0 | S10: 0 | T10: 0 | U10: 0 | V10: 14 | W10: 3 | X10: 3 | Y10: 0 | Z10: 2 | AA10: 348 | AB10: 347.9 | AC10: 367.9 | AD10: 358.9 | AE10: 93 | AF10: 1 | AG10: 9 | AH10: N
A11: 10 | B11: LeSean McCoy | C11: BUF | D11: RB | E11: 29 | F11: 16 | G11: 16 | H11: 0 | I11: 0 | J11: 0 | K11: 0 | L11: 0 | M11: 287 | N11: 1138 | O11: 3.97 | P11: 6 | Q11: 77 | R11: 59 | S11: 448 | T11: 7.59 | U11: 2 | V11: 3 | W11: 1 | X11: 8 | Y11: 0 | Z11: 0 | AA11: 205 | AB11: 263.6 | AC11: 270.6 | AD11: 234.1 | AE11: 78 | AF11: 7 | AG11: 10 | AH11: N
A12: 11 | B12: Rob Gronkowski | C12: NWE | D12: TE | E12: 28 | F12: 14 | G12: 14 | H12: 0 | I12: 0 | J12: 0 | K12: 0 | L12: 0 | M12: 0 | N12: 0 | O12: 0 | P12: 0 | Q12: 105 | R12: 69 | S12: 1084 | T12: 15.71 | U12: 8 | V12: 1 | W12: 0 | X12: 8 | Y12: 1 | Z12: 0 | AA12: 158 | AB12: 227.4 | AC12: 230.4 | AD12: 192.9 | AE12: 77 | AF12: 1 | AG12: 11 | AH12: N
A13: 12 | B13: Travis Kelce | C13: KAN | D13: TE | E13: 28 | F13: 15 | G13: 15 | H13: 0 | I13: 1 | J13: 0 | K13: 0 | L13: 1 | M13: 2 | N13: 7 | O13: 3.5 | P13: 0 | Q13: 122 | R13: 83 | S13: 1038 | T13: 12.51 | U13: 8 | V13: 0 | W13: 0 | X13: 8 | Y13: 0 | Z13: 0 | AA13: 151 | AB13: 233.5 | AC13: 237.5 | AD13: 193 | AE13: 69 | AF13: 2 | AG13: 12 | AH13: N
... A75: 74 | B75: Tyler Kroft | C75: CIN | D75: TE | E75: 25 | F75: 16 | G75: 16 | H75: 0 | I75: 0 | J75: 0 | K75: 0 | L75: 0 | M75: 0 | N75: 0 | O75: 0 | P75: 0 | Q75: 62 | R75: 42 | S75: 404 | T75: 9.62 | U75: 7 | V75: 0 | W75: 0 | X75: 7 | Y75: 0 | Z75: 0 | AA75: 82 | AB75: 124.4 | AC75: 127.4 | AD75: 103.4 | AE75: 1 | AF75: 11 | AG75: 74 | AH75: N
A76: 75 | B76: Jermaine Kearse | C76: NYJ | D76: WR | E76: 27 | F76: 16 | G76: 14 | H76: 0 | I76: 0 | J76: 0 | K76: 0 | L76: 0 | M76: 0 | N76: 0 | O76: 0 | P76: 0 | Q76: 102 | R76: 65 | S76: 810 | T76: 12.46 | U76: 5 | V76: 1 | W76: 0 | X76: 5 | Y76: 0 | Z76: 0 | AA76: 111 | AB76: 176 | AC76: 179 | AD76: 143.5 | AF76: 30 | AG76: 75 | AH76: N
A77: 76 | B77: Jared Goff | C77: LAR | D77: QB | E77: 23 | F77: 15 | G77: 15 | H77: 296 | I77: 477 | J77: 3804 | K77: 28 | L77: 7 | M77: 28 | N77: 51 | O77: 1.82 | P77: 1 | Q77: 0 | R77: 0 | S77: 0 | T77: 0 | U77: 0 | V77: 8 | W77: 3 | X77: 1 | Y77: 0 | Z77: 0 | AA77: 255 | AB77: 255.3 | AC77: 268.3 | AD77: 262.3 | AF77: 12 | AG77: 76 | AH77: N
A78: 77 | B78: Hunter Henry | C78: LAC | D78: TE | E78: 23 | F78: 14 | G78: 13 | H78: 0 | I78: 0 | J78: 0 | K78: 0 | L78: 0 | M78: 0 | N78: 0 | O78: 0 | P78: 0 | Q78: 62 | R78: 45 | S78: 579 | T78: 12.87 | U78: 4 | V78: 0 | W78: 0 | X78: 4 | Y78: 0 | Z78: 0 | AA78: 82 | AB78: 126.9 | AC78: 129.9 | AD78: 104.4 | AF78: 12 | AG78: 77 | AH78: N
A79: 78 | B79: Alex Armah | C79: CAR | E79: 23 | F79: 9 | G79: 0 | H79: 0 | I79: 0 | J79: 0 | K79: 0 | L79: 0 | M79: 0 | N79: 0 | O79: 0 | P79: 0 | Q79: 0 | R79: 0 | S79: 0 | T79: 0 | U79: 0 | V79: 0 | W79: 0 | X79: 0 | Y79: 0 | Z79: 0 | AF79: 1 | AG79: 78 | AH79: N
A80: 79 | B80: Blake Bortles | C80: JAX | D80: QB | E80: 25 | F80: 16 | G80: 16 | H80: 315 | I80: 523 | J80: 3687 | K80: 21 | L80: 13 | M80: 57 | N80: 322 | O80: 5.65 | P80: 2 | Q80: 0 | R80: 0 | S80: 0 | T80: 0 | U80: 0 | V80: 9 | W80: 3 | X80: 2 | Y80: 0 | Z80: 3 | AA80: 250 | AB80: 249.7 | AC80: 271.7 | AD80: 262.7 | AF80: 13 | AH80: N
A81: 80 | B81: Case Keenum | C81: MIN | D81: QB | E81: 29 | F81: 15 | G81: 14 | H81: 325 | I81: 481 | J81: 3547 | K81: 22 | L81: 7 | M81: 40 | N81: 160 | O81: 4 | P81: 1 | Q81: 0 | R81: 0 | S81: 0 | T81: 0 | U81: 0 | V81: 1 | W81: 1 | X81: 1 | Y81: 0 | Z81: 1 | AA81: 238 | AB81: 237.9 | AC81: 251.9 | AD81: 244.9 | AF81: 14 | AH81: N
A82: 81 | B82: Matt Ryan | C82: ATL | D82: QB | E82: 32 | F82: 16 | G82: 16 | H82: 342 | I82: 529 | J82: 4095 | K82: 20 | L82: 12 | M82: 32 | N82: 143 | O82: 4.47 | P82: 0 | Q82: 0 | R82: 0 | S82: 0 | T82: 0 | U82: 0 | V82: 4 | W82: 3 | X82: 0 | Y82: 0 | Z82: 0 | AA82: 228 | AB82: 228.1 | AC82: 249.1 | AD82: 240.1 | AF82: 15 | AH82: N
A83: 82 | B83: Tyrod Taylor | C83: BUF | D83: QB | E83: 28 | F83: 15 | G83: 14 | H83: 263 | I83: 420 | J83: 2799 | K83: 14 | L83: 4 | M83: 84 | N83: 427 | O83: 5.08 | P83: 4 | Q83: 0 | R83: 0 | S83: 0 | T83: 0 | U83: 0 | V83: 4 | W83: 2 | X83: 4 | Y83: 0 | Z83: 0 | AA83: 223 | AB83: 222.7 | AC83: 234.7 | AD83: 226.7 | AF83: 16 | AH83: N
A84: 83 | B84: Andy Dalton | C84: CIN | D84: QB | E84: 30 | F84: 16 | G84: 16 | H84: 297 | I84: 496 | J84: 3320 | K84: 25 | L84: 12 | M84: 38 | N84: 99 | O84: 2.61 | P84: 0 | Q84: 0 | R84: 0 | S84: 0 | T84: 0 | U84: 0 | V84: 4 | W84: 4 | X84: 0 | Y84: 0 | Z84: 0 | AA84: 211 | AB84: 210.7 | AC84: 229.7 | AD84: 222.7 | AF84: 17 | AH84: N
A85: 84 | B85: Marcus Mariota | C85: TEN | D85: QB | E85: 24 | F85: 15 | G85: 15 | H85: 281 | I85: 453 | J85: 3232 | K85: 13 | L85: 15 | M85: 60 | N85: 312 | O85: 5.2 | P85: 5 | Q85: 0 | R85: 0 | S85: 0 | T85: 0 | U85: 0 | V85: 2 | W85: 1 | X85: 5 | Y85: 0 | Z85: 0 | AA85: 210 | AB85: 210.5 | AC85: 232.5 | AD85: 225.5 | AF85: 18 | AH85: N
A86: 85 | B86: Jacoby Brissett | C86: IND | D86: QB | E86: 25 | F86: 16 | G86: 15 | H86: 276 | I86: 469 | J86: 3098 | K86: 13 | L86: 7 | M86: 63 | N86: 260 | O86: 4.13 | P86: 4 | Q86: 0 | R86: 0 | S86: 0 | T86: 0 | U86: 0 | V86: 8 | W86: 3 | X86: 4 | Y86: 0 | Z86: 0 | AA86: 206 | AB86: 205.9 | AC86: 221.9 | AD86: 212.9 | AF86: 20 | AH86: N
A87: 86 | B87: Derek Carr | C87: OAK | D87: QB | E87: 26 | F87: 15 | G87: 15 | H87: 323 | I87: 515 | J87: 3496 | K87: 22 | L87: 13 | M87: 23 | N87: 66 | O87: 2.87 | P87: 0 | Q87: 0 | R87: 0 | S87: 0 | T87: 0 | U87: 0 | V87: 8 | W87: 3 | X87: 0 | Y87: 0 | Z87: 2 | AA87: 206 | AB87: 206.4 | AC87: 225.4 | AD87: 219.4 | AF87: 19 | AH87: N
A88: 87 | B88: Josh McCown | C88: NYJ | D88: QB | E88: 38 | F88: 13 | G88: 13 | H88: 267 | I88: 397 | J88: 2926 | K88: 18 | L88: 9 | M88: 37 | N88: 124 | O88: 3.35 | P88: 5 | Q88: 0 | R88: 0 | S88: 0 | T88: 0 | U88: 0 | V88: 11 | W88: 4 | X88: 5 | Y88: 0 | Z88: 0 | AA88: 205 | AB88: 205.4 | AC88: 224.4 | AD88: 214.4 | AF88: 21 | AH88: N
A89: 88 | B89: Jameis Winston | C89: TAM | D89: QB | E89: 23 | F89: 13 | G89: 13 | H89: 282 | I89: 442 | J89: 3504 | K89: 19 | L89: 11 | M89: 33 | N89: 135 | O89: 4.09 | P89: 1 | Q89: 0 | R89: 0 | S89: 0 | T89: 0 | U89: 0 | V89: 15 | W89: 7 | X89: 1 | Y89: 0 | Z89: 1 | AA89: 202 | AB89: 201.7 | AC89: 225.7 | AD89: 212.7 | AF89: 22 | AH89: N
A90: 89 | B90: Eli Manning | C90: NYG | D90: QB | E90: 36 | F90: 15 | G90: 15 | H90: 352 | I90: 571 | J90: 3468 | K90: 19 | L90: 13 | M90: 12 | N90: 26 | O90: 2.17 | P90: 1 | Q90: 0 | R90: 0 | S90: 0 | T90: 0 | U90: 0 | V90: 11 | W90: 5 | X90: 1 | Y90: 0 | Z90: 0 | AA90: 187 | AB90: 187.3 | AC90: 208.3 | AD90: 200.3 | AF90: 23 | AH90: N
A91: 90 | B91: Joe Flacco | C91: BAL | D91: QB | E91: 32 | F91: 16 | G91: 16 | H91: 352 | I91: 549 | J91: 3141 | K91: 18 | L91: 13 | M91: 25 | N91: 54 | O91: 2.16 | P91: 1 | Q91: 0 | R91: 0 | S91: 0 | T91: 0 | U91: 0 | V91: 6 | W91: 0 | X91: 1 | Y91: 0 | Z91: 1 | AA91: 185 | AB91: 185 | AC91: 201 | AD91: 198 | AF91: 24 | AH91: N
... A516: 515 | B516: Kevin White | C516: CHI | D516: WR | E516: 25 | F516: 1 | G516: 1 | H516: 0 | I516: 0 | J516: 0 | K516: 0 | L516: 0 | M516: 0 | N516: 0 | O516: 0 | P516: 0 | Q516: 4 | R516: 2 | S516: 6 | T516: 3 | U516: 0 | V516: 0 | W516: 0 | X516: 0 | Y516: 0 | Z516: 0 | AA516: 1 | AB516: 2.6 | AC516: 2.6 | AD516: 1.6 | AF516: 192 | AH516: N
A517: 516 | B517: Derek Anderson | C517: CAR | D517: QB | E517: 34 | F517: 3 | G517: 0 | H517: 2 | I517: 8 | J517: 17 | K517: 0 | L517: 0 | M517: 2 | N517: -2 | O517: -1 | P517: 0 | Q517: 0 | R517: 0 | S517: 0 | T517: 0 | U517: 0 | V517: 0 | W517: 0 | X517: 0 | Y517: 0 | Z517: 0 | AB517: 0.5 | AC517: 0.5 | AD517: 0.5 | AF517: 65 | AH517: N
A518: 517 | B518: Joe Banyard | C518: BUF | E518: 29 | F518: 3 | G518: 0 | H518: 0 | I518: 0 | J518: 0 | K518: 0 | L518: 0 | M518: 0 | N518: 0 | O518: 0 | P518: 0 | Q518: 0 | R518: 0 | S518: 0 | T518: 0 | U518: 0 | V518: 0 | W518: 0 | X518: 0 | Y518: 0 | Z518: 0 | AF518: 156 | AH518: N
A519: 518 | B519: Evan Baylis | C519: HOU | E519: 24 | F519: 1 | G519: 0 | H519: 0 | I519: 0 | J519: 0 | K519: 0 | L519: 0 | M519: 0 | N519: 0 | O519: 0 | P519: 0 | Q519: 0 | R519: 0 | S519: 0 | T519: 0 | U519: 0 | V519: 0 | W519: 0 | X519: 0 | Y519: 0 | Z519: 0 | AF519: 122 | AH519: N
A520: 519 | B520: Victor Bolden | C520: SFO | E520: 22 | F520: 9 | G520: 0 | H520: 0 | I520: 0 | J520: 0 | K520: 0 | L520: 0 | M520: 0 | N520: 0 | O520: 0 | P520: 0 | Q520: 0 | R520: 0 | S520: 0 | T520: 0 | U520: 0 | V520: 0 | W520: 0 | X520: 0 | Y520: 0 | Z520: 0 | AF520: 203 | AH520: N
A521: 520 | B521: Ben Braunecker | C521: CHI | E521: 23 | F521: 8 | G521: 0 | H521: 0 | I521: 0 | J521: 0 | K521: 0 | L521: 0 | M521: 0 | N521: 0 | O521: 0 | P521: 0 | Q521: 0 | R521: 0 | S521: 0 | T521: 0 | U521: 0 | V521: 0 | W521: 0 | X521: 0 | Y521: 0 | Z521: 0 | AF521: 109 | AH521: N
A522: 521 | B522: Joe Callahan | C522: GNB | D522: QB | E522: 24 | F522: 1 | G522: 0 | H522: 5 | I522: 7 | J522: 11 | K522: 0 | L522: 0 | M522: 0 | N522: 0 | O522: 0 | P522: 0 | Q522: 0 | R522: 0 | S522: 0 | T522: 0 | U522: 0 | V522: 0 | W522: 0 | X522: 0 | Y522: 0 | Z522: 0 | AB522: 0.4 | AC522: 0.4 | AD522: 0.4 | AF522: 66 | AH522: N
A523: 522 | B523: Cethan Carter | C523: CIN | E523: 22 | F523: 16 | G523: 0 | H523: 0 | I523: 0 | J523: 0 | K523: 0 | L523: 0 | M523: 0 | N523: 0 | O523: 0 | P523: 0 | Q523: 0 | R523: 0 | S523: 0 | T523: 0 | U523: 0 | V523: 0 | W523: 0 | X523: 0 | Y523: 0 | Z523: 0 | AF523: 111 | AH523: N
A524: 523 | B524: Stacy Coley | C524: MIN | E524: 23 | F524: 4 | G524: 0 | H524: 0 | I524: 0 | J524: 0 | K524: 0 | L524: 0 | M524: 0 | N524: 0 | O524: 0 | P524: 0 | Q524: 0 | R524: 0 | S524: 0 | T524: 0 | U524: 0 | V524: 0 | W524: 0 | X524: 0 | Y524: 0 | Z524: 0 | AF524: 204 | AH524: N
A525: 524 | B525: Cody Core | C525: CIN | E525: 23 | F525: 13 | G525: 0 | H525: 0 | I525: 0 | J525: 0 | K525: 0 | L525: 0 | M525: 0 | N525: 0 | O525: 0 | P525: 0 | Q525: 4 | R525: 0 | S525: 0 | T525: 0 | U525: 0 | V525: 0 | W525: 0 | X525: 0 | Y525: 0 | Z525: 0 | AF525: 199 | AH525: N
A526: 525 | B526: Sean Culkin | C526: LAC | E526: 24 | F526: 1 | G526: 0 | H526: 0 | I526: 0 | J526: 0 | K526: 0 | L526: 0 | M526: 0 | N526: 0 | O526: 0 | P526: 0 | Q526: 0 | R526: 0 | S526: 0 | T526: 0 | U526: 0 | V526: 0 | W526: 0 | X526: 0 | Y526: 0 | Z526: 0 | AF526: 115 | AH526: N
A527: 526 | B527: Jeff Cumberland | C527: LAC | D527: TE | E527: 30 | F527: 7 | G527: 3 | H527: 0 | I527: 0 | J527: 0 | K527: 0 | L527: 0 | M527: 0 | N527: 0 | O527: 0 | P527: 0 | Q527: 3 | R527: 2 | S527: 2 | T527: 1 | U527: 0 | V527: 0 | W527: 0 | X527: 0 | Y527: 0 | Z527: 0 | AB527: 2.2 | AC527: 2.2 | AD527: 1.2 | AF527: 108 | AH527: N
A528: 527 | B528: Chase Daniel | C528: NOR | D528: QB | E528: 31 | F528: 1 | G528: 0 | H528: 0 | I528: 0 | J528: 0 | K528: 0 | L528: 0 | M528: 3 | N528: -2 | O528: -0.67 | P528: 0 | Q528: 0 | R528: 0 | S528: 0 | T528: 0 | U528: 0 | V528: 0 | W528: 0 | X528: 0 | Y528: 0 | Z528: 0 | AB528: -0.2 | AC528: -0.2 | AD528: -0.2 | AF528: 69 | AH528: N
A529: 528 | B529: Austin Davis | C529: SEA | D529: QB | E529: 28 | F529: 3 | G529: 0 | H529: 0 | I529: 0 | J529: 0 | K529: 0 | L529: 0 | M529: 1 | N529: -1 | O529: -1 | P529: 0 | Q529: 0 | R529: 0 | S529: 0 | T529: 0 | U529: 0 | V529: 0 | W529: 0 | X529: 0 | Y529: 0 | Z529: 0 | AB529: -0.1 | AC529: -0.1 | AD529: -0.1 | AF529: 68 | AH529: N
A530: 529 | B530: Geremy Davis | C530: LAC | E530: 25 | F530: 2 | G530: 0 | H530: 0 | I530: 0 | J530: 0 | K530: 0 | L530: 0 | M530: 0 | N530: 0 | O530: 0 | P530: 0 | Q530: 0 | R530: 0 | S530: 0 | T530: 0 | U530: 0 | V530: 0 | W530: 0 | X530: 0 | Y530: 0 | Z530: 0 | AF530: 200 | AH530: N
A531: 530 | B531: Justin Davis | C531: LAR | D531: RB | E531: 22 | F531: 4 | G531: 0 | H531: 0 | I531: 0 | J531: 0 | K531: 0 | L531: 0 | M531: 1 | N531: 1 | O531: 1 | P531: 0 | Q531: 0 | R531: 0 | S531: 0 | T531: 0 | U531: 0 | V531: 0 | W531: 0 | X531: 0 | Y531: 0 | Z531: 0 | AB531: 0.1 | AC531: 0.1 | AD531: 0.1 | AF531: 154 | AH531: N
A532: 531 | B532: Jim Dray | C532: ARI | E532: 31 | F532: 1 | G532: 0 | H532: 0 | I532: 0 | J532: 0 | K532: 0 | L532: 0 | M532: 0 | N532: 0 | O532: 0 | P532: 0 | Q532: 0 | R532: 0 | S532: 0 | T532: 0 | U532: 0 | V532: 0 | W532: 0 | X532: 0 | Y532: 0 | Z532: 0 | AF532: 113 | AH532: N
A533: 532 | B533: Gavin Escobar | C533: BAL | E533: 26 | F533: 2 | G533: 0 | H533: 0 | I533: 0 | J533: 0 | K533: 0 | L533: 0 | M533: 0 | N533: 0 | O533: 0 | P533: 0 | Q533: 0 | R533: 0 | S533: 0 | T533: 0 | U533: 0 | V533: 0 | W533: 0 | X533: 0 | Y533: 0 | Z533: 0 | AF533: 124 | AH533: N
A534: 533 | B534: Garrett Griffin | C534: NOR | D534: TE | E534: 23 | F534: 3 | G534: 0 | H534: 0 | I534: 0 | J534: 0 | K534: 0 | L534: 0 | M534: 0 | N534: 0 | O534: 0 | P534: 0 | Q534: 1 | R534: 1 | S534: 4 | T534: 4 | U534: 0 | V534: 0 | W534: 0 | X534: 0 | Y534: 0 | Z534: 0 | AB534: 1.4 | AC534: 1.4 | AD534: 0.9 | AF534: 106 | AH534: N
A535: 534 | B535: Justin Hardee | C535: NOR | E535: 23 | F535: 14 | G535: 0 | H535: 0 | I535: 0 | J535: 0 | K535: 0 | L535: 0 | M535: 0 | N535: 0 | O535: 0 | P535: 0 | Q535: 0 | R535: 0 | S535: 0 | T535: 0 | U535: 0 | V535: 0 | W535: 0 | X535: 0 | Y535: 0 | Z535: 0 | AF535: 205 | AH535: N
A536: 535 | B536: Clark Harris | C536: CIN | E536: 33 | F536: 16 | G536: 0 | H536: 0 | I536: 0 | J536: 0 | K536: 0 | L536: 0 | M536: 0 | N536: 0 | O536: 0 | P536: 0 | Q536: 0 | R536: 0 | S536: 0 | T536: 0 | U536: 0 | V536: 0 | W536: 0 | X536: 0 | Y536: 0 | Z536: 0 | AF536: 116 | AH536: N
A537: 536 | B537: Matt Hazel | C537: IND | D537: WR | E537: 25 | F537: 4 | G537: 0 | H537: 0 | I537: 0 | J537: 0 | K537: 0 | L537: 0 | M537: 0 | N537: 0 | O537: 0 | P537: 0 | Q537: 1 | R537: 1 | S537: 1 | T537: 1 | U537: 0 | V537: 0 | W537: 0 | X537: 0 | Y537: 0 | Z537: 0 | AB537: 1.1 | AC537: 1.1 | AD537: 0.6 | AF537: 197 | AH537: N
A538: 537 | B538: Bronson Hill | C538: ARI | D538: RB | E538: 24 | F538: 2 | G538: 0 | H538: 0 | I538: 0 | J538: 0 | K538: 0 | L538: 0 | M538: 1 | N538: -2 | O538: -2 | P538: 0 | Q538: 0 | R538: 0 | S538: 0 | T538: 0 | U538: 0 | V538: 0 | W538: 0 | X538: 0 | Y538: 0 | Z538: 0 | AB538: -0.2 | AC538: -0.2 | AD538: -0.2 | AF538: 160 | AH538: N
A539: 538 | B539: Andy Jones | C539: 2TM | E539: 23 | F539: 3 | G539: 0 | H539: 0 | I539: 0 | J539: 0 | K539: 0 | L539: 0 | M539: 0 | N539: 0 | O539: 0 | P539: 0 | Q539: 0 | R539: 0 | S539: 0 | T539: 0 | U539: 0 | V539: 0 | W539: 0 | X539: 0 | Y539: 0 | Z539: 0 | AF539: 201 | AH539: N
A540: 539 | B540: Joe Kerridge | C540: GNB | D540: RB | E540: 25 | F540: 4 | G540: 0 | H540: 0 | I540: 0 | J540: 0 | K540: 0 | L540: 0 | M540: 0 | N540: 0 | O540: 0 | P540: 0 | Q540: 1 | R540: 1 | S540: 3 | T540: 3 | U540: 0 | V540: 0 | W540: 0 | X540: 0 | Y540: 0 | Z540: 0 | AB540: 1.3 | AC540: 1.3 | AD540: 0.8 | AF540: 152 | AH540: N
A541: 540 | B541: John Kuhn | C541: NOR | D541: RB | E541: 35 | F541: 2 | G541: 1 | H541: 0 | I541: 0 | J541: 0 | K541: 0 | L541: 0 | M541: 1 | N541: 2 | O541: 2 | P541: 0 | Q541: 0 | R541: 0 | S541: 0 | T541: 0 | U541: 0 | V541: 0 | W541: 0 | X541: 0 | Y541: 0 | Z541: 0 | AB541: 0.2 | AC541: 0.2 | AD541: 0.2 | AF541: 153 | AH541: N
A542: 541 | B542: Matt LaCosse | C542: 2TM | E542: 25 | F542: 5 | G542: 1 | H542: 0 | I542: 0 | J542: 0 | K542: 0 | L542: 0 | M542: 0 | N542: 0 | O542: 0 | P542: 0 | Q542: 1 | R542: 0 | S542: 0 | T542: 0 | U542: 0 | V542: 0 | W542: 0 | X542: 0 | Y542: 0 | Z542: 0 | AF542: 123 | AH542: N
A543: 542 | B543: Daniel Lasco | C543: NOR | E543: 25 | F543: 3 | G543: 0 | H543: 0 | I543: 0 | J543: 0 | K543: 0 | L543: 0 | M543: 0 | N543: 0 | O543: 0 | P543: 0 | Q543: 0 | R543: 0 | S543: 0 | T543: 0 | U543: 0 | V543: 0 | W543: 0 | X543: 0 | Y543: 0 | Z543: 0 | AF543: 159 | AH543: N
A544: 543 | B544: Khari Lee | C544: BUF | E544: 25 | F544: 8 | G544: 0 | H544: 0 | I544: 0 | J544: 0 | K544: 0 | L544: 0 | M544: 0 | N544: 0 | O544: 0 | P544: 0 | Q544: 0 | R544: 0 | S544: 0 | T544: 0 | U544: 0 | V544: 0 | W544: 0 | X544: 0 | Y544: 0 | Z544: 0 | AF544: 112 | AH544: N
A545: 544 | B545: Terrence Magee | C545: ATL | E545: 24 | F545: 2 | G545: 0 | H545: 0 | I545: 0 | J545: 0 | K545: 0 | L545: 0 | M545: 0 | N545: 0 | O545: 0 | P545: 0 | Q545: 0 | R545: 0 | S545: 0 | T545: 0 | U545: 0 | V545: 0 | W545: 0 | X545: 0 | Y545: 0 | Z545: 0 | AF545: 157 | AH545: N
A546: 545 | B546: Ryan Malleck | C546: HOU | D546: TE | E546: 24 | F546: 2 | G546: 0 | H546: 0 | I546: 0 | J546: 0 | K546: 0 | L546: 0 | M546: 0 | N546: 0 | O546: 0 | P546: 0 | Q546: 1 | R546: 1 | S546: 3 | T546: 3 | U546: 0 | V546: 0 | W546: 0 | X546: 0 | Y546: 0 | Z546: 0 | AB546: 1.3 | AC546: 1.3 | AD546: 0.8 | AF546: 107 | AH546: N
A547: 546 | B547: Bradley Marquez | C547: DET | E547: 25 | F547: 1 | G547: 0 | H547: 0 | I547: 0 | J547: 0 | K547: 0 | L547: 0 | M547: 0 | N547: 0 | O547: 0 | P547: 0 | Q547: 0 | R547: 0 | S547: 0 | T547: 0 | U547: 0 | V547: 0 | W547: 0 | X547: 0 | Y547: 0 | Z547: 0 | AF547: 202 | AH547: N
A548: 547 | B548: Max McCaffrey | C548: JAX | D548: WR | E548: 23 | F548: 5 | G548: 0 | H548: 0 | I548: 0 | J548: 0 | K548: 0 | L548: 0 | M548: 0 | N548: 0 | O548: 0 | P548: 0 | Q548: 1 | R548: 1 | S548: 4 | T548: 4 | U548: 0 | V548: 0 | W548: 0 | X548: 0 | Y548: 0 | Z548: 0 | AB548: 1.4 | AC548: 1.4 | AD548: 0.9 | AF548: 195 | AH548: N
A549: 548 | B549: Colt McCoy | C549: WAS | E549: 31 | F549: 1 | G549: 0 | H549: 0 | I549: 0 | J549: 0 | K549: 0 | L549: 0 | M549: 0 | N549: 0 | O549: 0 | P549: 0 | Q549: 0 | R549: 0 | S549: 0 | T549: 0 | U549: 0 | V549: 0 | W549: 0 | X549: 0 | Y549: 0 | Z549: 0 | AF549: 67 | AH549: N
A550: 549 | B550: Darren McFadden | C550: DAL | D550: RB | E550: 30 | F550: 1 | G550: 0 | H550: 0 | I550: 0 | J550: 0 | K550: 0 | L550: 0 | M550: 1 | N550: -2 | O550: -2 | P550: 0 | Q550: 0 | R550: 0 | S550: 0 | T550: 0 | U550: 0 | V550: 0 | W550: 0 | X550: 0 | Y550: 0 | Z550: 0 | AB550: -0.2 | AC550: -0.2 | AD550: -0.2 | AF550: 161 | AH550: N
A551: 550 | B551: Ryan O'Malley | C551: NYG | E551: 24 | F551: 1 | G551: 0 | H551: 0 | I551: 0 | J551: 0 | K551: 0 | L551: 0 | M551: 0 | N551: 0 | O551: 0 | P551: 0 | Q551: 0 | R551: 0 | S551: 0 | T551: 0 | U551: 0 | V551: 0 | W551: 0 | X551: 0 | Y551: 0 | Z551: 0 | AF551: 118 | AH551: N
A552: 551 | B552: Logan Paulsen | C552: SFO | E552: 30 | F552: 14 | G552: 1 | H552: 0 | I552: 0 | J552: 0 | K552: 0 | L552: 0 | M552: 0 | N552: 0 | O552: 0 | P552: 0 | Q552: 2 | R552: 0 | S552: 0 | T552: 0 | U552: 0 | V552: 0 | W552: 0 | X552: 0 | Y552: 0 | Z552: 0 | AF552: 119 | AH552: N
A553: 552 | B553: Charone Peake | C553: NYJ | D553: WR | E553: 25 | F553: 3 | G553: 0 | H553: 0 | I553: 0 | J553: 0 | K553: 0 | L553: 0 | M553: 0 | N553: 0 | O553: 0 | P553: 0 | Q553: 1 | R553: 1 | S553: 3 | T553: 3 | U553: 0 | V553: 0 | W553: 0 | X553: 0 | Y553: 0 | Z553: 0 | AB553: 1.3 | AC553: 1.3 | AD553: 0.8 | AF553: 196 | AH553: N
A554: 553 | B554: John Phillips | C554: NOR | E554: 30 | F554: 1 | G554: 0 | H554: 0 | I554: 0 | J554: 0 | K554: 0 | L554: 0 | M554: 0 | N554: 0 | O554: 0 | P554: 0 | Q554: 0 | R554: 0 | S554: 0 | T554: 0 | U554: 0 | V554: 0 | W554: 0 | X554: 0 | Y554: 0 | Z554: 0 | AF554: 117 | AH554: N
A555: 554 | B555: MyCole Pruitt | C555: HOU | E555: 25 | F555: 1 | G555: 0 | H555: 0 | I555: 0 | J555: 0 | K555: 0 | L555: 0 | M555: 0 | N555: 0 | O555: 0 | P555: 0 | Q555: 0 | R555: 0 | S555: 0 | T555: 0 | U555: 0 | V555: 0 | W555: 0 | X555: 0 | Y555: 0 | Z555: 0 | AF555: 110 | AH555: N
A556: 555 | B556: Eric Saubert | C556: ATL | E556: 23 | F556: 14 | G556: 0 | H556: 0 | I556: 0 | J556: 0 | K556: 0 | L556: 0 | M556: 0 | N556: 0 | O556: 0 | P556: 0 | Q556: 0 | R556: 0 | S556: 0 | T556: 0 | U556: 0 | V556: 0 | W556: 0 | X556: 0 | Y556: 0 | Z556: 0 | AF556: 114 | AH556: N
A557: 556 | B557: Matthew Slater | C557: NWE | E557: 32 | F557: 9 | G557: 0 | H557: 0 | I557: 0 | J557: 0 | K557: 0 | L557: 0 | M557: 0 | N557: 0 | O557: 0 | P557: 0 | Q557: 0 | R557: 0 | S557: 0 | T557: 0 | U557: 0 | V557: 0 | W557: 0 | X557: 0 | Y557: 0 | Z557: 0 | AF557: 198 | AH557: N
A558: 557 | B558: Shane Smith | C558: NYG | E558: 24 | F558: 11 | G558: 4 | H558: 0 | I558: 0 | J558: 0 | K558: 0 | L558: 0 | M558: 0 | N558: 0 | O558: 0 | P558: 0 | Q558: 0 | R558: 0 | S558: 0 | T558: 0 | U558: 0 | V558: 0 | W558: 0 | X558: 0 | Y558: 0 | Z558: 0 | AF558: 2 | AH558: N
A559: 558 | B559: Nate Solder | C559: NWE | E559: 29 | F559: 16 | G559: 16 | H559: 0 | I559: 0 | J559: 0 | K559: 0 | L559: 0 | M559: 0 | N559: 0 | O559: 0 | P559: 0 | Q559: 0 | R559: 0 | S559: 0 | T559: 0 | U559: 0 | V559: 0 | W559: 0 | X559: 0 | Y559: 0 | Z559: 0 | AF559: 120 | AH559: N
A560: 559 | B560: C.J. Spiller | C560: KAN | D560: RB | E560: 30 | F560: 1 | G560: 0 | H560: 0 | I560: 0 | J560: 0 | K560: 0 | L560: 0 | M560: 2 | N560: 0 | O560: 0 | P560: 0 | Q560: 2 | R560: 0 | S560: 0 | T560: 0 | U560: 0 | V560: 0 | W560: 0 | X560: 0 | Y560: 0 | Z560: 0 | AF560: 155 | AH560: N
A561: 560 | B561: Jordan Todman | C561: HOU | E561: 27 | F561: 14 | G561: 0 | H561: 0 | I561: 0 | J561: 0 | K561: 0 | L561: 0 | M561: 0 | N561: 0 | O561: 0 | P561: 0 | Q561: 0 | R561: 0 | S561: 0 | T561: 0 | U561: 0 | V561: 0 | W561: 0 | X561: 0 | Y561: 0 | Z561: 0 | AF561: 158 | AH561: N
A562: 561 | B562: Hakeem Valles | C562: DET | E562: 25 | F562: 1 | G562: 0 | H562: 0 | I562: 0 | J562: 0 | K562: 0 | L562: 0 | M562: 0 | N562: 0 | O562: 0 | P562: 0 | Q562: 0 | R562: 0 | S562: 0 | T562: 0 | U562: 0 | V562: 0 | W562: 0 | X562: 0 | Y562: 0 | Z562: 0 | AF562: 121 | AH562: N
A563: 562 | B563: Kellen Clemens | C563: LAC | D563: QB | E563: 34 | F563: 8 | G563: 0 | H563: 6 | I563: 8 | J563: 36 | K563: 0 | L563: 1 | M563: 5 | N563: -5 | O563: -1 | P563: 0 | Q563: 0 | R563: 0 | S563: 0 | T563: 0 | U563: 0 | V563: 0 | W563: 0 | X563: 0 | Y563: 0 | Z563: 0 | AA563: -1 | AB563: -1.1 | AC563: -0.1 | AD563: -0.1 | AF563: 72 | AH563: N
A564: 563 | B564: Chad Henne | C564: JAX | D564: QB | E564: 32 | F564: 2 | G564: 0 | H564: 0 | I564: 2 | J564: 0 | K564: 0 | L564: 0 | M564: 5 | N564: -5 | O564: -1 | P564: 0 | Q564: 0 | R564: 0 | S564: 0 | T564: 0 | U564: 0 | V564: 0 | W564: 0 | X564: 0 | Y564: 0 | Z564: 0 | AA564: -1 | AB564: -0.5 | AC564: -0.5 | AD564: -0.5 | AF564: 70 | AH564: N
A565: 564 | B565: Isaiah McKenzie | C565: DEN | D565: WR | E565: 22 | F565: 11 | G565: 0 | H565: 0 | I565: 0 | J565: 0 | K565: 0 | L565: 0 | M565: 1 | N565: 4 | O565: 4 | P565: 0 | Q565: 13 | R565: 4 | S565: 29 | T565: 7.25 | U565: 0 | V565: 6 | W565: 2 | X565: 0 | Y565: 0 | Z565: 0 | AA565: -1 | AB565: 3.3 | AC565: 5.3 | AD565: 1.3 | AF565: 206 | AH565: N
A566: 565 | B566: Kalif Raymond | C566: 2TM | D566: WR | E566: 23 | F566: 8 | G566: 0 | H566: 0 | I566: 0 | J566: 0 | K566: 0 | L566: 0 | M566: 1 | N566: -1 | O566: -1 | P566: 0 | Q566: 1 | R566: 1 | S566: 12 | T566: 12 | U566: 0 | V566: 5 | W566: 1 | X566: 0 | Y566: 0 | Z566: 0 | AA566: -1 | AB566: 0.1 | AC566: 1.1 | AD566: -0.4 | AF566: 209 | AH566: N
A567: 566 | B567: Andre Roberts | C567: ATL | D567: WR | E567: 29 | F567: 16 | G567: 0 | H567: 0 | I567: 0 | J567: 0 | K567: 0 | L567: 0 | M567: 0 | N567: 0 | O567: 0 | P567: 0 | Q567: 4 | R567: 1 | S567: 12 | T567: 12 | U567: 0 | V567: 4 | W567: 1 | X567: 0 | Y567: 0 | Z567: 0 | AA567: -1 | AB567: 0.2 | AC567: 1.2 | AD567: -0.3 | AF567: 207 | AH567: N
A568: 567 | B568: John Ross | C568: CIN | D568: WR | E568: 23 | F568: 3 | G568: 1 | H568: 0 | I568: 0 | J568: 0 | K568: 0 | L568: 0 | M568: 1 | N568: 12 | O568: 12 | P568: 0 | Q568: 2 | R568: 0 | S568: 0 | T568: 0 | U568: 0 | V568: 1 | W568: 1 | X568: 0 | Y568: 0 | Z568: 0 | AA568: -1 | AB568: -0.8 | AC568: 0.2 | AD568: -0.8 | AF568: 208 | AH568: N
A569: 568 | B569: Jake Rudock | C569: DET | D569: QB | E569: 24 | F569: 3 | G569: 0 | H569: 3 | I569: 5 | J569: 24 | K569: 0 | L569: 1 | M569: 0 | N569: 0 | O569: 0 | P569: 0 | Q569: 0 | R569: 0 | S569: 0 | T569: 0 | U569: 0 | V569: 0 | W569: 0 | X569: 0 | Y569: 0 | Z569: 0 | AA569: -1 | AB569: -1 | AF569: 71 | AH569: N
A570: 569 | B570: Tyler Bray | C570: KAN | D570: QB | E570: 26 | F570: 1 | G570: 0 | H570: 0 | I570: 1 | J570: 0 | K570: 0 | L570: 0 | M570: 1 | N570: 0 | O570: 0 | P570: 0 | Q570: 0 | R570: 0 | S570: 0 | T570: 0 | U570: 0 | V570: 1 | W570: 1 | X570: 0 | Y570: 0 | Z570: 0 | AA570: -2 | AB570: -2 | AC570: -1 | AD570: -2 | AF570: 73 | AH570: N
A571: 570 | B571: Teddy Bridgewater | C571: MIN | D571: QB | E571: 25 | F571: 1 | G571: 0 | H571: 0 | I571: 2 | J571: 0 | K571: 0 | L571: 1 | M571: 3 | N571: -3 | O571: -1 | P571: 0 | Q571: 0 | R571: 0 | S571: 0 | T571: 0 | U571: 0 | V571: 0 | W571: 0 | X571: 0 | Y571: 0 | Z571: 0 | AA571: -2 | AB571: -2.3 | AC571: -1.3 | AD571: -1.3 | AF571: 74 | AH571: N
A572: 571 | B572: Devante Mays | C572: GNB | D572: RB | E572: 23 | F572: 8 | G572: 0 | H572: 0 | I572: 0 | J572: 0 | K572: 0 | L572: 0 | M572: 4 | N572: 1 | O572: 0.25 | P572: 0 | Q572: 3 | R572: 3 | S572: 0 | T572: 0 | U572: 0 | V572: 2 | W572: 1 | X572: 0 | Y572: 0 | Z572: 0 | AA572: -2 | AB572: 1.1 | AC572: 2.1 | AD572: -0.4 | AF572: 162 | AH572: N

Sheet 2018 Stats
A1: Rk | B1: Player | C1: Tm | D1: FantPos | E1: Age | F1: Games G | G1: Games GS | H1: Passing Cmp | I1: Passing Att | J1: Passing Yds | K1: Passing TD | L1: Passing Int | M1: Rushing Att | N1: Rushing Yds | O1: Rushing Y/A | P1: Rushing TD | Q1: Receiving Tgt | R1: Receiving Rec | S1: Receiving Yds | T1: Receiving Y/R | U1: Receiving TD | V1: Fumbles Fmb | W1: Fumbles FL | X1: Scoring TD | Y1: Scoring 2PM | Z1: Scoring 2PP | AA1: Fantasy FantPt | AB1: Fantasy PPR | AC1: Fantasy DKPt | AD1: Fantasy FDPt | AE1: Fantasy VBD | AF1: Fantasy PosRank | AG1: Fantasy OvRank | AH1: Custom
A2: 1 | B2: Todd Gurley | C2: LAR | D2: RB | E2: 24 | F2: 14 | G2: 14 | H2: 0 | I2: 0 | J2: 0 | K2: 0 | L2: 0 | M2: 256 | N2: 1251 | O2: 4.89 | P2: 17 | Q2: 81 | R2: 59 | S2: 580 | T2: 9.83 | U2: 4 | V2: 1 | W2: 1 | X2: 21 | Y2: 3 | Z2: 0 | AA2: 313 | AB2: 372.1 | AC2: 379.1 | AD2: 342.6 | AE2: 178 | AF2: 1 | AG2: 1 | AH2: N
A3: 2 | B3: Saquon Barkley | C3: NYG | D3: RB | E3: 21 | F3: 16 | G3: 16 | H3: 0 | I3: 0 | J3: 0 | K3: 0 | L3: 0 | M3: 261 | N3: 1307 | O3: 5.01 | P3: 11 | Q3: 121 | R3: 91 | S3: 721 | T3: 7.92 | U3: 4 | V3: 0 | W3: 0 | X3: 15 | Y3: 1 | Z3: 0 | AA3: 295 | AB3: 385.8 | AC3: 391.8 | AD3: 340.3 | AE3: 159 | AF3: 2 | AG3: 2 | AH3: N
A4: 3 | B4: Christian McCaffrey | C4: CAR | D4: RB | E4: 22 | F4: 16 | G4: 16 | H4: 1 | I4: 1 | J4: 50 | K4: 1 | L4: 0 | M4: 219 | N4: 1098 | O4: 5.01 | P4: 7 | Q4: 124 | R4: 107 | S4: 867 | T4: 8.1 | U4: 6 | V4: 4 | W4: 1 | X4: 13 | Y4: 0 | Z4: 0 | AA4: 279 | AB4: 385.5 | AC4: 392.5 | AD4: 332 | AE4: 143 | AF4: 3 | AG4: 3 | AH4: N
A5: 4 | B5: Alvin Kamara | C5: NOR | D5: RB | E5: 23 | F5: 15 | G5: 13 | H5: 0 | I5: 0 | J5: 0 | K5: 0 | L5: 0 | M5: 194 | N5: 883 | O5: 4.55 | P5: 14 | Q5: 105 | R5: 81 | S5: 709 | T5: 8.75 | U5: 4 | V5: 1 | W5: 0 | X5: 18 | Y5: 3 | Z5: 0 | AA5: 273 | AB5: 354.2 | AC5: 360.2 | AD5: 313.7 | AE5: 138 | AF5: 4 | AG5: 4 | AH5: N
A6: 5 | B6: Patrick Mahomes | C6: KAN | D6: QB | E6: 23 | F6: 16 | G6: 16 | H6: 383 | I6: 580 | J6: 5097 | K6: 50 | L6: 12 | M6: 60 | N6: 272 | O6: 4.53 | P6: 2 | Q6: 0 | R6: 0 | S6: 0 | T6: 0 | U6: 0 | V6: 9 | W6: 2 | X6: 2 | Y6: 1 | Z6: 0 | AA6: 417 | AB6: 417.1 | AC6: 437.1 | AD6: 429.1 | AE6: 134 | AF6: 1 | AG6: 5 | AH6: N
A7: 6 | B7: Tyreek Hill | C7: KAN | D7: WR | E7: 24 | F7: 16 | G7: 16 | H7: 0 | I7: 0 | J7: 0 | K7: 0 | L7: 0 | M7: 22 | N7: 151 | O7: 6.86 | P7: 1 | Q7: 137 | R7: 87 | S7: 1479 | T7: 17 | U7: 12 | V7: 0 | W7: 0 | X7: 14 | Y7: 0 | Z7: 0 | AA7: 247 | AB7: 334 | AC7: 340 | AD7: 290.5 | AE7: 131 | AF7: 1 | AG7: 6 | AH7: N
A8: 7 | B8: Ezekiel Elliott | C8: DAL | D8: RB | E8: 23 | F8: 15 | G8: 15 | H8: 0 | I8: 0 | J8: 0 | K8: 0 | L8: 0 | M8: 304 | N8: 1434 | O8: 4.72 | P8: 6 | Q8: 95 | R8: 77 | S8: 567 | T8: 7.36 | U8: 3 | V8: 6 | W8: 1 | X8: 9 | Y8: 0 | Z8: 0 | AA8: 252 | AB8: 329.1 | AC8: 336.1 | AD8: 290.6 | AE8: 117 | AF8: 5 | AG8: 7 | AH8: N
A9: 8 | B9: Travis Kelce | C9: KAN | D9: TE | E9: 29 | F9: 16 | G9: 16 | H9: 0 | I9: 0 | J9: 0 | K9: 0 | L9: 0 | M9: 0 | N9: 0 | O9: 0 | P9: 0 | Q9: 150 | R9: 103 | S9: 1336 | T9: 12.97 | U9: 10 | V9: 2 | W9: 1 | X9: 10 | Y9: 0 | Z9: 0 | AA9: 192 | AB9: 294.6 | AC9: 298.6 | AD9: 243.1 | AE9: 109 | AF9: 1 | AG9: 8 | AH9: N
A10: 9 | B10: Antonio Brown | C10: PIT | D10: WR | E10: 30 | F10: 15 | G10: 15 | H10: 0 | I10: 1 | J10: 0 | K10: 0 | L10: 0 | M10: 0 | N10: 0 | O10: 0 | P10: 0 | Q10: 168 | R10: 104 | S10: 1297 | T10: 12.47 | U10: 15 | V10: 0 | W10: 0 | X10: 15 | Y10: 0 | Z10: 0 | AA10: 220 | AB10: 323.7 | AC10: 326.7 | AD10: 271.7 | AE10: 103 | AF10: 2 | AG10: 9 | AH10: N
A11: 10 | B11: Davante Adams | C11: GNB | D11: WR | E11: 26 | F11: 15 | G11: 15 | H11: 0 | I11: 0 | J11: 0 | K11: 0 | L11: 0 | M11: 0 | N11: 0 | O11: 0 | P11: 0 | Q11: 169 | R11: 111 | S11: 1386 | T11: 12.49 | U11: 13 | V11: 0 | W11: 0 | X11: 13 | Y11: 1 | Z11: 0 | AA11: 219 | AB11: 329.6 | AC11: 332.6 | AD11: 274.1 | AE11: 102 | AF11: 3 | AG11: 10 | AH11: N
A12: 11 | B12: DeAndre Hopkins | C12: HOU | D12: WR | E12: 26 | F12: 16 | G12: 16 | H12: 0 | I12: 1 | J12: 0 | K12: 0 | L12: 0 | M12: 1 | N12: -7 | O12: -7 | P12: 0 | Q12: 163 | R12: 115 | S12: 1572 | T12: 13.67 | U12: 11 | V12: 2 | W12: 2 | X12: 11 | Y12: 0 | Z12: 0 | AA12: 219 | AB12: 333.5 | AC12: 338.5 | AD12: 276 | AE12: 102 | AF12: 4 | AG12: 11 | AH12: N
A13: 12 | B13: Julio Jones | C13: ATL | D13: WR | E13: 29 | F13: 16 | G13: 16 | H13: 0 | I13: 0 | J13: 0 | K13: 0 | L13: 0 | M13: 2 | N13: 12 | O13: 6 | P13: 0 | Q13: 170 | R13: 113 | S13: 1677 | T13: 14.84 | U13: 8 | V13: 2 | W13: 2 | X13: 8 | Y13: 0 | Z13: 0 | AA13: 213 | AB13: 325.9 | AC13: 330.9 | AD13: 269.4 | AE13: 97 | AF13: 5 | AG13: 12 | AH13: N
... A73: 72 | B73: Rob Gronkowski | C73: NWE | D73: TE | E73: 29 | F73: 13 | G73: 11 | H73: 0 | I73: 0 | J73: 0 | K73: 0 | L73: 0 | M73: 0 | N73: 0 | O73: 0 | P73: 0 | Q73: 72 | R73: 47 | S73: 682 | T73: 14.51 | U73: 3 | V73: 1 | W73: 1 | X73: 3 | Y73: 0 | Z73: 0 | AA73: 84 | AB73: 131.2 | AC73: 135.2 | AD73: 107.7 | AE73: 1 | AF73: 11 | AG73: 72 | AH73: N
A74: 73 | B74: Larry Fitzgerald | C74: ARI | D74: WR | E74: 35 | F74: 16 | G74: 16 | H74: 1 | I74: 1 | J74: 32 | K74: 1 | L74: 0 | M74: 0 | N74: 0 | O74: 0 | P74: 0 | Q74: 112 | R74: 69 | S74: 734 | T74: 10.64 | U74: 6 | V74: 0 | W74: 0 | X74: 6 | Y74: 1 | Z74: 0 | AA74: 117 | AB74: 185.7 | AC74: 188.7 | AD74: 151.2 | AF74: 28 | AG74: 73 | AH74: N
A75: 74 | B75: Sterling Shepard | C75: NYG | D75: WR | E75: 25 | F75: 16 | G75: 16 | H75: 0 | I75: 0 | J75: 0 | K75: 0 | L75: 0 | M75: 3 | N75: 33 | O75: 11 | P75: 0 | Q75: 107 | R75: 66 | S75: 872 | T75: 13.21 | U75: 4 | V75: 1 | W75: 0 | X75: 4 | Y75: 1 | Z75: 0 | AA75: 117 | AB75: 182.5 | AC75: 185.5 | AD75: 149.5 | AF75: 29 | AG75: 74 | AH75: N
A76: 75 | B76: Mohamed Sanu | C76: ATL | D76: WR | E76: 29 | F76: 16 | G76: 16 | H76: 1 | I76: 2 | J76: 5 | K76: 1 | L76: 0 | M76: 7 | N76: 44 | O76: 6.29 | P76: 0 | Q76: 94 | R76: 66 | S76: 838 | T76: 12.7 | U76: 4 | V76: 2 | W76: 1 | X76: 4 | Y76: 1 | Z76: 0 | AA76: 116 | AB76: 182.4 | AC76: 186.4 | AD76: 149.4 | AF76: 30 | AG76: 75 | AH76: N
A77: 76 | B77: Matt Breida | C77: SFO | D77: RB | E77: 23 | F77: 14 | G77: 13 | H77: 0 | I77: 0 | J77: 0 | K77: 0 | L77: 0 | M77: 153 | N77: 814 | O77: 5.32 | P77: 3 | Q77: 31 | R77: 27 | S77: 261 | T77: 9.67 | U77: 2 | V77: 1 | W77: 1 | X77: 5 | Y77: 0 | Z77: 0 | AA77: 136 | AB77: 162.5 | AC77: 169.5 | AD77: 149 | AF77: 24 | AG77: 76 | AH77: N
A78: 77 | B78: Shane Smith | C78: NYG | E78: 25 | F78: 2 | G78: 0 | H78: 0 | I78: 0 | J78: 0 | K78: 0 | L78: 0 | M78: 0 | N78: 0 | O78: 0 | P78: 0 | Q78: 0 | R78: 0 | S78: 0 | T78: 0 | U78: 0 | V78: 0 | W78: 0 | X78: 0 | Y78: 0 | Z78: 0 | AF78: 1 | AG78: 77 | AH78: N
A79: 78 | B79: Vance McDonald | C79: PIT | D79: TE | E79: 28 | F79: 15 | G79: 14 | H79: 0 | I79: 0 | J79: 0 | K79: 0 | L79: 0 | M79: 0 | N79: 0 | O79: 0 | P79: 0 | Q79: 72 | R79: 50 | S79: 610 | T79: 12.2 | U79: 4 | V79: 2 | W79: 1 | X79: 4 | Y79: 0 | Z79: 0 | AA79: 83 | AB79: 133 | AC79: 137 | AD79: 108 | AF79: 12 | AG79: 78 | AH79: N
A80: 79 | B80: Cam Newton | C80: CAR | D80: QB | E80: 29 | F80: 14 | G80: 14 | H80: 320 | I80: 471 | J80: 3395 | K80: 24 | L80: 13 | M80: 101 | N80: 488 | O80: 4.83 | P80: 4 | Q80: 0 | R80: 0 | S80: 0 | T80: 0 | U80: 0 | V80: 6 | W80: 0 | X80: 4 | Y80: 0 | Z80: 2 | AA80: 283 | AB80: 282.6 | AC80: 301.6 | AD80: 295.6 | AF80: 12 | AH80: N
A81: 80 | B81: Kirk Cousins | C81: MIN | D81: QB | E81: 30 | F81: 16 | G81: 16 | H81: 425 | I81: 606 | J81: 4298 | K81: 30 | L81: 10 | M81: 44 | N81: 123 | O81: 2.8 | P81: 1 | Q81: 1 | R81: 1 | S81: -1 | T81: -1 | U81: 0 | V81: 9 | W81: 7 | X81: 1 | Y81: 0 | Z81: 3 | AA81: 282 | AB81: 283.1 | AC81: 306.1 | AD81: 292.6 | AF81: 13 | AH81: N
A82: 81 | B82: Tom Brady | C82: NWE | D82: QB | E82: 41 | F82: 16 | G82: 16 | H82: 375 | I82: 570 | J82: 4355 | K82: 29 | L82: 11 | M82: 23 | N82: 35 | O82: 1.52 | P82: 2 | Q82: 1 | R82: 1 | S82: 6 | T82: 6 | U82: 0 | V82: 4 | W82: 2 | X82: 2 | Y82: 0 | Z82: 0 | AA82: 280 | AB82: 281.3 | AC82: 297.3 | AD82: 291.8 | AF82: 14 | AH82: N
A83: 82 | B83: Mitchell Trubisky | C83: CHI | D83: QB | E83: 24 | F83: 14 | G83: 14 | H83: 289 | I83: 434 | J83: 3223 | K83: 24 | L83: 12 | M83: 68 | N83: 421 | O83: 6.19 | P83: 3 | Q83: 0 | R83: 0 | S83: 0 | T83: 0 | U83: 0 | V83: 6 | W83: 3 | X83: 3 | Y83: 0 | Z83: 4 | AA83: 263 | AB83: 263 | AC83: 284 | AD83: 275 | AF83: 15 | AH83: N
A84: 83 | B84: Eli Manning | C84: NYG | D84: QB | E84: 37 | F84: 16 | G84: 16 | H84: 380 | I84: 576 | J84: 4299 | K84: 21 | L84: 11 | M84: 15 | N84: 20 | O84: 1.33 | P84: 1 | Q84: 0 | R84: 0 | S84: 0 | T84: 0 | U84: 0 | V84: 7 | W84: 4 | X84: 1 | Y84: 0 | Z84: 3 | AA84: 240 | AB84: 240 | AC84: 258 | AD84: 251 | AF84: 17 | AH84: N
A85: 84 | B85: Baker Mayfield | C85: CLE | D85: QB | E85: 23 | F85: 14 | G85: 13 | H85: 310 | I85: 486 | J85: 3725 | K85: 27 | L85: 14 | M85: 39 | N85: 131 | O85: 3.36 | P85: 0 | Q85: 1 | R85: 0 | S85: 0 | T85: 0 | U85: 0 | V85: 7 | W85: 3 | X85: 0 | Y85: 1 | Z85: 1 | AA85: 240 | AB85: 240.1 | AC85: 263.1 | AD85: 254.1 | AF85: 16 | AH85: N
A86: 85 | B86: Derek Carr | C86: OAK | D86: QB | E86: 27 | F86: 16 | G86: 16 | H86: 381 | I86: 553 | J86: 4049 | K86: 19 | L86: 10 | M86: 24 | N86: 47 | O86: 1.96 | P86: 1 | Q86: 1 | R86: 1 | S86: -9 | T86: -9 | U86: 0 | V86: 12 | W86: 7 | X86: 1 | Y86: 0 | Z86: 1 | AA86: 216 | AB86: 216.8 | AC86: 236.8 | AD86: 226.3 | AF86: 18 | AH86: N
A87: 86 | B87: Case Keenum | C87: DEN | D87: QB | E87: 30 | F87: 16 | G87: 16 | H87: 365 | I87: 586 | J87: 3890 | K87: 18 | L87: 15 | M87: 26 | N87: 93 | O87: 3.58 | P87: 2 | Q87: 0 | R87: 0 | S87: 0 | T87: 0 | U87: 0 | V87: 11 | W87: 2 | X87: 2 | Y87: 0 | Z87: 0 | AA87: 215 | AB87: 214.9 | AC87: 234.9 | AD87: 229.9 | AF87: 19 | AH87: N
A88: 87 | B88: Matthew Stafford | C88: DET | D88: QB | E88: 30 | F88: 16 | G88: 16 | H88: 367 | I88: 555 | J88: 3777 | K88: 21 | L88: 11 | M88: 25 | N88: 71 | O88: 2.84 | P88: 0 | Q88: 0 | R88: 0 | S88: 0 | T88: 0 | U88: 0 | V88: 6 | W88: 4 | X88: 0 | Y88: 0 | Z88: 0 | AA88: 212 | AB88: 212.2 | AC88: 230.2 | AD88: 223.2 | AF88: 20 | AH88: N
A89: 88 | B89: Josh Allen | C89: BUF | D89: QB | E89: 22 | F89: 12 | G89: 11 | H89: 169 | I89: 320 | J89: 2074 | K89: 10 | L89: 12 | M89: 89 | N89: 631 | O89: 7.09 | P89: 8 | Q89: 1 | R89: 0 | S89: 0 | T89: 0 | U89: 0 | V89: 8 | W89: 2 | X89: 8 | Y89: 0 | Z89: 1 | AA89: 208 | AB89: 208.1 | AC89: 228.1 | AD89: 220.1 | AF89: 21 | AH89: N
A90: 89 | B90: Jameis Winston | C90: TAM | D90: QB | E90: 24 | F90: 11 | G90: 9 | H90: 244 | I90: 378 | J90: 2992 | K90: 19 | L90: 14 | M90: 49 | N90: 281 | O90: 5.73 | P90: 1 | Q90: 0 | R90: 0 | S90: 0 | T90: 0 | U90: 0 | V90: 7 | W90: 3 | X90: 1 | Y90: 0 | Z90: 0 | AA90: 196 | AB90: 195.8 | AC90: 218.8 | AD90: 209.8 | AF90: 22 | AH90: N
A91: 90 | B91: Carson Wentz | C91: PHI | D91: QB | E91: 26 | F91: 11 | G91: 11 | H91: 279 | I91: 401 | J91: 3074 | K91: 21 | L91: 7 | M91: 34 | N91: 93 | O91: 2.74 | P91: 0 | Q91: 1 | R91: 1 | S91: 4 | T91: 4 | U91: 0 | V91: 9 | W91: 6 | X91: 0 | Y91: 0 | Z91: 1 | AA91: 193 | AB91: 193.7 | AC91: 209.7 | AD91: 200.2 | AF91: 23 | AH91: N
... A538: 537 | B538: Tim White | C538: BAL | D538: WR | E538: 24 | F538: 3 | G538: 0 | H538: 0 | I538: 0 | J538: 0 | K538: 0 | L538: 0 | M538: 0 | N538: 0 | O538: 0 | P538: 0 | Q538: 1 | R538: 1 | S538: 14 | T538: 14 | U538: 0 | V538: 1 | W538: 0 | X538: 0 | Y538: 0 | Z538: 0 | AA538: 1 | AB538: 2.4 | AC538: 2.4 | AD538: 1.9 | AF538: 192 | AH538: N
A539: 538 | B539: Saeed Blacknall | C539: OAK | E539: 22 | F539: 1 | G539: 0 | H539: 0 | I539: 0 | J539: 0 | K539: 0 | L539: 0 | M539: 0 | N539: 0 | O539: 0 | P539: 0 | Q539: 0 | R539: 0 | S539: 0 | T539: 0 | U539: 0 | V539: 0 | W539: 0 | X539: 0 | Y539: 0 | Z539: 0 | AF539: 210 | AH539: N
A540: 539 | B540: Daniel Brown | C540: CHI | E540: 26 | F540: 14 | G540: 0 | H540: 0 | I540: 0 | J540: 0 | K540: 0 | L540: 0 | M540: 0 | N540: 0 | O540: 0 | P540: 0 | Q540: 0 | R540: 0 | S540: 0 | T540: 0 | U540: 0 | V540: 0 | W540: 0 | X540: 0 | Y540: 0 | Z540: 0 | AF540: 119 | AH540: N
A541: 540 | B541: Deante Burton | C541: 2TM | E541: 24 | F541: 3 | G541: 0 | H541: 0 | I541: 0 | J541: 0 | K541: 0 | L541: 0 | M541: 0 | N541: 0 | O541: 0 | P541: 0 | Q541: 0 | R541: 0 | S541: 0 | T541: 0 | U541: 0 | V541: 0 | W541: 0 | X541: 0 | Y541: 0 | Z541: 0 | AF541: 211 | AH541: N
A542: 541 | B542: Jehu Chesson | C542: WAS | D542: WR | E542: 25 | F542: 12 | G542: 0 | H542: 0 | I542: 0 | J542: 0 | K542: 0 | L542: 0 | M542: 1 | N542: -4 | O542: -4 | P542: 0 | Q542: 2 | R542: 1 | S542: 7 | T542: 7 | U542: 0 | V542: 0 | W542: 0 | X542: 0 | Y542: 0 | Z542: 0 | AB542: 1.3 | AC542: 1.3 | AD542: 0.8 | AF542: 205 | AH542: N
A543: 542 | B543: Lavon Coleman | C543: GNB | E543: 24 | F543: 1 | G543: 0 | H543: 0 | I543: 0 | J543: 0 | K543: 0 | L543: 0 | M543: 0 | N543: 0 | O543: 0 | P543: 0 | Q543: 0 | R543: 0 | S543: 0 | T543: 0 | U543: 0 | V543: 0 | W543: 0 | X543: 0 | Y543: 0 | Z543: 0 | AF543: 162 | AH543: N
A544: 543 | B544: Stacy Coley | C544: 2TM | E544: 24 | F544: 3 | G544: 0 | H544: 0 | I544: 0 | J544: 0 | K544: 0 | L544: 0 | M544: 0 | N544: 0 | O544: 0 | P544: 0 | Q544: 1 | R544: 0 | S544: 0 | T544: 0 | U544: 0 | V544: 1 | W544: 0 | X544: 0 | Y544: 0 | Z544: 0 | AF544: 212 | AH544: N
A545: 544 | B545: Pharoh Cooper | C545: 2TM | E545: 23 | F545: 7 | G545: 0 | H545: 0 | I545: 0 | J545: 0 | K545: 0 | L545: 0 | M545: 0 | N545: 0 | O545: 0 | P545: 0 | Q545: 1 | R545: 0 | S545: 0 | T545: 0 | U545: 0 | V545: 1 | W545: 0 | X545: 0 | Y545: 0 | Z545: 0 | AF545: 213 | AH545: N
A546: 545 | B546: Jerome Cunningham | C546: DET | E546: 27 | F546: 3 | G546: 0 | H546: 0 | I546: 0 | J546: 0 | K546: 0 | L546: 0 | M546: 0 | N546: 0 | O546: 0 | P546: 0 | Q546: 1 | R546: 0 | S546: 0 | T546: 0 | U546: 0 | V546: 0 | W546: 0 | X546: 0 | Y546: 0 | Z546: 0 | AF546: 124 | AH546: N
A547: 546 | B547: Darrell Daniels | C547: 2TM | E547: 24 | F547: 11 | G547: 3 | H547: 0 | I547: 0 | J547: 0 | K547: 0 | L547: 0 | M547: 0 | N547: 0 | O547: 0 | P547: 0 | Q547: 2 | R547: 0 | S547: 0 | T547: 0 | U547: 0 | V547: 0 | W547: 0 | X547: 0 | Y547: 0 | Z547: 0 | AF547: 132 | AH547: N
A548: 547 | B548: Geremy Davis | C548: LAC | E548: 26 | F548: 14 | G548: 0 | H548: 0 | I548: 0 | J548: 0 | K548: 0 | L548: 0 | M548: 0 | N548: 0 | O548: 0 | P548: 0 | Q548: 1 | R548: 0 | S548: 0 | T548: 0 | U548: 0 | V548: 0 | W548: 0 | X548: 0 | Y548: 0 | Z548: 0 | AF548: 233 | AH548: N
A549: 548 | B549: Trevor Davis | C549: GNB | E549: 25 | F549: 2 | G549: 0 | H549: 0 | I549: 0 | J549: 0 | K549: 0 | L549: 0 | M549: 0 | N549: 0 | O549: 0 | P549: 0 | Q549: 0 | R549: 0 | S549: 0 | T549: 0 | U549: 0 | V549: 0 | W549: 0 | X549: 0 | Y549: 0 | Z549: 0 | AF549: 218 | AH549: N
A550: 549 | B550: Dalyn Dawkins | C550: TEN | E550: 24 | F550: 2 | G550: 0 | H550: 0 | I550: 0 | J550: 0 | K550: 0 | L550: 0 | M550: 0 | N550: 0 | O550: 0 | P550: 0 | Q550: 0 | R550: 0 | S550: 0 | T550: 0 | U550: 0 | V550: 0 | W550: 0 | X550: 0 | Y550: 0 | Z550: 0 | AF550: 154 | AH550: N
A551: 550 | B551: Matthew Dayes | C551: SFO | E551: 24 | F551: 7 | G551: 0 | H551: 0 | I551: 0 | J551: 0 | K551: 0 | L551: 0 | M551: 0 | N551: 0 | O551: 0 | P551: 0 | Q551: 0 | R551: 0 | S551: 0 | T551: 0 | U551: 0 | V551: 0 | W551: 0 | X551: 0 | Y551: 0 | Z551: 0 | AF551: 158 | AH551: N
A552: 551 | B552: Garrett Dickerson | C552: NYG | E552: 23 | F552: 4 | G552: 0 | H552: 0 | I552: 0 | J552: 0 | K552: 0 | L552: 0 | M552: 0 | N552: 0 | O552: 0 | P552: 0 | Q552: 0 | R552: 0 | S552: 0 | T552: 0 | U552: 0 | V552: 0 | W552: 0 | X552: 0 | Y552: 0 | Z552: 0 | AF552: 125 | AH552: N
A553: 552 | B553: Quinton Dunbar | C553: WAS | E553: 26 | F553: 7 | G553: 6 | H553: 0 | I553: 0 | J553: 0 | K553: 0 | L553: 0 | M553: 0 | N553: 0 | O553: 0 | P553: 0 | Q553: 0 | R553: 0 | S553: 0 | T553: 0 | U553: 0 | V553: 0 | W553: 0 | X553: 0 | Y553: 0 | Z553: 0 | AF553: 214 | AH553: N
A554: 553 | B554: Steven Dunbar | C554: SFO | E554: 23 | F554: 1 | G554: 0 | H554: 0 | I554: 0 | J554: 0 | K554: 0 | L554: 0 | M554: 0 | N554: 0 | O554: 0 | P554: 0 | Q554: 0 | R554: 0 | S554: 0 | T554: 0 | U554: 0 | V554: 0 | W554: 0 | X554: 0 | Y554: 0 | Z554: 0 | AF554: 223 | AH554: N
... A567: 566 | B567: Temarrick Hemingway | C567: DEN | E567: 25 | F567: 5 | G567: 0 | H567: 0 | I567: 0 | J567: 0 | K567: 0 | L567: 0 | M567: 0 | N567: 0 | O567: 0 | P567: 0 | Q567: 0 | R567: 0 | S567: 0 | T567: 0 | U567: 0 | V567: 0 | W567: 0 | X567: 0 | Y567: 0 | Z567: 0 | AF567: 122 | AH567: N
A568: 567 | B568: De'Angelo Henderson | C568: NYJ | D568: RB | E568: 26 | F568: 3 | G568: 0 | H568: 0 | I568: 0 | J568: 0 | K568: 0 | L568: 0 | M568: 2 | N568: 19 | O568: 9.5 | P568: 0 | Q568: 0 | R568: 0 | S568: 0 | T568: 0 | U568: 0 | V568: 1 | W568: 1 | X568: 0 | Y568: 0 | Z568: 0 | AB568: -0.1 | AC568: 0.9 | AD568: -0.1 | AF568: 165 | AH568: N
A569: 568 | B569: Quadree Henderson | C569: NYG | E569: 22 | F569: 5 | G569: 0 | H569: 0 | I569: 0 | J569: 0 | K569: 0 | L569: 0 | M569: 0 | N569: 0 | O569: 0 | P569: 0 | Q569: 0 | R569: 0 | S569: 0 | T569: 0 | U569: 0 | V569: 0 | W569: 0 | X569: 0 | Y569: 0 | Z569: 0 | AF569: 228 | AH569: N
A570: 569 | B570: Hunter Henry | C570: LAC | E570: 24 | F570: 0 | G570: 0 | H570: 0 | I570: 0 | J570: 0 | K570: 0 | L570: 0 | M570: 0 | N570: 0 | O570: 0 | P570: 0 | Q570: 0 | R570: 0 | S570: 0 | T570: 0 | U570: 0 | V570: 0 | W570: 0 | X570: 0 | Y570: 0 | Z570: 0 | AF570: 131 | AH570: N
A571: 570 | B571: Darrius Heyward-Bey | C571: PIT | D571: WR | E571: 31 | F571: 14 | G571: 2 | H571: 0 | I571: 0 | J571: 0 | K571: 0 | L571: 0 | M571: 1 | N571: -7 | O571: -7 | P571: 0 | Q571: 2 | R571: 1 | S571: 9 | T571: 9 | U571: 0 | V571: 0 | W571: 0 | X571: 0 | Y571: 0 | Z571: 0 | AB571: 1.2 | AC571: 1.2 | AD571: 0.7 | AF571: 206 | AH571: N
A572: 571 | B572: Gabe Holmes | C572: ARI | E572: 27 | F572: 8 | G572: 4 | H572: 0 | I572: 0 | J572: 0 | K572: 0 | L572: 0 | M572: 0 | N572: 0 | O572: 0 | P572: 0 | Q572: 0 | R572: 0 | S572: 0 | T572: 0 | U572: 0 | V572: 0 | W572: 0 | X572: 0 | Y572: 0 | Z572: 0 | AF572: 123 | AH572: N
A573: 572 | B573: Johnny Holton | C573: OAK | E573: 27 | F573: 1 | G573: 0 | H573: 0 | I573: 0 | J573: 0 | K573: 0 | L573: 0 | M573: 0 | N573: 0 | O573: 0 | P573: 0 | Q573: 1 | R573: 0 | S573: 0 | T573: 0 | U573: 0 | V573: 0 | W573: 0 | X573: 0 | Y573: 0 | Z573: 0 | AF573: 236 | AH573: N
A574: 573 | B574: Buddy Howell | C574: HOU | E574: 22 | F574: 15 | G574: 0 | H574: 0 | I574: 0 | J574: 0 | K574: 0 | L574: 0 | M574: 0 | N574: 0 | O574: 0 | P574: 0 | Q574: 0 | R574: 0 | S574: 0 | T574: 0 | U574: 0 | V574: 0 | W574: 0 | X574: 0 | Y574: 0 | Z574: 0 | AF574: 161 | AH574: N
A575: 574 | B575: Chad Kelly | C575: DEN | D575: QB | E575: 24 | F575: 1 | G575: 0 | H575: 0 | I575: 0 | J575: 0 | K575: 0 | L575: 0 | M575: 1 | N575: -1 | O575: -1 | P575: 0 | Q575: 0 | R575: 0 | S575: 0 | T575: 0 | U575: 0 | V575: 0 | W575: 0 | X575: 0 | Y575: 0 | Z575: 0 | AB575: -0.1 | AC575: -0.1 | AD575: -0.1 | AF575: 69 | AH575: N
A576: 575 | B576: Ben Koyack | C576: JAX | E576: 25 | F576: 7 | G576: 2 | H576: 0 | I576: 0 | J576: 0 | K576: 0 | L576: 0 | M576: 0 | N576: 0 | O576: 0 | P576: 0 | Q576: 0 | R576: 0 | S576: 0 | T576: 0 | U576: 0 | V576: 0 | W576: 0 | X576: 0 | Y576: 0 | Z576: 0 | AF576: 127 | AH576: N
A577: 576 | B577: Chris Lacy | C577: DET | E577: 22 | F577: 1 | G577: 0 | H577: 0 | I577: 0 | J577: 0 | K577: 0 | L577: 0 | M577: 0 | N577: 0 | O577: 0 | P577: 0 | Q577: 1 | R577: 0 | S577: 0 | T577: 0 | U577: 0 | V577: 0 | W577: 0 | X577: 0 | Y577: 0 | Z577: 0 | AF577: 225 | AH577: N
A578: 577 | B578: Lance Lenoir | C578: DAL | E578: 23 | F578: 7 | G578: 0 | H578: 0 | I578: 0 | J578: 0 | K578: 0 | L578: 0 | M578: 0 | N578: 0 | O578: 0 | P578: 0 | Q578: 0 | R578: 0 | S578: 0 | T578: 0 | U578: 0 | V578: 0 | W578: 0 | X578: 0 | Y578: 0 | Z578: 0 | AF578: 219 | AH578: N
A579: 578 | B579: Tony Lippett | C579: NYG | E579: 26 | F579: 3 | G579: 0 | H579: 0 | I579: 0 | J579: 0 | K579: 0 | L579: 0 | M579: 0 | N579: 0 | O579: 0 | P579: 0 | Q579: 0 | R579: 0 | S579: 0 | T579: 0 | U579: 0 | V579: 0 | W579: 0 | X579: 0 | Y579: 0 | Z579: 0 | AF579: 216 | AH579: N
A580: 579 | B580: Sean Mannion | C580: LAR | D580: QB | E580: 26 | F580: 3 | G580: 0 | H580: 2 | I580: 3 | J580: 23 | K580: 0 | L580: 0 | M580: 7 | N580: -9 | O580: -1.29 | P580: 0 | Q580: 0 | R580: 0 | S580: 0 | T580: 0 | U580: 0 | V580: 0 | W580: 0 | X580: 0 | Y580: 0 | Z580: 0 | AF580: 67 | AH580: N
A581: 580 | B581: Bradley Marquez | C581: DET | E581: 26 | F581: 1 | G581: 0 | H581: 0 | I581: 0 | J581: 0 | K581: 0 | L581: 0 | M581: 0 | N581: 0 | O581: 0 | P581: 0 | Q581: 0 | R581: 0 | S581: 0 | T581: 0 | U581: 0 | V581: 0 | W581: 0 | X581: 0 | Y581: 0 | Z581: 0 | AF581: 217 | AH581: N
A582: 581 | B582: Freddie Martino | C582: TAM | E582: 27 | F582: 4 | G582: 0 | H582: 0 | I582: 0 | J582: 0 | K582: 0 | L582: 0 | M582: 0 | N582: 0 | O582: 0 | P582: 0 | Q582: 1 | R582: 0 | S582: 0 | T582: 0 | U582: 0 | V582: 0 | W582: 0 | X582: 0 | Y582: 0 | Z582: 0 | AF582: 238 | AH582: N
A583: 582 | B583: A.J. McCarron | C583: OAK | D583: QB | E583: 28 | F583: 2 | G583: 0 | H583: 1 | I583: 3 | J583: 8 | K583: 0 | L583: 0 | M583: 3 | N583: -2 | O583: -0.67 | P583: 0 | Q583: 0 | R583: 0 | S583: 0 | T583: 0 | U583: 0 | V583: 1 | W583: 0 | X583: 0 | Y583: 0 | Z583: 0 | AB583: 0.1 | AC583: 0.1 | AD583: 0.1 | AF583: 65 | AH583: N
A584: 583 | B584: Max McCaffrey | C584: SFO | E584: 24 | F584: 1 | G584: 0 | H584: 0 | I584: 0 | J584: 0 | K584: 0 | L584: 0 | M584: 0 | N584: 0 | O584: 0 | P584: 0 | Q584: 0 | R584: 0 | S584: 0 | T584: 0 | U584: 0 | V584: 0 | W584: 0 | X584: 0 | Y584: 0 | Z584: 0 | AF584: 226 | AH584: N
A585: 584 | B585: Tanner McEvoy | C585: MIA | E585: 25 | F585: 2 | G585: 0 | H585: 0 | I585: 0 | J585: 0 | K585: 0 | L585: 0 | M585: 0 | N585: 0 | O585: 0 | P585: 0 | Q585: 0 | R585: 0 | S585: 0 | T585: 0 | U585: 0 | V585: 0 | W585: 0 | X585: 0 | Y585: 0 | Z585: 0 | AF585: 229 | AH585: N
A586: 585 | B586: Jaydon Mickens | C586: JAX | E586: 24 | F586: 6 | G586: 0 | H586: 0 | I586: 0 | J586: 0 | K586: 0 | L586: 0 | M586: 0 | N586: 0 | O586: 0 | P586: 0 | Q586: 0 | R586: 0 | S586: 0 | T586: 0 | U586: 0 | V586: 1 | W586: 0 | X586: 0 | Y586: 0 | Z586: 0 | AF586: 230 | AH586: N
A587: 586 | B587: Steven Mitchell | C587: HOU | E587: 24 | F587: 1 | G587: 0 | H587: 0 | I587: 0 | J587: 0 | K587: 0 | L587: 0 | M587: 0 | N587: 0 | O587: 0 | P587: 0 | Q587: 0 | R587: 0 | S587: 0 | T587: 0 | U587: 0 | V587: 0 | W587: 0 | X587: 0 | Y587: 0 | Z587: 0 | AF587: 207 | AH587: N
A588: 587 | B588: Dare Ogunbowale | C588: TAM | E588: 24 | F588: 2 | G588: 0 | H588: 0 | I588: 0 | J588: 0 | K588: 0 | L588: 0 | M588: 0 | N588: 0 | O588: 0 | P588: 0 | Q588: 0 | R588: 0 | S588: 0 | T588: 0 | U588: 0 | V588: 0 | W588: 0 | X588: 0 | Y588: 0 | Z588: 0 | AF588: 163 | AH588: N
A589: 588 | B589: Senorise Perry | C589: MIA | E589: 27 | F589: 16 | G589: 0 | H589: 0 | I589: 0 | J589: 0 | K589: 0 | L589: 0 | M589: 0 | N589: 0 | O589: 0 | P589: 0 | Q589: 0 | R589: 0 | S589: 0 | T589: 0 | U589: 0 | V589: 0 | W589: 0 | X589: 0 | Y589: 0 | Z589: 0 | AF589: 156 | AH589: N
A590: 589 | B590: Thomas Rawls | C590: CIN | E590: 25 | F590: 1 | G590: 0 | H590: 0 | I590: 0 | J590: 0 | K590: 0 | L590: 0 | M590: 0 | N590: 0 | O590: 0 | P590: 0 | Q590: 0 | R590: 0 | S590: 0 | T590: 0 | U590: 0 | V590: 0 | W590: 0 | X590: 0 | Y590: 0 | Z590: 0 | AF590: 159 | AH590: N
A591: 590 | B591: Keenan Reynolds | C591: SEA | E591: 25 | F591: 2 | G591: 0 | H591: 0 | I591: 0 | J591: 0 | K591: 0 | L591: 0 | M591: 0 | N591: 0 | O591: 0 | P591: 0 | Q591: 0 | R591: 0 | S591: 0 | T591: 0 | U591: 0 | V591: 0 | W591: 0 | X591: 0 | Y591: 0 | Z591: 0 | AF591: 164 | AH591: N
A592: 591 | B592: Cooper Rush | C592: DAL | E592: 25 | F592: 1 | G592: 0 | H592: 0 | I592: 0 | J592: 0 | K592: 0 | L592: 0 | M592: 0 | N592: 0 | O592: 0 | P592: 0 | Q592: 0 | R592: 0 | S592: 0 | T592: 0 | U592: 0 | V592: 0 | W592: 0 | X592: 0 | Y592: 0 | Z592: 0 | AF592: 68 | AH592: N
A593: 592 | B593: Alonzo Russell | C593: NYG | E593: 26 | F593: 1 | G593: 0 | H593: 0 | I593: 0 | J593: 0 | K593: 0 | L593: 0 | M593: 0 | N593: 0 | O593: 0 | P593: 0 | Q593: 0 | R593: 0 | S593: 0 | T593: 0 | U593: 0 | V593: 0 | W593: 0 | X593: 0 | Y593: 0 | Z593: 0 | AF593: 208 | AH593: N
A594: 593 | B594: Mark Sanchez | C594: WAS | D594: QB | E594: 32 | F594: 2 | G594: 1 | H594: 19 | I594: 35 | J594: 138 | K594: 0 | L594: 3 | M594: 1 | N594: 8 | O594: 8 | P594: 0 | Q594: 0 | R594: 0 | S594: 0 | T594: 0 | U594: 0 | V594: 1 | W594: 0 | X594: 0 | Y594: 0 | Z594: 0 | AB594: 0.3 | AC594: 3.3 | AD594: 3.3 | AF594: 64 | AH594: N
A595: 594 | B595: Matt Schaub | C595: ATL | D595: QB | E595: 37 | F595: 3 | G595: 0 | H595: 5 | I595: 7 | J595: 20 | K595: 0 | L595: 0 | M595: 1 | N595: 0 | O595: 0 | P595: 0 | Q595: 1 | R595: 1 | S595: -7 | T595: -7 | U595: 0 | V595: 1 | W595: 0 | X595: 0 | Y595: 0 | Z595: 0 | AB595: 1.1 | AC595: 1.1 | AD595: 0.6 | AF595: 66 | AH595: N
A596: 595 | B596: Mason Schreck | C596: CIN | E596: 25 | F596: 6 | G596: 0 | H596: 0 | I596: 0 | J596: 0 | K596: 0 | L596: 0 | M596: 0 | N596: 0 | O596: 0 | P596: 0 | Q596: 0 | R596: 0 | S596: 0 | T596: 0 | U596: 0 | V596: 0 | W596: 0 | X596: 0 | Y596: 0 | Z596: 0 | AF596: 129 | AH596: N
A597: 596 | B597: Boston Scott | C597: PHI | E597: 23 | F597: 2 | G597: 0 | H597: 0 | I597: 0 | J597: 0 | K597: 0 | L597: 0 | M597: 0 | N597: 0 | O597: 0 | P597: 0 | Q597: 0 | R597: 0 | S597: 0 | T597: 0 | U597: 0 | V597: 0 | W597: 0 | X597: 0 | Y597: 0 | Z597: 0 | AF597: 160 | AH597: N
A598: 597 | B598: Da'Mari Scott | C598: BUF | E598: 23 | F598: 3 | G598: 0 | H598: 0 | I598: 0 | J598: 0 | K598: 0 | L598: 0 | M598: 0 | N598: 0 | O598: 0 | P598: 0 | Q598: 0 | R598: 0 | S598: 0 | T598: 0 | U598: 0 | V598: 0 | W598: 0 | X598: 0 | Y598: 0 | Z598: 0 | AF598: 239 | AH598: N
A599: 598 | B599: Cam Sims | C599: WAS | E599: 22 | F599: 1 | G599: 0 | H599: 0 | I599: 0 | J599: 0 | K599: 0 | L599: 0 | M599: 0 | N599: 0 | O599: 0 | P599: 0 | Q599: 0 | R599: 0 | S599: 0 | T599: 0 | U599: 0 | V599: 0 | W599: 0 | X599: 0 | Y599: 0 | Z599: 0 | AF599: 220 | AH599: N
A600: 599 | B600: Matthew Slater | C600: NWE | E600: 33 | F600: 16 | G600: 0 | H600: 0 | I600: 0 | J600: 0 | K600: 0 | L600: 0 | M600: 0 | N600: 0 | O600: 0 | P600: 0 | Q600: 0 | R600: 0 | S600: 0 | T600: 0 | U600: 0 | V600: 0 | W600: 0 | X600: 0 | Y600: 0 | Z600: 0 | AF600: 232 | AH600: N
A601: 600 | B601: Nate Solder | C601: NYG | E601: 30 | F601: 16 | G601: 16 | H601: 0 | I601: 0 | J601: 0 | K601: 0 | L601: 0 | M601: 0 | N601: 0 | O601: 0 | P601: 0 | Q601: 0 | R601: 0 | S601: 0 | T601: 0 | U601: 0 | V601: 0 | W601: 0 | X601: 0 | Y601: 0 | Z601: 0 | AF601: 126 | AH601: N
A602: 601 | B602: Brandon Tate | C602: NOR | E602: 31 | F602: 1 | G602: 0 | H602: 0 | I602: 0 | J602: 0 | K602: 0 | L602: 0 | M602: 0 | N602: 0 | O602: 0 | P602: 0 | Q602: 0 | R602: 0 | S602: 0 | T602: 0 | U602: 0 | V602: 1 | W602: 0 | X602: 0 | Y602: 0 | Z602: 0 | AF602: 231 | AH602: N
A603: 602 | B603: Mike Thomas | C603: LAR | E603: 24 | F603: 1 | G603: 0 | H603: 0 | I603: 0 | J603: 0 | K603: 0 | L603: 0 | M603: 0 | N603: 0 | O603: 0 | P603: 0 | Q603: 0 | R603: 0 | S603: 0 | T603: 0 | U603: 0 | V603: 0 | W603: 0 | X603: 0 | Y603: 0 | Z603: 0 | AF603: 222 | AH603: N
A604: 603 | B604: Danny Vitale | C604: GNB | D604: RB | E604: 25 | F604: 5 | G604: 0 | H604: 0 | I604: 0 | J604: 0 | K604: 0 | L604: 0 | M604: 0 | N604: 0 | O604: 0 | P604: 0 | Q604: 2 | R604: 1 | S604: 2 | T604: 2 | U604: 0 | V604: 0 | W604: 0 | X604: 0 | Y604: 0 | Z604: 0 | AB604: 1.2 | AC604: 1.2 | AD604: 0.7 | AF604: 152 | AH604: N
A605: 604 | B605: Clive Walford | C605: NYJ | E605: 27 | F605: 1 | G605: 1 | H605: 0 | I605: 0 | J605: 0 | K605: 0 | L605: 0 | M605: 0 | N605: 0 | O605: 0 | P605: 0 | Q605: 0 | R605: 0 | S605: 0 | T605: 0 | U605: 0 | V605: 0 | W605: 0 | X605: 0 | Y605: 0 | Z605: 0 | AF605: 130 | AH605: N
A606: 605 | B606: Mike Wallace | C606: PHI | E606: 32 | F606: 2 | G606: 2 | H606: 0 | I606: 0 | J606: 0 | K606: 0 | L606: 0 | M606: 0 | N606: 0 | O606: 0 | P606: 0 | Q606: 3 | R606: 0 | S606: 0 | T606: 0 | U606: 0 | V606: 0 | W606: 0 | X606: 0 | Y606: 0 | Z606: 0 | AF606: 224 | AH606: N
A607: 606 | B607: Brandon Weeden | C607: HOU | D607: QB | E607: 35 | F607: 1 | G607: 0 | H607: 0 | I607: 0 | J607: 0 | K607: 0 | L607: 0 | M607: 1 | N607: -1 | O607: -1 | P607: 0 | Q607: 0 | R607: 0 | S607: 0 | T607: 0 | U607: 0 | V607: 0 | W607: 0 | X607: 0 | Y607: 0 | Z607: 0 | AB607: -0.1 | AC607: -0.1 | AD607: -0.1 | AF607: 70 | AH607: N
A608: 607 | B608: Markus Wheaton | C608: PHI | E608: 27 | F608: 1 | G608: 0 | H608: 0 | I608: 0 | J608: 0 | K608: 0 | L608: 0 | M608: 0 | N608: 0 | O608: 0 | P608: 0 | Q608: 0 | R608: 0 | S608: 0 | T608: 0 | U608: 0 | V608: 0 | W608: 0 | X608: 0 | Y608: 0 | Z608: 0 | AF608: 240 | AH608: N
A609: 608 | B609: Cole Wick | C609: SFO | E609: 25 | F609: 5 | G609: 0 | H609: 0 | I609: 0 | J609: 0 | K609: 0 | L609: 0 | M609: 0 | N609: 0 | O609: 0 | P609: 0 | Q609: 1 | R609: 0 | S609: 0 | T609: 0 | U609: 0 | V609: 0 | W609: 0 | X609: 0 | Y609: 0 | Z609: 0 | AF609: 121 | AH609: N
A610: 609 | B610: Jonathan Williams | C610: NOR | D610: RB | E610: 24 | F610: 3 | G610: 0 | H610: 0 | I610: 0 | J610: 0 | K610: 0 | L610: 0 | M610: 3 | N610: 0 | O610: 0 | P610: 0 | Q610: 1 | R610: 1 | S610: 1 | T610: 1 | U610: 0 | V610: 0 | W610: 0 | X610: 0 | Y610: 0 | Z610: 0 | AB610: 1.1 | AC610: 1.1 | AD610: 0.6 | AF610: 153 | AH610: N
A611: 610 | B611: Deon Yelder | C611: KAN | E611: 23 | F611: 3 | G611: 0 | H611: 0 | I611: 0 | J611: 0 | K611: 0 | L611: 0 | M611: 0 | N611: 0 | O611: 0 | P611: 0 | Q611: 0 | R611: 0 | S611: 0 | T611: 0 | U611: 0 | V611: 0 | W611: 0 | X611: 0 | Y611: 0 | Z611: 0 | AF611: 135 | AH611: N
A612: 611 | B612: Jacoby Brissett | C612: IND | D612: QB | E612: 26 | F612: 4 | G612: 0 | H612: 2 | I612: 4 | J612: 2 | K612: 0 | L612: 0 | M612: 7 | N612: -7 | O612: -1 | P612: 0 | Q612: 0 | R612: 0 | S612: 0 | T612: 0 | U612: 0 | V612: 0 | W612: 0 | X612: 0 | Y612: 0 | Z612: 0 | AA612: -1 | AB612: -0.6 | AC612: -0.6 | AD612: -0.6 | AF612: 72 | AH612: N
A613: 612 | B613: Brian Hoyer | C613: NWE | D613: QB | E613: 33 | F613: 5 | G613: 0 | H613: 1 | I613: 2 | J613: 7 | K613: 0 | L613: 0 | M613: 11 | N613: -8 | O613: -0.73 | P613: 0 | Q613: 0 | R613: 0 | S613: 0 | T613: 0 | U613: 0 | V613: 0 | W613: 0 | X613: 0 | Y613: 0 | Z613: 0 | AA613: -1 | AB613: -0.5 | AC613: -0.5 | AD613: -0.5 | AF613: 71 | AH613: N
A614: 613 | B614: J'Mon Moore | C614: GNB | D614: WR | E614: 23 | F614: 12 | G614: 0 | H614: 0 | I614: 0 | J614: 0 | K614: 0 | L614: 0 | M614: 0 | N614: 0 | O614: 0 | P614: 0 | Q614: 3 | R614: 2 | S614: 15 | T614: 7.5 | U614: 0 | V614: 1 | W614: 1 | X614: 0 | Y614: 0 | Z614: 0 | AA614: -1 | AB614: 1.5 | AC614: 2.5 | AD614: 0.5 | AF614: 241 | AH614: N
A615: 614 | B615: Geno Smith | C615: LAC | D615: QB | E615: 28 | F615: 5 | G615: 0 | H615: 1 | I615: 4 | J615: 8 | K615: 0 | L615: 0 | M615: 8 | N615: 2 | O615: 0.25 | P615: 0 | Q615: 0 | R615: 0 | S615: 0 | T615: 0 | U615: 0 | V615: 1 | W615: 1 | X615: 0 | Y615: 0 | Z615: 0 | AA615: -1 | AB615: -1.5 | AC615: -0.5 | AD615: -1.5 | AF615: 73 | AH615: N
A616: 615 | B616: Rod Streater | C616: CLE | D616: WR | E616: 30 | F616: 3 | G616: 0 | H616: 0 | I616: 0 | J616: 0 | K616: 0 | L616: 0 | M616: 1 | N616: -11 | O616: -11 | P616: 0 | Q616: 0 | R616: 0 | S616: 0 | T616: 0 | U616: 0 | V616: 0 | W616: 0 | X616: 0 | Y616: 0 | Z616: 0 | AA616: -1 | AB616: -1.1 | AC616: -1.1 | AD616: -1.1 | AF616: 242 | AH616: N
A617: 616 | B617: Robert Turbin | C617: IND | D617: RB | E617: 29 | F617: 2 | G617: 0 | H617: 0 | I617: 0 | J617: 0 | K617: 0 | L617: 0 | M617: 4 | N617: 10 | O617: 2.5 | P617: 0 | Q617: 2 | R617: 1 | S617: 3 | T617: 3 | U617: 0 | V617: 1 | W617: 1 | X617: 0 | Y617: 0 | Z617: 0 | AA617: -1 | AB617: 0.3 | AC617: 1.3 | AD617: -0.2 | AF617: 166 | AH617: N
...

Sheet 2019 Stats
A1: Rk | B1: Player | C1: Tm | D1: FantPos | E1: Age | F1: Games G | G1: Games GS | H1: Passing Cmp | I1: Passing Att | J1: Passing Yds | K1: Passing TD | L1: Passing Int | M1: Rushing Att | N1: Rushing Yds | O1: Rushing Y/A | P1: Rushing TD | Q1: Receiving Tgt | R1: Receiving Rec | S1: Receiving Yds | T1: Receiving Y/R | U1: Receiving TD | V1: Fumbles Fmb | W1: Fumbles FL | X1: Scoring TD | Y1: Scoring 2PM | Z1: Scoring 2PP | AA1: Fantasy FantPt | AB1: Fantasy PPR | AC1: Fantasy DKPt | AD1: Fantasy FDPt | AE1: Fantasy VBD | AF1: Fantasy PosRank | AG1: Fantasy OvRank | AH1: Custom
A2: 1 | B2: Christian McCaffrey | C2: CAR | D2: RB | E2: 23 | F2: 16 | G2: 16 | H2: 0 | I2: 2 | J2: 0 | K2: 0 | L2: 0 | M2: 287 | N2: 1387 | O2: 4.83 | P2: 15 | Q2: 142 | R2: 116 | S2: 1005 | T2: 8.66 | U2: 4 | V2: 1 | W2: 0 | X2: 19 | Y2: 1 | Z2: 0 | AA2: 355 | AB2: 471.2 | AC2: 477.2 | AD2: 413.2 | AE2: 215 | AF2: 1 | AG2: 1 | AH2: N
A3: 2 | B3: Lamar Jackson | C3: BAL | D3: QB | E3: 22 | F3: 15 | G3: 15 | H3: 265 | I3: 401 | J3: 3127 | K3: 36 | L3: 6 | M3: 176 | N3: 1206 | O3: 6.85 | P3: 7 | Q3: 0 | R3: 0 | S3: 0 | T3: 0 | U3: 0 | V3: 9 | W3: 2 | X3: 7 | Y3: 0 | Z3: 0 | AA3: 416 | AB3: 415.7 | AC3: 429.7 | AD3: 421.7 | AE3: 152 | AF3: 1 | AG3: 2 | AH3: N
A4: 3 | B4: Derrick Henry | C4: TEN | D4: RB | E4: 25 | F4: 15 | G4: 15 | H4: 0 | I4: 0 | J4: 0 | K4: 0 | L4: 0 | M4: 303 | N4: 1540 | O4: 5.08 | P4: 16 | Q4: 24 | R4: 18 | S4: 206 | T4: 11.44 | U4: 2 | V4: 5 | W4: 3 | X4: 18 | Y4: 0 | Z4: 0 | AA4: 277 | AB4: 294.6 | AC4: 303.6 | AD4: 285.6 | AE4: 136 | AF4: 2 | AG4: 3 | AH4: N
A5: 4 | B5: Aaron Jones | C5: GNB | D5: RB | E5: 25 | F5: 16 | G5: 16 | H5: 0 | I5: 0 | J5: 0 | K5: 0 | L5: 0 | M5: 236 | N5: 1084 | O5: 4.59 | P5: 16 | Q5: 68 | R5: 49 | S5: 474 | T5: 9.67 | U5: 3 | V5: 3 | W5: 2 | X5: 19 | Y5: 0 | Z5: 0 | AA5: 266 | AB5: 314.8 | AC5: 322.8 | AD5: 290.3 | AE5: 125 | AF5: 3 | AG5: 4 | AH5: N
A6: 5 | B6: Ezekiel Elliott | C6: DAL | D6: RB | E6: 24 | F6: 16 | G6: 16 | H6: 0 | I6: 0 | J6: 0 | K6: 0 | L6: 0 | M6: 301 | N6: 1357 | O6: 4.51 | P6: 12 | Q6: 71 | R6: 54 | S6: 420 | T6: 7.78 | U6: 2 | V6: 3 | W6: 2 | X6: 14 | Y6: 0 | Z6: 0 | AA6: 258 | AB6: 311.7 | AC6: 319.7 | AD6: 284.7 | AE6: 117 | AF6: 4 | AG6: 5 | AH6: N
A7: 6 | B7: Dalvin Cook | C7: MIN | D7: RB | E7: 24 | F7: 14 | G7: 14 | H7: 0 | I7: 0 | J7: 0 | K7: 0 | L7: 0 | M7: 250 | N7: 1135 | O7: 4.54 | P7: 13 | Q7: 63 | R7: 53 | S7: 519 | T7: 9.79 | U7: 0 | V7: 4 | W7: 2 | X7: 13 | Y7: 0 | Z7: 0 | AA7: 239 | AB7: 292.4 | AC7: 300.4 | AD7: 265.9 | AE7: 99 | AF7: 5 | AG7: 6 | AH7: N
A8: 7 | B8: Michael Thomas | C8: NOR | D8: WR | E8: 26 | F8: 16 | G8: 15 | H8: 0 | I8: 0 | J8: 0 | K8: 0 | L8: 0 | M8: 1 | N8: -9 | O8: -9 | P8: 0 | Q8: 185 | R8: 149 | S8: 1725 | T8: 11.58 | U8: 9 | V8: 1 | W8: 0 | X8: 9 | Y8: 0 | Z8: 0 | AA8: 226 | AB8: 374.6 | AC8: 377.6 | AD8: 300.1 | AE8: 97 | AF8: 1 | AG8: 7 | AH8: N
A9: 8 | B9: Travis Kelce | C9: KAN | D9: TE | E9: 30 | F9: 16 | G9: 16 | H9: 0 | I9: 0 | J9: 0 | K9: 0 | L9: 0 | M9: 1 | N9: 4 | O9: 4 | P9: 1 | Q9: 136 | R9: 97 | S9: 1229 | T9: 12.67 | U9: 5 | V9: 1 | W9: 1 | X9: 6 | Y9: 0 | Z9: 0 | AA9: 157 | AB9: 254.3 | AC9: 258.3 | AD9: 205.8 | AE9: 80 | AF9: 1 | AG9: 8 | AH9: N
A10: 9 | B10: Nick Chubb | C10: CLE | D10: RB | E10: 24 | F10: 16 | G10: 16 | H10: 0 | I10: 0 | J10: 0 | K10: 0 | L10: 0 | M10: 298 | N10: 1494 | O10: 5.01 | P10: 8 | Q10: 49 | R10: 36 | S10: 278 | T10: 7.72 | U10: 0 | V10: 3 | W10: 3 | X10: 8 | Y10: 0 | Z10: 0 | AA10: 219 | AB10: 255.2 | AC10: 264.2 | AD10: 237.2 | AE10: 79 | AF10: 6 | AG10: 9 | AH10: N
A11: 10 | B11: Austin Ekeler | C11: LAC | D11: RB | E11: 24 | F11: 16 | G11: 8 | H11: 0 | I11: 0 | J11: 0 | K11: 0 | L11: 0 | M11: 132 | N11: 557 | O11: 4.22 | P11: 3 | Q11: 108 | R11: 92 | S11: 993 | T11: 10.79 | U11: 8 | V11: 3 | W11: 2 | X11: 11 | Y11: 0 | Z11: 0 | AA11: 217 | AB11: 309 | AC11: 317 | AD11: 263 | AE11: 76 | AF11: 7 | AG11: 10 | AH11: N
A12: 11 | B12: Mark Ingram | C12: BAL | D12: RB | E12: 30 | F12: 15 | G12: 15 | H12: 0 | I12: 0 | J12: 0 | K12: 0 | L12: 0 | M12: 202 | N12: 1018 | O12: 5.04 | P12: 10 | Q12: 29 | R12: 26 | S12: 247 | T12: 9.5 | U12: 5 | V12: 2 | W12: 2 | X12: 15 | Y12: 2 | Z12: 0 | AA12: 217 | AB12: 242.5 | AC12: 250.5 | AD12: 229.5 | AE12: 76 | AF12: 8 | AG12: 11 | AH12: N
A13: 12 | B13: Dak Prescott | C13: DAL | D13: QB | E13: 26 | F13: 16 | G13: 16 | H13: 388 | I13: 596 | J13: 4902 | K13: 30 | L13: 11 | M13: 52 | N13: 277 | O13: 5.33 | P13: 3 | Q13: 0 | R13: 0 | S13: 0 | T13: 0 | U13: 0 | V13: 6 | W13: 2 | X13: 3 | Y13: 0 | Z13: 1 | AA13: 338 | AB13: 337.8 | AC13: 356.8 | AD13: 348.8 | AE13: 74 | AF13: 2 | AG13: 12 | AH13: N
... A75: 74 | B75: Davante Adams | C75: GNB | D75: WR | E75: 27 | F75: 12 | G75: 12 | H75: 0 | I75: 0 | J75: 0 | K75: 0 | L75: 0 | M75: 0 | N75: 0 | O75: 0 | P75: 0 | Q75: 127 | R75: 83 | S75: 997 | T75: 12.01 | U75: 5 | V75: 2 | W75: 1 | X75: 5 | Y75: 1 | Z75: 0 | AA75: 130 | AB75: 212.7 | AC75: 216.7 | AD75: 171.2 | AE75: 1 | AF75: 29 | AG75: 74 | AH75: N
A76: 75 | B76: Sony Michel | C76: NWE | D76: RB | E76: 24 | F76: 16 | G76: 14 | H76: 0 | I76: 0 | J76: 0 | K76: 0 | L76: 0 | M76: 247 | N76: 912 | O76: 3.69 | P76: 7 | Q76: 20 | R76: 12 | S76: 94 | T76: 7.83 | U76: 0 | V76: 2 | W76: 1 | X76: 7 | Y76: 0 | Z76: 0 | AA76: 141 | AB76: 152.6 | AC76: 156.6 | AD76: 146.6 | AF76: 24 | AG76: 75 | AH76: N
A77: 76 | B77: Tom Brady | C77: NWE | D77: QB | E77: 42 | F77: 16 | G77: 16 | H77: 373 | I77: 613 | J77: 4057 | K77: 24 | L77: 8 | M77: 26 | N77: 34 | O77: 1.31 | P77: 3 | Q77: 0 | R77: 0 | S77: 0 | T77: 0 | U77: 0 | V77: 4 | W77: 1 | X77: 3 | Y77: 0 | Z77: 1 | AA77: 264 | AB77: 263.7 | AC77: 275.7 | AD77: 271.7 | AF77: 12 | AG77: 76 | AH77: N
A78: 77 | B78: Jason Witten | C78: DAL | D78: TE | E78: 37 | F78: 16 | G78: 16 | H78: 0 | I78: 0 | J78: 0 | K78: 0 | L78: 0 | M78: 0 | N78: 0 | O78: 0 | P78: 0 | Q78: 83 | R78: 63 | S78: 529 | T78: 8.4 | U78: 4 | V78: 1 | W78: 1 | X78: 4 | Y78: 1 | Z78: 0 | AA78: 77 | AB78: 139.9 | AC78: 143.9 | AD78: 108.4 | AF78: 12 | AG78: 77 | AH78: N
A79: 78 | B79: Michael Burton | C79: WAS | E79: 27 | F79: 10 | G79: 2 | H79: 0 | I79: 0 | J79: 0 | K79: 0 | L79: 0 | M79: 0 | N79: 0 | O79: 0 | P79: 0 | Q79: 1 | R79: 0 | S79: 0 | T79: 0 | U79: 0 | V79: 0 | W79: 0 | X79: 0 | Y79: 0 | Z79: 0 | AF79: 1 | AG79: 78 | AH79: N
A80: 79 | B80: Jared Goff | C80: LAR | D80: QB | E80: 25 | F80: 16 | G80: 16 | H80: 394 | I80: 626 | J80: 4638 | K80: 22 | L80: 16 | M80: 33 | N80: 40 | O80: 1.21 | P80: 2 | Q80: 0 | R80: 0 | S80: 0 | T80: 0 | U80: 0 | V80: 10 | W80: 5 | X80: 2 | Y80: 0 | Z80: 0 | AA80: 248 | AB80: 247.5 | AC80: 271.5 | AD80: 263.5 | AF80: 13 | AH80: N
A81: 80 | B81: Jimmy Garoppolo | C81: SFO | D81: QB | E81: 28 | F81: 16 | G81: 16 | H81: 329 | I81: 476 | J81: 3978 | K81: 27 | L81: 13 | M81: 46 | N81: 62 | O81: 1.35 | P81: 1 | Q81: 0 | R81: 0 | S81: 0 | T81: 0 | U81: 0 | V81: 10 | W81: 5 | X81: 1 | Y81: 0 | Z81: 2 | AA81: 247 | AB81: 247.3 | AC81: 268.3 | AD81: 260.3 | AF81: 14 | AH81: N
A82: 81 | B82: Derek Carr | C82: OAK | D82: QB | E82: 28 | F82: 16 | G82: 16 | H82: 361 | I82: 513 | J82: 4054 | K82: 21 | L82: 8 | M82: 27 | N82: 82 | O82: 3.04 | P82: 2 | Q82: 0 | R82: 0 | S82: 0 | T82: 0 | U82: 0 | V82: 7 | W82: 3 | X82: 2 | Y82: 0 | Z82: 0 | AA82: 244 | AB82: 244.4 | AC82: 258.4 | AD82: 252.4 | AF82: 16 | AH82: N
A83: 82 | B83: Kirk Cousins | C83: MIN | D83: QB | E83: 31 | F83: 15 | G83: 15 | H83: 307 | I83: 444 | J83: 3603 | K83: 26 | L83: 6 | M83: 31 | N83: 63 | O83: 2.03 | P83: 1 | Q83: 1 | R83: 0 | S83: 0 | T83: 0 | U83: 0 | V83: 10 | W83: 3 | X83: 1 | Y83: 0 | Z83: 1 | AA83: 244 | AB83: 244.4 | AC83: 256.4 | AD83: 250.4 | AF83: 15 | AH83: N
A84: 83 | B84: Ryan Fitzpatrick | C84: MIA | D84: QB | E84: 37 | F84: 15 | G84: 13 | H84: 311 | I84: 502 | J84: 3529 | K84: 20 | L84: 13 | M84: 54 | N84: 243 | O84: 4.5 | P84: 4 | Q84: 0 | R84: 0 | S84: 0 | T84: 0 | U84: 0 | V84: 9 | W84: 2 | X84: 4 | Y84: 0 | Z84: 1 | AA84: 241 | AB84: 241.5 | AC84: 262.5 | AD84: 254.5 | AF84: 17 | AH84: N
A85: 84 | B85: Philip Rivers | C85: LAC | D85: QB | E85: 38 | F85: 16 | G85: 16 | H85: 390 | I85: 591 | J85: 4615 | K85: 23 | L85: 20 | M85: 12 | N85: 29 | O85: 2.42 | P85: 0 | Q85: 0 | R85: 0 | S85: 0 | T85: 0 | U85: 0 | V85: 8 | W85: 3 | X85: 0 | Y85: 0 | Z85: 1 | AA85: 236 | AB85: 235.5 | AC85: 261.5 | AD85: 255.5 | AF85: 18 | AH85: N
A86: 85 | B86: Baker Mayfield | C86: CLE | D86: QB | E86: 24 | F86: 16 | G86: 16 | H86: 317 | I86: 534 | J86: 3827 | K86: 22 | L86: 21 | M86: 28 | N86: 141 | O86: 5.04 | P86: 3 | Q86: 0 | R86: 0 | S86: 0 | T86: 0 | U86: 0 | V86: 6 | W86: 2 | X86: 3 | Y86: 0 | Z86: 1 | AA86: 229 | AB86: 229.2 | AC86: 258.2 | AD86: 250.2 | AF86: 20 | AH86: N
A87: 86 | B87: Gardner Minshew II | C87: JAX | D87: QB | E87: 23 | F87: 14 | G87: 12 | H87: 285 | I87: 470 | J87: 3271 | K87: 21 | L87: 6 | M87: 67 | N87: 344 | O87: 5.13 | P87: 0 | Q87: 0 | R87: 0 | S87: 0 | T87: 0 | U87: 0 | V87: 13 | W87: 7 | X87: 0 | Y87: 0 | Z87: 3 | AA87: 229 | AB87: 229.2 | AC87: 248.2 | AD87: 235.2 | AF87: 19 | AH87: N
A88: 87 | B88: Drew Brees | C88: NOR | D88: QB | E88: 40 | F88: 11 | G88: 11 | H88: 281 | I88: 378 | J88: 2979 | K88: 27 | L88: 4 | M88: 9 | N88: -4 | O88: -0.44 | P88: 1 | Q88: 0 | R88: 0 | S88: 0 | T88: 0 | U88: 0 | V88: 0 | W88: 0 | X88: 1 | Y88: 0 | Z88: 0 | AA88: 225 | AB88: 224.8 | AC88: 231.8 | AD88: 228.8 | AF88: 21 | AH88: N
A89: 88 | B89: Ryan Tannehill | C89: TEN | D89: QB | E89: 31 | F89: 12 | G89: 10 | H89: 201 | I89: 286 | J89: 2742 | K89: 22 | L89: 6 | M89: 43 | N89: 185 | O89: 4.3 | P89: 4 | Q89: 0 | R89: 0 | S89: 0 | T89: 0 | U89: 0 | V89: 6 | W89: 3 | X89: 4 | Y89: 1 | Z89: 0 | AA89: 224 | AB89: 224.2 | AC89: 239.2 | AD89: 230.2 | AF89: 22 | AH89: N
A90: 89 | B90: Jacoby Brissett | C90: IND | D90: QB | E90: 27 | F90: 15 | G90: 15 | H90: 272 | I90: 447 | J90: 2942 | K90: 18 | L90: 6 | M90: 56 | N90: 228 | O90: 4.07 | P90: 4 | Q90: 1 | R90: 1 | S90: 2 | T90: 2 | U90: 0 | V90: 7 | W90: 5 | X90: 4 | Y90: 0 | Z90: 1 | AA90: 217 | AB90: 217.7 | AC90: 234.7 | AD90: 223.2 | AF90: 23 | AH90: N
A91: 90 | B91: Daniel Jones | C91: NYG | D91: QB | E91: 22 | F91: 13 | G91: 12 | H91: 284 | I91: 459 | J91: 3027 | K91: 24 | L91: 12 | M91: 45 | N91: 279 | O91: 6.2 | P91: 2 | Q91: 0 | R91: 0 | S91: 0 | T91: 0 | U91: 0 | V91: 18 | W91: 11 | X91: 2 | Y91: 0 | Z91: 2 | AA91: 215 | AB91: 215 | AC91: 244 | AD91: 227 | AF91: 24 | AH91: N
... A537: 536 | B537: Dexter Williams | C537: GNB | D537: RB | E537: 22 | F537: 4 | G537: 0 | H537: 0 | I537: 0 | J537: 0 | K537: 0 | L537: 0 | M537: 5 | N537: 11 | O537: 2.2 | P537: 0 | Q537: 0 | R537: 0 | S537: 0 | T537: 0 | U537: 0 | V537: 0 | W537: 0 | X537: 0 | Y537: 0 | Z537: 0 | AA537: 1 | AB537: 1.1 | AC537: 1.1 | AD537: 1.1 | AF537: 140 | AH537: N
A538: 537 | B538: Jerell Adams | C538: HOU | E538: 27 | F538: 1 | G538: 0 | H538: 0 | I538: 0 | J538: 0 | K538: 0 | L538: 0 | M538: 0 | N538: 0 | O538: 0 | P538: 0 | Q538: 0 | R538: 0 | S538: 0 | T538: 0 | U538: 0 | V538: 0 | W538: 0 | X538: 0 | Y538: 0 | Z538: 0 | AF538: 125 | AH538: N
A539: 538 | B539: Stephen Anderson | C539: LAC | E539: 26 | F539: 1 | G539: 0 | H539: 0 | I539: 0 | J539: 0 | K539: 0 | L539: 0 | M539: 0 | N539: 0 | O539: 0 | P539: 0 | Q539: 0 | R539: 0 | S539: 0 | T539: 0 | U539: 0 | V539: 0 | W539: 0 | X539: 0 | Y539: 0 | Z539: 0 | AF539: 120 | AH539: N
A540: 539 | B540: Evan Baylis | C540: GNB | E540: 26 | F540: 3 | G540: 0 | H540: 0 | I540: 0 | J540: 0 | K540: 0 | L540: 0 | M540: 0 | N540: 0 | O540: 0 | P540: 0 | Q540: 0 | R540: 0 | S540: 0 | T540: 0 | U540: 0 | V540: 0 | W540: 0 | X540: 0 | Y540: 0 | Z540: 0 | AF540: 130 | AH540: N
A541: 540 | B541: Kendall Blanton | C541: LAR | E541: 24 | F541: 1 | G541: 0 | H541: 0 | I541: 0 | J541: 0 | K541: 0 | L541: 0 | M541: 0 | N541: 0 | O541: 0 | P541: 0 | Q541: 0 | R541: 0 | S541: 0 | T541: 0 | U541: 0 | V541: 0 | W541: 0 | X541: 0 | Y541: 0 | Z541: 0 | AF541: 117 | AH541: N
A542: 541 | B542: Tim Boyle | C542: GNB | D542: QB | E542: 25 | F542: 3 | G542: 0 | H542: 3 | I542: 4 | J542: 15 | K542: 0 | L542: 0 | M542: 5 | N542: -7 | O542: -1.4 | P542: 0 | Q542: 0 | R542: 0 | S542: 0 | T542: 0 | U542: 0 | V542: 0 | W542: 0 | X542: 0 | Y542: 0 | Z542: 0 | AB542: -0.1 | AC542: -0.1 | AD542: -0.1 | AF542: 68 | AH542: N
A543: 542 | B543: Deante Burton | C543: DAL | E543: 25 | F543: 3 | G543: 0 | H543: 0 | I543: 0 | J543: 0 | K543: 0 | L543: 0 | M543: 0 | N543: 0 | O543: 0 | P543: 0 | Q543: 0 | R543: 0 | S543: 0 | T543: 0 | U543: 0 | V543: 0 | W543: 0 | X543: 0 | Y543: 0 | Z543: 0 | AF543: 224 | AH543: N
A544: 543 | B544: Trenton Cannon | C544: NYJ | E544: 25 | F544: 4 | G544: 0 | H544: 0 | I544: 0 | J544: 0 | K544: 0 | L544: 0 | M544: 0 | N544: 0 | O544: 0 | P544: 0 | Q544: 0 | R544: 0 | S544: 0 | T544: 0 | U544: 0 | V544: 0 | W544: 0 | X544: 0 | Y544: 0 | Z544: 0 | AF544: 156 | AH544: N
A545: 544 | B545: Garrett Celek | C545: SFO | E545: 31 | F545: 5 | G545: 1 | H545: 0 | I545: 0 | J545: 0 | K545: 0 | L545: 0 | M545: 0 | N545: 0 | O545: 0 | P545: 0 | Q545: 0 | R545: 0 | S545: 0 | T545: 0 | U545: 0 | V545: 0 | W545: 0 | X545: 0 | Y545: 0 | Z545: 0 | AF545: 121 | AH545: N
A546: 545 | B546: Jordan Chunn | C546: DAL | E546: 24 | F546: 1 | G546: 0 | H546: 0 | I546: 0 | J546: 0 | K546: 0 | L546: 0 | M546: 0 | N546: 0 | O546: 0 | P546: 0 | Q546: 0 | R546: 0 | S546: 0 | T546: 0 | U546: 0 | V546: 0 | W546: 0 | X546: 0 | Y546: 0 | Z546: 0 | AF546: 163 | AH546: N
A547: 546 | B547: Chandler Cox | C547: MIA | E547: 23 | F547: 13 | G547: 3 | H547: 0 | I547: 0 | J547: 0 | K547: 0 | L547: 0 | M547: 0 | N547: 0 | O547: 0 | P547: 0 | Q547: 0 | R547: 0 | S547: 0 | T547: 0 | U547: 0 | V547: 0 | W547: 0 | X547: 0 | Y547: 0 | Z547: 0 | AF547: 164 | AH547: N
A548: 547 | B548: River Cracraft | C548: DEN | E548: 25 | F548: 1 | G548: 0 | H548: 0 | I548: 0 | J548: 0 | K548: 0 | L548: 0 | M548: 0 | N548: 0 | O548: 0 | P548: 0 | Q548: 0 | R548: 0 | S548: 0 | T548: 0 | U548: 0 | V548: 0 | W548: 0 | X548: 0 | Y548: 0 | Z548: 0 | AF548: 234 | AH548: N
A549: 548 | B549: Jerome Cunningham | C549: WAS | E549: 28 | F549: 2 | G549: 1 | H549: 0 | I549: 0 | J549: 0 | K549: 0 | L549: 0 | M549: 0 | N549: 0 | O549: 0 | P549: 0 | Q549: 0 | R549: 0 | S549: 0 | T549: 0 | U549: 0 | V549: 0 | W549: 0 | X549: 0 | Y549: 0 | Z549: 0 | AF549: 119 | AH549: N
A550: 549 | B550: Darrell Daniels | C550: ARI | D550: TE | E550: 25 | F550: 11 | G550: 0 | H550: 0 | I550: 0 | J550: 0 | K550: 0 | L550: 0 | M550: 0 | N550: 0 | O550: 0 | P550: 0 | Q550: 3 | R550: 1 | S550: 4 | T550: 4 | U550: 0 | V550: 0 | W550: 0 | X550: 0 | Y550: 0 | Z550: 0 | AB550: 1.4 | AC550: 1.4 | AD550: 0.9 | AF550: 113 | AH550: N
A551: 550 | B551: Davion Davis | C551: MIN | E551: 23 | F551: 2 | G551: 0 | H551: 0 | I551: 0 | J551: 0 | K551: 0 | L551: 0 | M551: 0 | N551: 0 | O551: 0 | P551: 0 | Q551: 0 | R551: 0 | S551: 0 | T551: 0 | U551: 0 | V551: 0 | W551: 0 | X551: 0 | Y551: 0 | Z551: 0 | AF551: 238 | AH551: N
A552: 551 | B552: James Develin | C552: NWE | D552: RB | E552: 31 | F552: 2 | G552: 2 | H552: 0 | I552: 0 | J552: 0 | K552: 0 | L552: 0 | M552: 2 | N552: 3 | O552: 1.5 | P552: 0 | Q552: 0 | R552: 0 | S552: 0 | T552: 0 | U552: 0 | V552: 0 | W552: 0 | X552: 0 | Y552: 0 | Z552: 0 | AB552: 0.3 | AC552: 0.3 | AD552: 0.3 | AF552: 153 | AH552: N
A553: 552 | B553: Garrett Dickerson | C553: NYG | E553: 24 | F553: 4 | G553: 0 | H553: 0 | I553: 0 | J553: 0 | K553: 0 | L553: 0 | M553: 0 | N553: 0 | O553: 0 | P553: 0 | Q553: 0 | R553: 0 | S553: 0 | T553: 0 | U553: 0 | V553: 0 | W553: 0 | X553: 0 | Y553: 0 | Z553: 0 | AF553: 134 | AH553: N
A554: 553 | B554: Gehrig Dieter | C554: KAN | E554: 26 | F554: 2 | G554: 0 | H554: 0 | I554: 0 | J554: 0 | K554: 0 | L554: 0 | M554: 0 | N554: 0 | O554: 0 | P554: 0 | Q554: 0 | R554: 0 | S554: 0 | T554: 0 | U554: 0 | V554: 0 | W554: 0 | X554: 0 | Y554: 0 | Z554: 0 | AF554: 231 | AH554: N
A555: 554 | B555: Brandon Dillon | C555: MIN | E555: 22 | F555: 1 | G555: 0 | H555: 0 | I555: 0 | J555: 0 | K555: 0 | L555: 0 | M555: 0 | N555: 0 | O555: 0 | P555: 0 | Q555: 0 | R555: 0 | S555: 0 | T555: 0 | U555: 0 | V555: 0 | W555: 0 | X555: 0 | Y555: 0 | Z555: 0 | AF555: 122 | AH555: N
A556: 555 | B556: Josh Doctson | C556: MIN | E556: 27 | F556: 1 | G556: 0 | H556: 0 | I556: 0 | J556: 0 | K556: 0 | L556: 0 | M556: 0 | N556: 0 | O556: 0 | P556: 0 | Q556: 0 | R556: 0 | S556: 0 | T556: 0 | U556: 0 | V556: 0 | W556: 0 | X556: 0 | Y556: 0 | Z556: 0 | AF556: 221 | AH556: N
A557: 556 | B557: Quinton Dunbar | C557: WAS | E557: 27 | F557: 11 | G557: 11 | H557: 0 | I557: 0 | J557: 0 | K557: 0 | L557: 0 | M557: 0 | N557: 0 | O557: 0 | P557: 0 | Q557: 0 | R557: 0 | S557: 0 | T557: 0 | U557: 0 | V557: 0 | W557: 0 | X557: 0 | Y557: 0 | Z557: 0 | AF557: 222 | AH557: N
A558: 557 | B558: Alex Ellis | C558: PHI | E558: 26 | F558: 3 | G558: 0 | H558: 0 | I558: 0 | J558: 0 | K558: 0 | L558: 0 | M558: 0 | N558: 0 | O558: 0 | P558: 0 | Q558: 0 | R558: 0 | S558: 0 | T558: 0 | U558: 0 | V558: 0 | W558: 0 | X558: 0 | Y558: 0 | Z558: 0 | AF558: 118 | AH558: N
A559: 558 | B559: David Fales | C559: NYJ | E559: 29 | F559: 2 | G559: 0 | H559: 0 | I559: 0 | J559: 0 | K559: 0 | L559: 0 | M559: 0 | N559: 0 | O559: 0 | P559: 0 | Q559: 0 | R559: 0 | S559: 0 | T559: 0 | U559: 0 | V559: 0 | W559: 0 | X559: 0 | Y559: 0 | Z559: 0 | AF559: 67 | AH559: N
A560: 559 | B560: David Fluellen | C560: TEN | E560: 27 | F560: 2 | G560: 0 | H560: 0 | I560: 0 | J560: 0 | K560: 0 | L560: 0 | M560: 0 | N560: 0 | O560: 0 | P560: 0 | Q560: 0 | R560: 0 | S560: 0 | T560: 0 | U560: 0 | V560: 0 | W560: 0 | X560: 0 | Y560: 0 | Z560: 0 | AF560: 160 | AH560: N
A561: 560 | B561: D.J. Foster | C561: ARI | E561: 26 | F561: 6 | G561: 0 | H561: 0 | I561: 0 | J561: 0 | K561: 0 | L561: 0 | M561: 0 | N561: 0 | O561: 0 | P561: 0 | Q561: 0 | R561: 0 | S561: 0 | T561: 0 | U561: 0 | V561: 0 | W561: 0 | X561: 0 | Y561: 0 | Z561: 0 | AF561: 162 | AH561: N
A562: 561 | B562: Travis Fulgham | C562: DET | E562: 24 | F562: 3 | G562: 0 | H562: 0 | I562: 0 | J562: 0 | K562: 0 | L562: 0 | M562: 0 | N562: 0 | O562: 0 | P562: 0 | Q562: 3 | R562: 0 | S562: 0 | T562: 0 | U562: 0 | V562: 0 | W562: 0 | X562: 0 | Y562: 0 | Z562: 0 | AF562: 226 | AH562: N
A563: 562 | B563: Zach Gentry | C563: PIT | D563: TE | E563: 23 | F563: 4 | G563: 0 | H563: 0 | I563: 0 | J563: 0 | K563: 0 | L563: 0 | M563: 0 | N563: 0 | O563: 0 | P563: 0 | Q563: 1 | R563: 1 | S563: 4 | T563: 4 | U563: 0 | V563: 0 | W563: 0 | X563: 0 | Y563: 0 | Z563: 0 | AB563: 1.4 | AC563: 1.4 | AD563: 0.9 | AF563: 114 | AH563: N
A564: 563 | B564: Garrett Gilbert | C564: CLE | D564: QB | E564: 28 | F564: 5 | G564: 0 | H564: 0 | I564: 3 | J564: 0 | K564: 0 | L564: 0 | M564: 3 | N564: -3 | O564: -1 | P564: 0 | Q564: 0 | R564: 0 | S564: 0 | T564: 0 | U564: 0 | V564: 0 | W564: 0 | X564: 0 | Y564: 0 | Z564: 0 | AB564: -0.3 | AC564: -0.3 | AD564: -0.3 | AF564: 70 | AH564: N
A565: 564 | B565: Cullen Gillaspia | C565: HOU | E565: 24 | F565: 16 | G565: 0 | H565: 0 | I565: 0 | J565: 0 | K565: 0 | L565: 0 | M565: 0 | N565: 0 | O565: 0 | P565: 0 | Q565: 0 | R565: 0 | S565: 0 | T565: 0 | U565: 0 | V565: 0 | W565: 0 | X565: 0 | Y565: 0 | Z565: 0 | AF565: 161 | AH565: N
A566: 565 | B566: C.J. Goodwin | C566: DAL | E566: 29 | F566: 16 | G566: 0 | H566: 0 | I566: 0 | J566: 0 | K566: 0 | L566: 0 | M566: 0 | N566: 0 | O566: 0 | P566: 0 | Q566: 0 | R566: 0 | S566: 0 | T566: 0 | U566: 0 | V566: 0 | W566: 0 | X566: 0 | Y566: 0 | Z566: 0 | AF566: 237 | AH566: N
A567: 566 | B567: Cyril Grayson | C567: TAM | D567: WR | E567: 26 | F567: 2 | G567: 0 | H567: 0 | I567: 0 | J567: 0 | K567: 0 | L567: 0 | M567: 0 | N567: 0 | O567: 0 | P567: 0 | Q567: 1 | R567: 1 | S567: 3 | T567: 3 | U567: 0 | V567: 0 | W567: 0 | X567: 0 | Y567: 0 | Z567: 0 | AB567: 1.3 | AC567: 1.3 | AD567: 0.8 | AF567: 214 | AH567: N
A568: 567 | B568: Xavier Grimble | C568: PIT | D568: TE | E568: 27 | F568: 3 | G568: 1 | H568: 0 | I568: 0 | J568: 0 | K568: 0 | L568: 0 | M568: 0 | N568: 0 | O568: 0 | P568: 0 | Q568: 3 | R568: 1 | S568: 3 | T568: 3 | U568: 0 | V568: 0 | W568: 0 | X568: 0 | Y568: 0 | Z568: 0 | AB568: 1.3 | AC568: 1.3 | AD568: 0.8 | AF568: 115 | AH568: N
A569: 568 | B569: Jalen Guyton | C569: LAC | E569: 22 | F569: 3 | G569: 0 | H569: 0 | I569: 0 | J569: 0 | K569: 0 | L569: 0 | M569: 0 | N569: 0 | O569: 0 | P569: 0 | Q569: 2 | R569: 0 | S569: 0 | T569: 0 | U569: 0 | V569: 0 | W569: 0 | X569: 0 | Y569: 0 | Z569: 0 | AF569: 218 | AH569: N
A570: 569 | B570: Justin Hardee | C570: NOR | E570: 25 | F570: 16 | G570: 0 | H570: 0 | I570: 0 | J570: 0 | K570: 0 | L570: 0 | M570: 0 | N570: 0 | O570: 0 | P570: 0 | Q570: 1 | R570: 0 | S570: 0 | T570: 0 | U570: 0 | V570: 0 | W570: 0 | X570: 0 | Y570: 0 | Z570: 0 | AF570: 233 | AH570: N
A571: 570 | B571: Clark Harris | C571: CIN | E571: 35 | F571: 16 | G571: 0 | H571: 0 | I571: 0 | J571: 0 | K571: 0 | L571: 0 | M571: 0 | N571: 0 | O571: 0 | P571: 0 | Q571: 0 | R571: 0 | S571: 0 | T571: 0 | U571: 0 | V571: 0 | W571: 0 | X571: 0 | Y571: 0 | Z571: 0 | AF571: 127 | AH571: N
A572: 571 | B572: Krishawn Hogan | C572: NOR | D572: WR | E572: 24 | F572: 8 | G572: 0 | H572: 0 | I572: 0 | J572: 0 | K572: 0 | L572: 0 | M572: 0 | N572: 0 | O572: 0 | P572: 0 | Q572: 1 | R572: 1 | S572: 4 | T572: 4 | U572: 0 | V572: 0 | W572: 0 | X572: 0 | Y572: 0 | Z572: 0 | AB572: 1.4 | AC572: 1.4 | AD572: 0.9 | AF572: 213 | AH572: N
A573: 572 | B573: Lil'Jordan Humphrey | C573: NOR | E573: 21 | F573: 5 | G573: 1 | H573: 0 | I573: 0 | J573: 0 | K573: 0 | L573: 0 | M573: 0 | N573: 0 | O573: 0 | P573: 0 | Q573: 1 | R573: 0 | S573: 0 | T573: 0 | U573: 0 | V573: 0 | W573: 0 | X573: 0 | Y573: 0 | Z573: 0 | AF573: 227 | AH573: N
A574: 573 | B574: Trenton Irwin | C574: CIN | E574: 24 | F574: 1 | G574: 0 | H574: 0 | I574: 0 | J574: 0 | K574: 0 | L574: 0 | M574: 0 | N574: 0 | O574: 0 | P574: 0 | Q574: 0 | R574: 0 | S574: 0 | T574: 0 | U574: 0 | V574: 0 | W574: 0 | X574: 0 | Y574: 0 | Z574: 0 | AF574: 219 | AH574: N
A575: 574 | B575: Gary Jennings Jr | C575: MIA | E575: 22 | F575: 1 | G575: 0 | H575: 0 | I575: 0 | J575: 0 | K575: 0 | L575: 0 | M575: 0 | N575: 0 | O575: 0 | P575: 0 | Q575: 0 | R575: 0 | S575: 0 | T575: 0 | U575: 0 | V575: 0 | W575: 0 | X575: 0 | Y575: 0 | Z575: 0 | AF575: 229 | AH575: N
A576: 575 | B576: Tom Kennedy | C576: DET | E576: 23 | F576: 1 | G576: 0 | H576: 0 | I576: 0 | J576: 0 | K576: 0 | L576: 0 | M576: 0 | N576: 0 | O576: 0 | P576: 0 | Q576: 0 | R576: 0 | S576: 0 | T576: 0 | U576: 0 | V576: 0 | W576: 0 | X576: 0 | Y576: 0 | Z576: 0 | AF576: 230 | AH576: N
A577: 576 | B577: Darvin Kidsy | C577: WAS | E577: 24 | F577: 3 | G577: 0 | H577: 0 | I577: 0 | J577: 0 | K577: 0 | L577: 0 | M577: 0 | N577: 0 | O577: 0 | P577: 0 | Q577: 0 | R577: 0 | S577: 0 | T577: 0 | U577: 0 | V577: 0 | W577: 0 | X577: 0 | Y577: 0 | Z577: 0 | AF577: 228 | AH577: N
A578: 577 | B578: Keith Kirkwood | C578: NOR | E578: 26 | F578: 1 | G578: 0 | H578: 0 | I578: 0 | J578: 0 | K578: 0 | L578: 0 | M578: 0 | N578: 0 | O578: 0 | P578: 0 | Q578: 0 | R578: 0 | S578: 0 | T578: 0 | U578: 0 | V578: 0 | W578: 0 | X578: 0 | Y578: 0 | Z578: 0 | AF578: 220 | AH578: N
A579: 578 | B579: Matt Lengel | C579: IND | E579: 29 | F579: 1 | G579: 1 | H579: 0 | I579: 0 | J579: 0 | K579: 0 | L579: 0 | M579: 0 | N579: 0 | O579: 0 | P579: 0 | Q579: 0 | R579: 0 | S579: 0 | T579: 0 | U579: 0 | V579: 0 | W579: 0 | X579: 0 | Y579: 0 | Z579: 0 | AF579: 124 | AH579: N
A580: 579 | B580: Josh Malone | C580: NYJ | E580: 23 | F580: 2 | G580: 0 | H580: 0 | I580: 0 | J580: 0 | K580: 0 | L580: 0 | M580: 0 | N580: 0 | O580: 0 | P580: 0 | Q580: 0 | R580: 0 | S580: 0 | T580: 0 | U580: 0 | V580: 0 | W580: 0 | X580: 0 | Y580: 0 | Z580: 0 | AF580: 235 | AH580: N
A581: 580 | B581: Jeremy McNichols | C581: JAX | E581: 24 | F581: 1 | G581: 0 | H581: 0 | I581: 0 | J581: 0 | K581: 0 | L581: 0 | M581: 0 | N581: 0 | O581: 0 | P581: 0 | Q581: 0 | R581: 0 | S581: 0 | T581: 0 | U581: 0 | V581: 0 | W581: 0 | X581: 0 | Y581: 0 | Z581: 0 | AF581: 165 | AH581: N
A582: 581 | B582: Trace McSorley | C582: BAL | D582: QB | E582: 24 | F582: 1 | G582: 0 | H582: 0 | I582: 0 | J582: 0 | K582: 0 | L582: 0 | M582: 1 | N582: 1 | O582: 1 | P582: 0 | Q582: 0 | R582: 0 | S582: 0 | T582: 0 | U582: 0 | V582: 0 | W582: 0 | X582: 0 | Y582: 0 | Z582: 0 | AB582: 0.1 | AC582: 0.1 | AD582: 0.1 | AF582: 64 | AH582: N
A583: 582 | B583: Carson Meier | C583: ATL | E583: 24 | F583: 1 | G583: 1 | H583: 0 | I583: 0 | J583: 0 | K583: 0 | L583: 0 | M583: 0 | N583: 0 | O583: 0 | P583: 0 | Q583: 0 | R583: 0 | S583: 0 | T583: 0 | U583: 0 | V583: 0 | W583: 0 | X583: 0 | Y583: 0 | Z583: 0 | AF583: 131 | AH583: N
A584: 583 | B584: Jaydon Mickens | C584: TAM | E584: 25 | F584: 1 | G584: 0 | H584: 0 | I584: 0 | J584: 0 | K584: 0 | L584: 0 | M584: 0 | N584: 0 | O584: 0 | P584: 0 | Q584: 0 | R584: 0 | S584: 0 | T584: 0 | U584: 0 | V584: 0 | W584: 0 | X584: 0 | Y584: 0 | Z584: 0 | AF584: 240 | AH584: N
A585: 584 | B585: Alfred Morris | C585: ARI | D585: RB | E585: 31 | F585: 1 | G585: 0 | H585: 0 | I585: 0 | J585: 0 | K585: 0 | L585: 0 | M585: 1 | N585: 4 | O585: 4 | P585: 0 | Q585: 0 | R585: 0 | S585: 0 | T585: 0 | U585: 0 | V585: 0 | W585: 0 | X585: 0 | Y585: 0 | Z585: 0 | AB585: 0.4 | AC585: 0.4 | AD585: 0.4 | AF585: 152 | AH585: N
A586: 585 | B586: Nick Mullens | C586: SFO | D586: QB | E586: 24 | F586: 1 | G586: 0 | H586: 0 | I586: 0 | J586: 0 | K586: 0 | L586: 0 | M586: 3 | N586: -3 | O586: -1 | P586: 0 | Q586: 0 | R586: 0 | S586: 0 | T586: 0 | U586: 0 | V586: 0 | W586: 0 | X586: 0 | Y586: 0 | Z586: 0 | AB586: -0.3 | AC586: -0.3 | AD586: -0.3 | AF586: 69 | AH586: N
A587: 586 | B587: Jojo Natson | C587: LAR | E587: 25 | F587: 12 | G587: 0 | H587: 0 | I587: 0 | J587: 0 | K587: 0 | L587: 0 | M587: 0 | N587: 0 | O587: 0 | P587: 0 | Q587: 0 | R587: 0 | S587: 0 | T587: 0 | U587: 0 | V587: 0 | W587: 0 | X587: 0 | Y587: 0 | Z587: 0 | AF587: 236 | AH587: N
A588: 587 | B588: Roosevelt Nix | C588: PIT | D588: RB | E588: 27 | F588: 3 | G588: 0 | H588: 0 | I588: 0 | J588: 0 | K588: 0 | L588: 0 | M588: 0 | N588: 0 | O588: 0 | P588: 0 | Q588: 3 | R588: 2 | S588: 4 | T588: 2 | U588: 0 | V588: 0 | W588: 0 | X588: 0 | Y588: 0 | Z588: 0 | AB588: 2.4 | AC588: 2.4 | AD588: 1.4 | AF588: 150 | AH588: N
A589: 588 | B589: Jamize Olawale | C589: DAL | E589: 30 | F589: 16 | G589: 5 | H589: 0 | I589: 0 | J589: 0 | K589: 0 | L589: 0 | M589: 0 | N589: 0 | O589: 0 | P589: 0 | Q589: 2 | R589: 0 | S589: 0 | T589: 0 | U589: 0 | V589: 0 | W589: 0 | X589: 0 | Y589: 0 | Z589: 0 | AF589: 2 | AH589: N
A590: 589 | B590: Matthew Orzech | C590: JAX | E590: 24 | F590: 16 | G590: 0 | H590: 0 | I590: 0 | J590: 0 | K590: 0 | L590: 0 | M590: 0 | N590: 0 | O590: 0 | P590: 0 | Q590: 0 | R590: 0 | S590: 0 | T590: 0 | U590: 0 | V590: 0 | W590: 0 | X590: 0 | Y590: 0 | Z590: 0 | AF590: 128 | AH590: N
A591: 590 | B591: Senorise Perry | C591: BUF | D591: RB | E591: 28 | F591: 11 | G591: 0 | H591: 0 | I591: 0 | J591: 0 | K591: 0 | L591: 0 | M591: 3 | N591: 3 | O591: 1 | P591: 0 | Q591: 1 | R591: 1 | S591: 1 | T591: 1 | U591: 0 | V591: 0 | W591: 0 | X591: 0 | Y591: 0 | Z591: 0 | AB591: 1.4 | AC591: 1.4 | AD591: 0.9 | AF591: 151 | AH591: N
A592: 591 | B592: Craig Reynolds | C592: WAS | E592: 23 | F592: 3 | G592: 0 | H592: 0 | I592: 0 | J592: 0 | K592: 0 | L592: 0 | M592: 0 | N592: 0 | O592: 0 | P592: 0 | Q592: 0 | R592: 0 | S592: 0 | T592: 0 | U592: 0 | V592: 0 | W592: 0 | X592: 0 | Y592: 0 | Z592: 0 | AF592: 157 | AH592: N
A593: 592 | B593: Richard Rodgers | C593: PHI | E593: 27 | F593: 1 | G593: 0 | H593: 0 | I593: 0 | J593: 0 | K593: 0 | L593: 0 | M593: 0 | N593: 0 | O593: 0 | P593: 0 | Q593: 0 | R593: 0 | S593: 0 | T593: 0 | U593: 0 | V593: 0 | W593: 0 | X593: 0 | Y593: 0 | Z593: 0 | AF593: 132 | AH593: N
A594: 593 | B594: Cooper Rush | C594: DAL | E594: 26 | F594: 2 | G594: 0 | H594: 0 | I594: 0 | J594: 0 | K594: 0 | L594: 0 | M594: 0 | N594: 0 | O594: 0 | P594: 0 | Q594: 0 | R594: 0 | S594: 0 | T594: 0 | U594: 0 | V594: 0 | W594: 0 | X594: 0 | Y594: 0 | Z594: 0 | AF594: 66 | AH594: N
A595: 594 | B595: Spencer Schnell | C595: TAM | E595: 25 | F595: 1 | G595: 0 | H595: 0 | I595: 0 | J595: 0 | K595: 0 | L595: 0 | M595: 0 | N595: 0 | O595: 0 | P595: 0 | Q595: 0 | R595: 0 | S595: 0 | T595: 0 | U595: 0 | V595: 0 | W595: 0 | X595: 0 | Y595: 0 | Z595: 0 | AF595: 215 | AH595: N
A596: 595 | B596: Mason Schreck | C596: CIN | E596: 26 | F596: 2 | G596: 0 | H596: 0 | I596: 0 | J596: 0 | K596: 0 | L596: 0 | M596: 0 | N596: 0 | O596: 0 | P596: 0 | Q596: 0 | R596: 0 | S596: 0 | T596: 0 | U596: 0 | V596: 0 | W596: 0 | X596: 0 | Y596: 0 | Z596: 0 | AF596: 129 | AH596: N
A597: 596 | B597: Trevor Siemian | C597: NYJ | D597: QB | E597: 28 | F597: 1 | G597: 1 | H597: 3 | I597: 6 | J597: 3 | K597: 0 | L597: 0 | M597: 0 | N597: 0 | O597: 0 | P597: 0 | Q597: 0 | R597: 0 | S597: 0 | T597: 0 | U597: 0 | V597: 0 | W597: 0 | X597: 0 | Y597: 0 | Z597: 0 | AB597: 0.1 | AC597: 0.1 | AD597: 0.1 | AF597: 63 | AH597: N
A598: 597 | B598: Matthew Slater | C598: NWE | E598: 34 | F598: 16 | G598: 0 | H598: 0 | I598: 0 | J598: 0 | K598: 0 | L598: 0 | M598: 0 | N598: 0 | O598: 0 | P598: 0 | Q598: 0 | R598: 0 | S598: 0 | T598: 0 | U598: 0 | V598: 0 | W598: 0 | X598: 0 | Y598: 0 | Z598: 0 | AF598: 217 | AH598: N
A599: 598 | B599: Rod Smith | C599: 2TM | E599: 27 | F599: 6 | G599: 0 | H599: 0 | I599: 0 | J599: 0 | K599: 0 | L599: 0 | M599: 0 | N599: 0 | O599: 0 | P599: 0 | Q599: 0 | R599: 0 | S599: 0 | T599: 0 | U599: 0 | V599: 0 | W599: 0 | X599: 0 | Y599: 0 | Z599: 0 | AF599: 159 | AH599: N
A600: 599 | B600: Nate Solder | C600: NYG | E600: 31 | F600: 16 | G600: 16 | H600: 0 | I600: 0 | J600: 0 | K600: 0 | L600: 0 | M600: 0 | N600: 0 | O600: 0 | P600: 0 | Q600: 0 | R600: 0 | S600: 0 | T600: 0 | U600: 0 | V600: 0 | W600: 0 | X600: 0 | Y600: 0 | Z600: 0 | AF600: 133 | AH600: N
A601: 600 | B601: Jace Sternberger | C601: GNB | E601: 23 | F601: 6 | G601: 1 | H601: 0 | I601: 0 | J601: 0 | K601: 0 | L601: 0 | M601: 0 | N601: 0 | O601: 0 | P601: 0 | Q601: 1 | R601: 0 | S601: 0 | T601: 0 | U601: 0 | V601: 0 | W601: 0 | X601: 0 | Y601: 0 | Z601: 0 | AF601: 123 | AH601: N
A602: 601 | B602: Alex Tanney | C602: NYG | D602: QB | E602: 32 | F602: 1 | G602: 0 | H602: 1 | I602: 1 | J602: 1 | K602: 0 | L602: 0 | M602: 0 | N602: 0 | O602: 0 | P602: 0 | Q602: 0 | R602: 0 | S602: 0 | T602: 0 | U602: 0 | V602: 0 | W602: 0 | X602: 0 | Y602: 0 | Z602: 0 | AF602: 65 | AH602: N
A603: 602 | B603: Taywan Taylor | C603: CLE | E603: 24 | F603: 3 | G603: 1 | H603: 0 | I603: 0 | J603: 0 | K603: 0 | L603: 0 | M603: 0 | N603: 0 | O603: 0 | P603: 0 | Q603: 1 | R603: 0 | S603: 0 | T603: 0 | U603: 0 | V603: 0 | W603: 0 | X603: 0 | Y603: 0 | Z603: 0 | AF603: 232 | AH603: N
A604: 603 | B604: Eric Tomlinson | C604: 3TM | D604: TE | E604: 27 | F604: 8 | G604: 3 | H604: 0 | I604: 0 | J604: 0 | K604: 0 | L604: 0 | M604: 0 | N604: 0 | O604: 0 | P604: 0 | Q604: 1 | R604: 1 | S604: 1 | T604: 1 | U604: 0 | V604: 0 | W604: 0 | X604: 0 | Y604: 0 | Z604: 0 | AB604: 1.1 | AC604: 1.1 | AD604: 0.6 | AF604: 116 | AH604: N
A605: 604 | B605: Robert Turbin | C605: SEA | E605: 30 | F605: 1 | G605: 0 | H605: 0 | I605: 0 | J605: 0 | K605: 0 | L605: 0 | M605: 0 | N605: 0 | O605: 0 | P605: 0 | Q605: 0 | R605: 0 | S605: 0 | T605: 0 | U605: 0 | V605: 0 | W605: 0 | X605: 0 | Y605: 0 | Z605: 0 | AF605: 158 | AH605: N
A606: 605 | B606: Jason Vander Laan | C606: NOR | E606: 27 | F606: 2 | G606: 1 | H606: 0 | I606: 0 | J606: 0 | K606: 0 | L606: 0 | M606: 0 | N606: 0 | O606: 0 | P606: 0 | Q606: 0 | R606: 0 | S606: 0 | T606: 0 | U606: 0 | V606: 0 | W606: 0 | X606: 0 | Y606: 0 | Z606: 0 | AF606: 126 | AH606: N
...

Sheet Fanduel Export
AJ1: 1 = playing, 0 = not playing | AK1: Attempts * playing | AL1: Make Sure Backup QB's are excluded | AN1: 1 pt/ 25 yds | AQ1: pro rata off of # of passes | AR1: .5 pt/reception | AU1: 1 pt/10 yrds | AZ1: 1 pt/10 yrds
A2: Week 1 pulled 8-10 | O2: Trimmed Full name | T2: 2020 Passing | Y2: 2020 Receiving | AD2: 2020 Rushing | AO2: Algorithm Columns
A3: ID | B3: Position | C3: First Name | D3: Nickname | E3: Last Name | F3: FPPG | G3: Played | H3: Salary | I3: Game | J3: Team | K3: Opponent | L3: Injury Indicator | M3: Injury Detail | N3: Tier | O3: Full Name | P3: Lookup Name | Q3: Def Passing Yds/att | R3: Def Rushing yds/att | S3: Def Passing Yds/Reception | T3: Attempts/gm | U3: Yards/gm | V3: Yards/Attempt | W3: Passing TD | X3: Targets Per Game | Y3: Receptions per game | Z3: Yards per game | AA3: Yards/reception | AB3: Long | AC3: Receiving TDs | AD3: Rushes | AE3: Rushing Yards | AF3: Yards/Att | AG3: Rushing TDs | AH3: # of Passes | AI3: # of Runs | AJ3: Playing? | AK3: # of Attempts | AL3: Adjusted Projected Attempts | AM3: Pass Yards per completion | AN3: Passing yards | AO3: Targets per game | AP3: Projected Team Targets | AQ3: Adjusted Projected Targets | AR3: Receptions | AS3: Adjusted Projected Receptions | AT3: Yards per Reception | AU3: Receiving yards | AV3: Rushes | AW3: Team Rushes | AX3: Adjusted Projected Rushes | AY3: Yards per Attempt | AZ3: Rushing yards | BA3: Fanduel Pts | BB3: Value per $1k | BC3: Targets per $1K | BD3: Name | BE3: Salary | BF3: Position
A4: 47691-55050 | B4: RB | C4: Christian | D4: Christian McCaffrey | E4: McCaffrey | F4: 25.825001 | G4: 16 | H4: 10000 | I4: LV@CAR | J4: CAR | K4: LV | O4: =D4 -> Christian McCaffrey | P4: =IFERROR(VLOOKUP(O:O,'Name Bridge'!A:B,2,FALSE),O:O) -> Christian McCaffrey | Q4: =VLOOKUP($K4,'Defensive Stats'!$AC:$AH,2,FALSE) -> 7.8079848 | R4: =VLOOKUP($K4,'Defensive Stats'!$AC:$AH,4,FALSE) -> 3.8765432 | S4: =VLOOKUP($K4,'Defensive Stats'!$AC:$AH,6,FALSE) -> 12.186944 | T4: =IFERROR(VLOOKUP($P4,Passing!$C:$AF,9,FALSE)/VLOOKUP($P4,Passing!$C:$AF,5,FALSE),0) -> 0.125 | U4: =IFERROR(VLOOKUP($P4,Passing!$C:$AF,11,FALSE)/VLOOKUP($P4,Passing!$C:$AF,5,FALSE),0) -> 0 | V4: =IFERROR(VLOOKUP($P4,Passing!$C:$AF,18,FALSE),0) -> 0.0 | W4: =IFERROR(VLOOKUP($P4,Passing!$C:$AF,12,FALSE)/VLOOKUP($P4,Passing!$C:$AF,5,FALSE),0) -> 0 | X4: =IFERROR(IF(OR($B4="D",$B4="K"),0,VLOOKUP($P4,Receiving!$C:$T,7,FALSE)/VLOOKUP($P4,Receiving!$C:$T,5,FALSE)),0)*$AJ4 -> 8.875 | Y4: =IFERROR(VLOOKUP($P4,Receiving!$C:$T,8,FALSE)/VLOOKUP($P4,Receiving!$C:$T,5,FALSE),0) -> 7.25 | Z4: =IFERROR(VLOOKUP($P4,Receiving!$C:$T,10,FALSE)/VLOOKUP($P4,Receiving!$C:$T,5,FALSE),0) -> 62.8125 | AA4: =IFERROR(VLOOKUP($P4,Receiving!$C:$T,11,FALSE),0) -> 8.7 | AB4: =IFERROR(VLOOKUP($P4,Receiving!$C:$T,14,FALSE),0) -> 28 | AC4: =IFERROR(VLOOKUP($P4,Receiving!$C:$T,11,FALSE)/VLOOKUP($P4,Receiving!$C:$T,5,FALSE),0) -> 0.54375 | AD4: =IFERROR(VLOOKUP($P4,Rushing!$C:$P,7,FALSE)/VLOOKUP($P4,Rushing!$C:$P,5,FALSE),0) -> 17.9375 | AE4: =IFERROR(VLOOKUP($P4,Rushing!$C:$P,8,FALSE)/VLOOKUP($P4,Rushing!$C:$P,5,FALSE),0) -> 86.6875 | AF4: =IFERROR(VLOOKUP($P4,Rushing!$C:$P,12,FALSE),0) -> 4.8 | AG4: =IFERROR(VLOOKUP($P4,Rushing!$C:$P,9,FALSE)/VLOOKUP($P4,Rushing!$C:$P,5,FALSE),0) -> 0.9375 | AH4: =VLOOKUP($J4,'Vegas Odds'!$B:$S,18,FALSE) -> 42.975625 | AI4: =VLOOKUP($J4,'Vegas Odds'!$B:$S,17,FALSE) -> 20.224375 | AJ4: 1 | AK4: =T4*AJ4 -> 0.125 | AL4: =IF(AND(AJ4=1,B4="QB"),AH4,0) -> 0 | AM4: =V4/Team_Defense_Table[[#Totals],[Passing yds/att]]*'Fanduel Export'!Q4 -> 0 | AN4: =AM4*AK4 -> 0 | AO4: =IFERROR(IF(OR($B4="D",$B4="K"),0,VLOOKUP($P4,Receiving!$C:$T,7,FALSE)/VLOOKUP($P4,Receiving!$C:$T,5,FALSE)),0)*$AJ4 -> 8.875 | AP4: =SUMIF($J:$J,$J4,AO:AO) -> 35.359295 | AQ4: =AO4/AP4*AH4 -> 10.786659 | AR4: =Y4*AJ4 -> 7.25 | AS4: =IFERROR(AR4/AO4*AQ4,0) -> 8.8116372 | AT4: =AA4/Team_Defense_Table[[#Totals],[Yards per completion]]*'Fanduel Export'!S4 -> 9.9850473 | AU4: =AR4*AT4 -> 72.391593 | AV4: =AD4*AJ4 -> 17.9375 | AW4: =SUMIF($J:$J,$J4,AV:AV) -> 28.778312 | AX4: =IFERROR(AV4/AW4*AI4,0) -> 12.605838 | AY4: =AF4/Team_Defense_Table[[#Totals],[Rushing Y/A]]*R4 -> 4.3147611 | AZ4: =AY4*AV4 -> 77.396028 | BA4: =AN4/25+AU4/10+AZ4/10+AR4*0.5 -> 18.603762 | BB4: =BA4/(H4/1000) -> 1.8603762 | BC4: =AO4/(H4/1000) -> 0.8875 | BE4: =H4 -> 10000 | BF4: =B4 -> RB
A5: 47691-63115 | B5: QB | C5: Lamar | D5: Lamar Jackson | E5: Jackson | F5: 28.112 | G5: 15 | H5: 9400 | I5: CLE@BAL | J5: BAL | K5: CLE | O5: =D5 -> Lamar Jackson | P5: =IFERROR(VLOOKUP(O:O,'Name Bridge'!A:B,2,FALSE),O:O) -> Lamar Jackson | Q5: =VLOOKUP($K5,'Defensive Stats'!$AC:$AH,2,FALSE) -> 6.7641326 | R5: =VLOOKUP($K5,'Defensive Stats'!$AC:$AH,4,FALSE) -> 5 | S5: =VLOOKUP($K5,'Defensive Stats'!$AC:$AH,6,FALSE) -> 10.91195 | T5: =IFERROR(VLOOKUP($P5,Passing!$C:$AF,9,FALSE)/VLOOKUP($P5,Passing!$C:$AF,5,FALSE),0) -> 26.733333 | U5: =IFERROR(VLOOKUP($P5,Passing!$C:$AF,11,FALSE)/VLOOKUP($P5,Passing!$C:$AF,5,FALSE),0) -> 208.46667 | V5: =IFERROR(VLOOKUP($P5,Passing!$C:$AF,18,FALSE),0) -> 7.8 | W5: =IFERROR(VLOOKUP($P5,Passing!$C:$AF,12,FALSE)/VLOOKUP($P5,Passing!$C:$AF,5,FALSE),0) -> 2.4 | X5: =IFERROR(IF(OR($B5="D",$B5="K"),0,VLOOKUP($P5,Receiving!$C:$T,7,FALSE)/VLOOKUP($P5,Receiving!$C:$T,5,FALSE)),0)*$AJ5 -> 0 | Y5: =IFERROR(VLOOKUP($P5,Receiving!$C:$T,8,FALSE)/VLOOKUP($P5,Receiving!$C:$T,5,FALSE),0) -> 0 | Z5: =IFERROR(VLOOKUP($P5,Receiving!$C:$T,10,FALSE)/VLOOKUP($P5,Receiving!$C:$T,5,FALSE),0) -> 0 | AA5: =IFERROR(VLOOKUP($P5,Receiving!$C:$T,11,FALSE),0) -> 0 | AB5: =IFERROR(VLOOKUP($P5,Receiving!$C:$T,14,FALSE),0) -> 0 | AC5: =IFERROR(VLOOKUP($P5,Receiving!$C:$T,11,FALSE)/VLOOKUP($P5,Receiving!$C:$T,5,FALSE),0) -> 0 | AD5: =IFERROR(VLOOKUP($P5,Rushing!$C:$P,7,FALSE)/VLOOKUP($P5,Rushing!$C:$P,5,FALSE),0) -> 11.733333 | AE5: =IFERROR(VLOOKUP($P5,Rushing!$C:$P,8,FALSE)/VLOOKUP($P5,Rushing!$C:$P,5,FALSE),0) -> 80.4 | AF5: =IFERROR(VLOOKUP($P5,Rushing!$C:$P,12,FALSE),0) -> 6.9 | AG5: =IFERROR(VLOOKUP($P5,Rushing!$C:$P,9,FALSE)/VLOOKUP($P5,Rushing!$C:$P,5,FALSE),0) -> 0.46666667 | AH5: =VLOOKUP($J5,'Vegas Odds'!$B:$S,18,FALSE) -> 12.779864 | AI5: =VLOOKUP($J5,'Vegas Odds'!$B:$S,17,FALSE) -> 50.520136 | AJ5: 1 | AK5: =T5*AJ5 -> 26.733333 | AL5: =IF(AND(AJ5=1,B5="QB"),AH5,0) -> 12.779864 | AM5: =V5/Team_Defense_Table[[#Totals],[Passing yds/att]]*'Fanduel Export'!Q5 -> 7.8275825 | AN5: =AM5*AK5 -> 209.25737 | AO5: =IFERROR(IF(OR($B5="D",$B5="K"),0,VLOOKUP($P5,Receiving!$C:$T,7,FALSE)/VLOOKUP($P5,Receiving!$C:$T,5,FALSE)),0)*$AJ5 -> 0 | AP5: =SUMIF($J:$J,$J5,AO:AO) -> 19.229762 | AQ5: =AO5/AP5*AH5 -> 0 | AR5: =Y5*AJ5 -> 0 | AS5: =IFERROR(AR5/AO5*AQ5,0) -> 0 | AT5: =AA5/Team_Defense_Table[[#Totals],[Yards per completion]]*'Fanduel Export'!S5 -> 0 | AU5: =AR5*AT5 -> 0 | AV5: =AD5*AJ5 -> 11.733333 | AW5: =SUMIF($J:$J,$J5,AV:AV) -> 27.742262 | AX5: =IFERROR(AV5/AW5*AI5,0) -> 21.367025 | AY5: =AF5/Team_Defense_Table[[#Totals],[Rushing Y/A]]*R5 -> 8 | AZ5: =AY5*AV5 -> 93.866667 | BA5: =AN5/25+AU5/10+AZ5/10+AR5*0.5 -> 17.756962 | BB5: =BA5/(H5/1000) -> 1.8890385 | BC5: =AO5/(H5/1000) -> 0 | BD5: =D5 -> Lamar Jackson | BE5: =H5 -> 9400 | BF5: =B5 -> QB
A6: 47691-28573 | B6: WR | C6: Michael | D6: Michael Thomas | E6: Thomas | F6: 18.75625 | G6: 16 | H6: 8800 | I6: TB@NO | J6: NO | K6: TB | O6: =D6 -> Michael Thomas | P6: =IFERROR(VLOOKUP(O:O,'Name Bridge'!A:B,2,FALSE),O:O) -> Michael Thomas | Q6: =VLOOKUP($K6,'Defensive Stats'!$AC:$AH,2,FALSE) -> 6.5090361 | R6: =VLOOKUP($K6,'Defensive Stats'!$AC:$AH,4,FALSE) -> 3.2624309 | S6: =VLOOKUP($K6,'Defensive Stats'!$AC:$AH,6,FALSE) -> 10.593137 | T6: =IFERROR(VLOOKUP($P6,Passing!$C:$AF,9,FALSE)/VLOOKUP($P6,Passing!$C:$AF,5,FALSE),0) -> 0 | U6: =IFERROR(VLOOKUP($P6,Passing!$C:$AF,11,FALSE)/VLOOKUP($P6,Passing!$C:$AF,5,FALSE),0) -> 0 | V6: =IFERROR(VLOOKUP($P6,Passing!$C:$AF,18,FALSE),0) -> 0 | W6: =IFERROR(VLOOKUP($P6,Passing!$C:$AF,12,FALSE)/VLOOKUP($P6,Passing!$C:$AF,5,FALSE),0) -> 0 | X6: =IFERROR(IF(OR($B6="D",$B6="K"),0,VLOOKUP($P6,Receiving!$C:$T,7,FALSE)/VLOOKUP($P6,Receiving!$C:$T,5,FALSE)),0)*$AJ6 -> 11.5625 | Y6: =IFERROR(VLOOKUP($P6,Receiving!$C:$T,8,FALSE)/VLOOKUP($P6,Receiving!$C:$T,5,FALSE),0) -> 9.3125 | Z6: =IFERROR(VLOOKUP($P6,Receiving!$C:$T,10,FALSE)/VLOOKUP($P6,Receiving!$C:$T,5,FALSE),0) -> 107.8125 | AA6: =IFERROR(VLOOKUP($P6,Receiving!$C:$T,11,FALSE),0) -> 11.6 | AB6: =IFERROR(VLOOKUP($P6,Receiving!$C:$T,14,FALSE),0) -> 49 | AC6: =IFERROR(VLOOKUP($P6,Receiving!$C:$T,11,FALSE)/VLOOKUP($P6,Receiving!$C:$T,5,FALSE),0) -> 0.725 | AD6: =IFERROR(VLOOKUP($P6,Rushing!$C:$P,7,FALSE)/VLOOKUP($P6,Rushing!$C:$P,5,FALSE),0) -> 0.0625 | AE6: =IFERROR(VLOOKUP($P6,Rushing!$C:$P,8,FALSE)/VLOOKUP($P6,Rushing!$C:$P,5,FALSE),0) -> -0.5625 | AF6: =IFERROR(VLOOKUP($P6,Rushing!$C:$P,12,FALSE),0) -> -9.0 | AG6: =IFERROR(VLOOKUP($P6,Rushing!$C:$P,9,FALSE)/VLOOKUP($P6,Rushing!$C:$P,5,FALSE),0) -> 0 | AH6: =VLOOKUP($J6,'Vegas Odds'!$B:$S,18,FALSE) -> 41.698086 | AI6: =VLOOKUP($J6,'Vegas Odds'!$B:$S,17,FALSE) -> 21.901914 | AJ6: 1 | AK6: =T6*AJ6 -> 0 | AL6: =IF(AND(AJ6=1,B6="QB"),AH6,0) -> 0 | AM6: =V6/Team_Defense_Table[[#Totals],[Passing yds/att]]*'Fanduel Export'!Q6 -> 0 | AN6: =AM6*AK6 -> 0 | AO6: =IFERROR(IF(OR($B6="D",$B6="K"),0,VLOOKUP($P6,Receiving!$C:$T,7,FALSE)/VLOOKUP($P6,Receiving!$C:$T,5,FALSE)),0)*$AJ6 -> 11.5625 | AP6: =SUMIF($J:$J,$J6,AO:AO) -> 40.582776 | AQ6: =AO6/AP6*AH6 -> 11.880265 | AR6: =Y6*AJ6 -> 9.3125 | AS6: =IFERROR(AR6/AO6*AQ6,0) -> 9.5684292 | AT6: =AA6/Team_Defense_Table[[#Totals],[Yards per completion]]*'Fanduel Export'!S6 -> 11.572273 | AU6: =AR6*AT6 -> 107.76679 | AV6: =AD6*AJ6 -> 0.0625 | AW6: =SUMIF($J:$J,$J6,AV:AV) -> 30.380682 | AX6: =IFERROR(AV6/AW6*AI6,0) -> 0.045057239 | AY6: =AF6/Team_Defense_Table[[#Totals],[Rushing Y/A]]*R6 -> -6.8085515 | AZ6: =AY6*AV6 -> -0.42553447 | BA6: =AN6/25+AU6/10+AZ6/10+AR6*0.5 -> 15.390376 | BB6: =BA6/(H6/1000) -> 1.7489063 | BC6: =AO6/(H6/1000) -> 1.3139205 | BD6: =D6 -> Michael Thomas | BE6: =H6 -> 8800 | BF6: =B6 -> WR
A7: 47691-54140 | B7: RB | C7: Dalvin | D7: Dalvin Cook | E7: Cook | F7: 18.992857 | G7: 14 | H7: 8700 | I7: GB@MIN | J7: MIN | K7: GB | O7: =D7 -> Dalvin Cook | P7: =IFERROR(VLOOKUP(O:O,'Name Bridge'!A:B,2,FALSE),O:O) -> Dalvin Cook | Q7: =VLOOKUP($K7,'Defensive Stats'!$AC:$AH,2,FALSE) -> 6.8150183 | R7: =VLOOKUP($K7,'Defensive Stats'!$AC:$AH,4,FALSE) -> 4.6739659 | S7: =VLOOKUP($K7,'Defensive Stats'!$AC:$AH,6,FALSE) -> 11.41411 | T7: =IFERROR(VLOOKUP($P7,Passing!$C:$AF,9,FALSE)/VLOOKUP($P7,Passing!$C:$AF,5,FALSE),0) -> 0 | U7: =IFERROR(VLOOKUP($P7,Passing!$C:$AF,11,FALSE)/VLOOKUP($P7,Passing!$C:$AF,5,FALSE),0) -> 0 | V7: =IFERROR(VLOOKUP($P7,Passing!$C:$AF,18,FALSE),0) -> 0 | W7: =IFERROR(VLOOKUP($P7,Passing!$C:$AF,12,FALSE)/VLOOKUP($P7,Passing!$C:$AF,5,FALSE),0) -> 0 | X7: =IFERROR(IF(OR($B7="D",$B7="K"),0,VLOOKUP($P7,Receiving!$C:$T,7,FALSE)/VLOOKUP($P7,Receiving!$C:$T,5,FALSE)),0)*$AJ7 -> 4.5 | Y7: =IFERROR(VLOOKUP($P7,Receiving!$C:$T,8,FALSE)/VLOOKUP($P7,Receiving!$C:$T,5,FALSE),0) -> 3.7857143 | Z7: =IFERROR(VLOOKUP($P7,Receiving!$C:$T,10,FALSE)/VLOOKUP($P7,Receiving!$C:$T,5,FALSE),0) -> 37.071429 | AA7: =IFERROR(VLOOKUP($P7,Receiving!$C:$T,11,FALSE),0) -> 9.8 | AB7: =IFERROR(VLOOKUP($P7,Receiving!$C:$T,14,FALSE),0) -> 31 | AC7: =IFERROR(VLOOKUP($P7,Receiving!$C:$T,11,FALSE)/VLOOKUP($P7,Receiving!$C:$T,5,FALSE),0) -> 0.7 | AD7: =IFERROR(VLOOKUP($P7,Rushing!$C:$P,7,FALSE)/VLOOKUP($P7,Rushing!$C:$P,5,FALSE),0) -> 17.857143 | AE7: =IFERROR(VLOOKUP($P7,Rushing!$C:$P,8,FALSE)/VLOOKUP($P7,Rushing!$C:$P,5,FALSE),0) -> 81.071429 | AF7: =IFERROR(VLOOKUP($P7,Rushing!$C:$P,12,FALSE),0) -> 4.5 | AG7: =IFERROR(VLOOKUP($P7,Rushing!$C:$P,9,FALSE)/VLOOKUP($P7,Rushing!$C:$P,5,FALSE),0) -> 0.92857143 | AH7: =VLOOKUP($J7,'Vegas Odds'!$B:$S,18,FALSE) -> 24.965897 | AI7: =VLOOKUP($J7,'Vegas Odds'!$B:$S,17,FALSE) -> 34.134103 | AJ7: 1 | AK7: =T7*AJ7 -> 0 | AL7: =IF(AND(AJ7=1,B7="QB"),AH7,0) -> 0 | AM7: =V7/Team_Defense_Table[[#Totals],[Passing yds/att]]*'Fanduel Export'!Q7 -> 0 | AN7: =AM7*AK7 -> 0 | AO7: =IFERROR(IF(OR($B7="D",$B7="K"),0,VLOOKUP($P7,Receiving!$C:$T,7,FALSE)/VLOOKUP($P7,Receiving!$C:$T,5,FALSE)),0)*$AJ7 -> 4.5 | AP7: =SUMIF($J:$J,$J7,AO:AO) -> 26.827244 | AQ7: =AO7/AP7*AH7 -> 4.1877778 | AR7: =Y7*AJ7 -> 3.7857143 | AS7: =IFERROR(AR7/AO7*AQ7,0) -> 3.5230512 | AT7: =AA7/Team_Defense_Table[[#Totals],[Yards per completion]]*'Fanduel Export'!S7 -> 10.534264 | AU7: =AR7*AT7 -> 39.879716 | AV7: =AD7*AJ7 -> 17.857143 | AW7: =SUMIF($J:$J,$J7,AV:AV) -> 37.682784 | AX7: =IFERROR(AV7/AW7*AI7,0) -> 16.175492 | AY7: =AF7/Team_Defense_Table[[#Totals],[Rushing Y/A]]*R7 -> 4.8771818 | AZ7: =AY7*AV7 -> 87.092533 | BA7: =AN7/25+AU7/10+AZ7/10+AR7*0.5 -> 14.590082 | BB7: =BA7/(H7/1000) -> 1.6770209 | BC7: =AO7/(H7/1000) -> 0.51724138 | BD7: =D7 -> Dalvin Cook | BE7: =H7 -> 8700 | BF7: =B7 -> RB
A8: 47691-22015 | B8: QB | C8: Russell | D8: Russell Wilson | E8: Wilson | F8: 20.85 | G8: 16 | H8: 8400 | I8: SEA@ATL | J8: SEA | K8: ATL | O8: =D8 -> Russell Wilson | P8: =IFERROR(VLOOKUP(O:O,'Name Bridge'!A:B,2,FALSE),O:O) -> Russell Wilson | Q8: =VLOOKUP($K8,'Defensive Stats'!$AC:$AH,2,FALSE) -> 7.3097015 | R8: =VLOOKUP($K8,'Defensive Stats'!$AC:$AH,4,FALSE) -> 4.216152 | S8: =VLOOKUP($K8,'Defensive Stats'!$AC:$AH,6,FALSE) -> 11.162393 | T8: =IFERROR(VLOOKUP($P8,Passing!$C:$AF,9,FALSE)/VLOOKUP($P8,Passing!$C:$AF,5,FALSE),0) -> 32.25 | U8: =IFERROR(VLOOKUP($P8,Passing!$C:$AF,11,FALSE)/VLOOKUP($P8,Passing!$C:$AF,5,FALSE),0) -> 256.875 | V8: =IFERROR(VLOOKUP($P8,Passing!$C:$AF,18,FALSE),0) -> 8.0 | W8: =IFERROR(VLOOKUP($P8,Passing!$C:$AF,12,FALSE)/VLOOKUP($P8,Passing!$C:$AF,5,FALSE),0) -> 1.9375 | X8: =IFERROR(IF(OR($B8="D",$B8="K"),0,VLOOKUP($P8,Receiving!$C:$T,7,FALSE)/VLOOKUP($P8,Receiving!$C:$T,5,FALSE)),0)*$AJ8 -> 0 | Y8: =IFERROR(VLOOKUP($P8,Receiving!$C:$T,8,FALSE)/VLOOKUP($P8,Receiving!$C:$T,5,FALSE),0) -> 0 | Z8: =IFERROR(VLOOKUP($P8,Receiving!$C:$T,10,FALSE)/VLOOKUP($P8,Receiving!$C:$T,5,FALSE),0) -> 0 | AA8: =IFERROR(VLOOKUP($P8,Receiving!$C:$T,11,FALSE),0) -> 0 | AB8: =IFERROR(VLOOKUP($P8,Receiving!$C:$T,14,FALSE),0) -> 0 | AC8: =IFERROR(VLOOKUP($P8,Receiving!$C:$T,11,FALSE)/VLOOKUP($P8,Receiving!$C:$T,5,FALSE),0) -> 0 | AD8: =IFERROR(VLOOKUP($P8,Rushing!$C:$P,7,FALSE)/VLOOKUP($P8,Rushing!$C:$P,5,FALSE),0) -> 4.6875 | AE8: =IFERROR(VLOOKUP($P8,Rushing!$C:$P,8,FALSE)/VLOOKUP($P8,Rushing!$C:$P,5,FALSE),0) -> 21.375 | AF8: =IFERROR(VLOOKUP($P8,Rushing!$C:$P,12,FALSE),0) -> 4.6 | AG8: =IFERROR(VLOOKUP($P8,Rushing!$C:$P,9,FALSE)/VLOOKUP($P8,Rushing!$C:$P,5,FALSE),0) -> 0.1875 | AH8: =VLOOKUP($J8,'Vegas Odds'!$B:$S,18,FALSE) -> 34.284944 | AI8: =VLOOKUP($J8,'Vegas Odds'!$B:$S,17,FALSE) -> 30.315056 | AJ8: 1 | AK8: =T8*AJ8 -> 32.25 | AL8: =IF(AND(AJ8=1,B8="QB"),AH8,0) -> 34.284944 | AM8: =V8/Team_Defense_Table[[#Totals],[Passing yds/att]]*'Fanduel Export'!Q8 -> 8.6758207 | AN8: =AM8*AK8 -> 279.79522 | AO8: =IFERROR(IF(OR($B8="D",$B8="K"),0,VLOOKUP($P8,Receiving!$C:$T,7,FALSE)/VLOOKUP($P8,Receiving!$C:$T,5,FALSE)),0)*$AJ8 -> 0 | AP8: =SUMIF($J:$J,$J8,AO:AO) -> 34.263041 | AQ8: =AO8/AP8*AH8 -> 0 | AR8: =Y8*AJ8 -> 0 | AS8: =IFERROR(AR8/AO8*AQ8,0) -> 0 | AT8: =AA8/Team_Defense_Table[[#Totals],[Yards per completion]]*'Fanduel Export'!S8 -> 0 | AU8: =AR8*AT8 -> 0 | AV8: =AD8*AJ8 -> 4.6875 | AW8: =SUMIF($J:$J,$J8,AV:AV) -> 46.789286 | AX8: =IFERROR(AV8/AW8*AI8,0) -> 3.0370591 | AY8: =AF8/Team_Defense_Table[[#Totals],[Rushing Y/A]]*R8 -> 4.4972288 | AZ8: =AY8*AV8 -> 21.08076 | BA8: =AN8/25+AU8/10+AZ8/10+AR8*0.5 -> 13.299885 | BB8: =BA8/(H8/1000) -> 1.5833196 | BC8: =AO8/(H8/1000) -> 0 | BD8: =D8 -> Russell Wilson | BE8: =H8 -> 8400 | BF8: =B8 -> QB
A9: 47691-42104 | B9: RB | C9: Alvin | D9: Alvin Kamara | E9: Kamara | F9: 14.858572 | G9: 14 | H9: 8300 | I9: TB@NO | J9: NO | K9: TB | O9: =D9 -> Alvin Kamara | P9: =IFERROR(VLOOKUP(O:O,'Name Bridge'!A:B,2,FALSE),O:O) -> Alvin Kamara | Q9: =VLOOKUP($K9,'Defensive Stats'!$AC:$AH,2,FALSE) -> 6.5090361 | R9: =VLOOKUP($K9,'Defensive Stats'!$AC:$AH,4,FALSE) -> 3.2624309 | S9: =VLOOKUP($K9,'Defensive Stats'!$AC:$AH,6,FALSE) -> 10.593137 | T9: =IFERROR(VLOOKUP($P9,Passing!$C:$AF,9,FALSE)/VLOOKUP($P9,Passing!$C:$AF,5,FALSE),0) -> 0.071428571 | U9: =IFERROR(VLOOKUP($P9,Passing!$C:$AF,11,FALSE)/VLOOKUP($P9,Passing!$C:$AF,5,FALSE),0) -> 0.92857143 | V9: =IFERROR(VLOOKUP($P9,Passing!$C:$AF,18,FALSE),0) -> 13.0 | W9: =IFERROR(VLOOKUP($P9,Passing!$C:$AF,12,FALSE)/VLOOKUP($P9,Passing!$C:$AF,5,FALSE),0) -> 0 | X9: =IFERROR(IF(OR($B9="D",$B9="K"),0,VLOOKUP($P9,Receiving!$C:$T,7,FALSE)/VLOOKUP($P9,Receiving!$C:$T,5,FALSE)),0)*$AJ9 -> 6.9285714 | Y9: =IFERROR(VLOOKUP($P9,Receiving!$C:$T,8,FALSE)/VLOOKUP($P9,Receiving!$C:$T,5,FALSE),0) -> 5.7857143 | Z9: =IFERROR(VLOOKUP($P9,Receiving!$C:$T,10,FALSE)/VLOOKUP($P9,Receiving!$C:$T,5,FALSE),0) -> 38.071429 | AA9: =IFERROR(VLOOKUP($P9,Receiving!$C:$T,11,FALSE),0) -> 6.6 | AB9: =IFERROR(VLOOKUP($P9,Receiving!$C:$T,14,FALSE),0) -> 41 | AC9: =IFERROR(VLOOKUP($P9,Receiving!$C:$T,11,FALSE)/VLOOKUP($P9,Receiving!$C:$T,5,FALSE),0) -> 0.47142857 | AD9: =IFERROR(VLOOKUP($P9,Rushing!$C:$P,7,FALSE)/VLOOKUP($P9,Rushing!$C:$P,5,FALSE),0) -> 12.214286 | AE9: =IFERROR(VLOOKUP($P9,Rushing!$C:$P,8,FALSE)/VLOOKUP($P9,Rushing!$C:$P,5,FALSE),0) -> 56.928571 | AF9: =IFERROR(VLOOKUP($P9,Rushing!$C:$P,12,FALSE),0) -> 4.7 | AG9: =IFERROR(VLOOKUP($P9,Rushing!$C:$P,9,FALSE)/VLOOKUP($P9,Rushing!$C:$P,5,FALSE),0) -> 0.35714286 | AH9: =VLOOKUP($J9,'Vegas Odds'!$B:$S,18,FALSE) -> 41.698086 | AI9: =VLOOKUP($J9,'Vegas Odds'!$B:$S,17,FALSE) -> 21.901914 | AJ9: 1 | AK9: =T9*AJ9 -> 0.071428571 | AL9: =IF(AND(AJ9=1,B9="QB"),AH9,0) -> 0 | AM9: =V9/Team_Defense_Table[[#Totals],[Passing yds/att]]*'Fanduel Export'!Q9 -> 12.553967 | AN9: =AM9*AK9 -> 0.89671191 | AO9: =IFERROR(IF(OR($B9="D",$B9="K"),0,VLOOKUP($P9,Receiving!$C:$T,7,FALSE)/VLOOKUP($P9,Receiving!$C:$T,5,FALSE)),0)*$AJ9 -> 6.9285714 | AP9: =SUMIF($J:$J,$J9,AO:AO) -> 40.582776 | AQ9: =AO9/AP9*AH9 -> 7.1189848 | AR9: =Y9*AJ9 -> 5.7857143 | AS9: =IFERROR(AR9/AO9*AQ9,0) -> 5.9447192 | AT9: =AA9/Team_Defense_Table[[#Totals],[Yards per completion]]*'Fanduel Export'!S9 -> 6.5842241 | AU9: =AR9*AT9 -> 38.09444 | AV9: =AD9*AJ9 -> 12.214286 | AW9: =SUMIF($J:$J,$J9,AV:AV) -> 30.380682 | AX9: =IFERROR(AV9/AW9*AI9,0) -> 8.8054718 | AY9: =AF9/Team_Defense_Table[[#Totals],[Rushing Y/A]]*R9 -> 3.5555769 | AZ9: =AY9*AV9 -> 43.428832 | BA9: =AN9/25+AU9/10+AZ9/10+AR9*0.5 -> 11.081053 | BB9: =BA9/(H9/1000) -> 1.3350666 | BC9: =AO9/(H9/1000) -> 0.83476764 | BD9: =D9 -> Alvin Kamara | BE9: =H9 -> 8300 | BF9: =B9 -> RB
A10: 47691-72731 | B10: RB | C10: Josh | D10: Josh Jacobs | E10: Jacobs | F10: 13.969231 | G10: 13 | H10: 8200 | I10: LV@CAR | J10: LV | K10: CAR | O10: =D10 -> Josh Jacobs | P10: =IFERROR(VLOOKUP(O:O,'Name Bridge'!A:B,2,FALSE),O:O) -> Josh Jacobs | Q10: =VLOOKUP($K10,'Defensive Stats'!$AC:$AH,2,FALSE) -> 6.7941176 | R10: =VLOOKUP($K10,'Defensive Stats'!$AC:$AH,4,FALSE) -> 5.1595506 | S10: =VLOOKUP($K10,'Defensive Stats'!$AC:$AH,6,FALSE) -> 10.651297 | T10: =IFERROR(VLOOKUP($P10,Passing!$C:$AF,9,FALSE)/VLOOKUP($P10,Passing!$C:$AF,5,FALSE),0) -> 0 | U10: =IFERROR(VLOOKUP($P10,Passing!$C:$AF,11,FALSE)/VLOOKUP($P10,Passing!$C:$AF,5,FALSE),0) -> 0 | V10: =IFERROR(VLOOKUP($P10,Passing!$C:$AF,18,FALSE),0) -> 0 | W10: =IFERROR(VLOOKUP($P10,Passing!$C:$AF,12,FALSE)/VLOOKUP($P10,Passing!$C:$AF,5,FALSE),0) -> 0 | X10: =IFERROR(IF(OR($B10="D",$B10="K"),0,VLOOKUP($P10,Receiving!$C:$T,7,FALSE)/VLOOKUP($P10,Receiving!$C:$T,5,FALSE)),0)*$AJ10 -> 2.0769231 | Y10: =IFERROR(VLOOKUP($P10,Receiving!$C:$T,8,FALSE)/VLOOKUP($P10,Receiving!$C:$T,5,FALSE),0) -> 1.5384615 | Z10: =IFERROR(VLOOKUP($P10,Receiving!$C:$T,10,FALSE)/VLOOKUP($P10,Receiving!$C:$T,5,FALSE),0) -> 12.769231 | AA10: =IFERROR(VLOOKUP($P10,Receiving!$C:$T,11,FALSE),0) -> 8.3 | AB10: =IFERROR(VLOOKUP($P10,Receiving!$C:$T,14,FALSE),0) -> 28 | AC10: =IFERROR(VLOOKUP($P10,Receiving!$C:$T,11,FALSE)/VLOOKUP($P10,Receiving!$C:$T,5,FALSE),0) -> 0.63846154 | AD10: =IFERROR(VLOOKUP($P10,Rushing!$C:$P,7,FALSE)/VLOOKUP($P10,Rushing!$C:$P,5,FALSE),0) -> 18.615385 | AE10: =IFERROR(VLOOKUP($P10,Rushing!$C:$P,8,FALSE)/VLOOKUP($P10,Rushing!$C:$P,5,FALSE),0) -> 88.461538 | AF10: =IFERROR(VLOOKUP($P10,Rushing!$C:$P,12,FALSE),0) -> 4.8 | AG10: =IFERROR(VLOOKUP($P10,Rushing!$C:$P,9,FALSE)/VLOOKUP($P10,Rushing!$C:$P,5,FALSE),0) -> 0.53846154 | AH10: =VLOOKUP($J10,'Vegas Odds'!$B:$S,18,FALSE) -> 29.094444 | AI10: =VLOOKUP($J10,'Vegas Odds'!$B:$S,17,FALSE) -> 32.205556 | AJ10: 1 | AK10: =T10*AJ10 -> 0 | AL10: =IF(AND(AJ10=1,B10="QB"),AH10,0) -> 0 | AM10: =V10/Team_Defense_Table[[#Totals],[Passing yds/att]]*'Fanduel Export'!Q10 -> 0 | AN10: =AM10*AK10 -> 0 | AO10: =IFERROR(IF(OR($B10="D",$B10="K"),0,VLOOKUP($P10,Receiving!$C:$T,7,FALSE)/VLOOKUP($P10,Receiving!$C:$T,5,FALSE)),0)*$AJ10 -> 2.0769231 | AP10: =SUMIF($J:$J,$J10,AO:AO) -> 44.777285 | AQ10: =AO10/AP10*AH10 -> 1.3494994 | AR10: =Y10*AJ10 -> 1.5384615 | AS10: =IFERROR(AR10/AO10*AQ10,0) -> 0.99962921 | AT10: =AA10/Team_Defense_Table[[#Totals],[Yards per completion]]*'Fanduel Export'!S10 -> 8.3256213 | AU10: =AR10*AT10 -> 12.808648 | AV10: =AD10*AJ10 -> 18.615385 | AW10: =SUMIF($J:$J,$J10,AV:AV) -> 27.354941 | AX10: =IFERROR(AV10/AW10*AI10,0) -> 21.91629 | AY10: =AF10/Team_Defense_Table[[#Totals],[Rushing Y/A]]*R10 -> 5.7428041 | AZ10: =AY10*AV10 -> 106.90451 | BA10: =AN10/25+AU10/10+AZ10/10+AR10*0.5 -> 12.740546 | BB10: =BA10/(H10/1000) -> 1.5537252 | BC10: =AO10/(H10/1000) -> 0.2532833 | BD10: =D10 -> Josh Jacobs | BE10: =H10 -> 8200 | BF10: =B10 -> RB
A11: 47691-14190 | B11: WR | C11: Julio | D11: Julio Jones | E11: Jones | F11: 14.973334 | G11: 15 | H11: 8200 | I11: SEA@ATL | J11: ATL | K11: SEA | O11: =D11 -> Julio Jones | P11: =IFERROR(VLOOKUP(O:O,'Name Bridge'!A:B,2,FALSE),O:O) -> Julio Jones | Q11: =VLOOKUP($K11,'Defensive Stats'!$AC:$AH,2,FALSE) -> 7.0618729 | R11: =VLOOKUP($K11,'Defensive Stats'!$AC:$AH,4,FALSE) -> 4.8530928 | S11: =VLOOKUP($K11,'Defensive Stats'!$AC:$AH,6,FALSE) -> 11.02611 | T11: =IFERROR(VLOOKUP($P11,Passing!$C:$AF,9,FALSE)/VLOOKUP($P11,Passing!$C:$AF,5,FALSE),0) -> 0 | U11: =IFERROR(VLOOKUP($P11,Passing!$C:$AF,11,FALSE)/VLOOKUP($P11,Passing!$C:$AF,5,FALSE),0) -> 0 | V11: =IFERROR(VLOOKUP($P11,Passing!$C:$AF,18,FALSE),0) -> 0 | W11: =IFERROR(VLOOKUP($P11,Passing!$C:$AF,12,FALSE)/VLOOKUP($P11,Passing!$C:$AF,5,FALSE),0) -> 0 | X11: =IFERROR(IF(OR($B11="D",$B11="K"),0,VLOOKUP($P11,Receiving!$C:$T,7,FALSE)/VLOOKUP($P11,Receiving!$C:$T,5,FALSE)),0)*$AJ11 -> 10.466667 | Y11: =IFERROR(VLOOKUP($P11,Receiving!$C:$T,8,FALSE)/VLOOKUP($P11,Receiving!$C:$T,5,FALSE),0) -> 6.6 | Z11: =IFERROR(VLOOKUP($P11,Receiving!$C:$T,10,FALSE)/VLOOKUP($P11,Receiving!$C:$T,5,FALSE),0) -> 92.933333 | AA11: =IFERROR(VLOOKUP($P11,Receiving!$C:$T,11,FALSE),0) -> 14.1 | AB11: =IFERROR(VLOOKUP($P11,Receiving!$C:$T,14,FALSE),0) -> 54 | AC11: =IFERROR(VLOOKUP($P11,Receiving!$C:$T,11,FALSE)/VLOOKUP($P11,Receiving!$C:$T,5,FALSE),0) -> 0.94 | AD11: =IFERROR(VLOOKUP($P11,Rushing!$C:$P,7,FALSE)/VLOOKUP($P11,Rushing!$C:$P,5,FALSE),0) -> 0.13333333 | AE11: =IFERROR(VLOOKUP($P11,Rushing!$C:$P,8,FALSE)/VLOOKUP($P11,Rushing!$C:$P,5,FALSE),0) -> -0.2 | AF11: =IFERROR(VLOOKUP($P11,Rushing!$C:$P,12,FALSE),0) -> -1.5 | AG11: =IFERROR(VLOOKUP($P11,Rushing!$C:$P,9,FALSE)/VLOOKUP($P11,Rushing!$C:$P,5,FALSE),0) -> 0 | AH11: =VLOOKUP($J11,'Vegas Odds'!$B:$S,18,FALSE) -> 44.77407 | AI11: =VLOOKUP($J11,'Vegas Odds'!$B:$S,17,FALSE) -> 21.32593 | AJ11: 1 | AK11: =T11*AJ11 -> 0 | AL11: =IF(AND(AJ11=1,B11="QB"),AH11,0) -> 0 | AM11: =V11/Team_Defense_Table[[#Totals],[Passing yds/att]]*'Fanduel Export'!Q11 -> 0 | AN11: =AM11*AL11 -> 0 | AO11: =IFERROR(IF(OR($B11="D",$B11="K"),0,VLOOKUP($P11,Receiving!$C:$T,7,FALSE)/VLOOKUP($P11,Receiving!$C:$T,5,FALSE)),0)*$AJ11 -> 10.466667 | AP11: =SUMIF($J:$J,$J11,AO:AO) -> 36.576282 | AQ11: =AO11/AP11*AH11 -> 12.812545 | AR11: =Y11*AJ11 -> 6.6 | AS11: =IFERROR(AR11/AO11*AQ11,0) -> 8.0792483 | AT11: =AA11/Team_Defense_Table[[#Totals],[Yards per completion]]*'Fanduel Export'!S11 -> 14.641228 | AU11: =AS11*AT11 -> 118.29011 | AV11: =AD11*AJ11 -> 0.13333333 | AW11: =SUMIF($J:$J,$J11,AV:AV) -> 30.87587 | AX11: =IFERROR(AV11/AW11*AI11,0) -> 0.092093188 | AY11: =AF11/Team_Defense_Table[[#Totals],[Rushing Y/A]]*R11 -> -1.6880323 | AZ11: =AY11*AX11 -> -0.15545627 | BA11: =AN11/25+AU11/10+AZ11/10+AR11*0.5 -> 15.113466 | BB11: =BA11/(H11/1000) -> 1.8431056 | BC11: =AO11/(H11/1000) -> 1.2764228 | BD11: =D11 -> Julio Jones | BE11: =H11 -> 8200 | BF11: =B11 -> WR
A12: 47691-6504 | B12: QB | C12: Drew | D12: Drew Brees | E12: Brees | F12: 20.796363 | G12: 11 | H12: 8100 | I12: TB@NO | J12: NO | K12: TB | O12: =D12 -> Drew Brees | P12: =IFERROR(VLOOKUP(O:O,'Name Bridge'!A:B,2,FALSE),O:O) -> Drew Brees | Q12: =VLOOKUP($K12,'Defensive Stats'!$AC:$AH,2,FALSE) -> 6.5090361 | R12: =VLOOKUP($K12,'Defensive Stats'!$AC:$AH,4,FALSE) -> 3.2624309 | S12: =VLOOKUP($K12,'Defensive Stats'!$AC:$AH,6,FALSE) -> 10.593137 | T12: =IFERROR(VLOOKUP($P12,Passing!$C:$AF,9,FALSE)/VLOOKUP($P12,Passing!$C:$AF,5,FALSE),0) -> 34.363636 | U12: =IFERROR(VLOOKUP($P12,Passing!$C:$AF,11,FALSE)/VLOOKUP($P12,Passing!$C:$AF,5,FALSE),0) -> 270.81818 | V12: =IFERROR(VLOOKUP($P12,Passing!$C:$AF,18,FALSE),0) -> 7.9 | W12: =IFERROR(VLOOKUP($P12,Passing!$C:$AF,12,FALSE)/VLOOKUP($P12,Passing!$C:$AF,5,FALSE),0) -> 2.4545455 | X12: =IFERROR(IF(OR($B12="D",$B12="K"),0,VLOOKUP($P12,Receiving!$C:$T,7,FALSE)/VLOOKUP($P12,Receiving!$C:$T,5,FALSE)),0)*$AJ12 -> 0 | Y12: =IFERROR(VLOOKUP($P12,Receiving!$C:$T,8,FALSE)/VLOOKUP($P12,Receiving!$C:$T,5,FALSE),0) -> 0 | Z12: =IFERROR(VLOOKUP($P12,Receiving!$C:$T,10,FALSE)/VLOOKUP($P12,Receiving!$C:$T,5,FALSE),0) -> 0 | AA12: =IFERROR(VLOOKUP($P12,Receiving!$C:$T,11,FALSE),0) -> 0 | AB12: =IFERROR(VLOOKUP($P12,Receiving!$C:$T,14,FALSE),0) -> 0 | AC12: =IFERROR(VLOOKUP($P12,Receiving!$C:$T,11,FALSE)/VLOOKUP($P12,Receiving!$C:$T,5,FALSE),0) -> 0 | AD12: =IFERROR(VLOOKUP($P12,Rushing!$C:$P,7,FALSE)/VLOOKUP($P12,Rushing!$C:$P,5,FALSE),0) -> 0.81818182 | AE12: =IFERROR(VLOOKUP($P12,Rushing!$C:$P,8,FALSE)/VLOOKUP($P12,Rushing!$C:$P,5,FALSE),0) -> -0.36363636 | AF12: =IFERROR(VLOOKUP($P12,Rushing!$C:$P,12,FALSE),0) -> -0.4 | AG12: =IFERROR(VLOOKUP($P12,Rushing!$C:$P,9,FALSE)/VLOOKUP($P12,Rushing!$C:$P,5,FALSE),0) -> 0.090909091 | AH12: =VLOOKUP($J12,'Vegas Odds'!$B:$S,18,FALSE) -> 41.698086 | AI12: =VLOOKUP($J12,'Vegas Odds'!$B:$S,17,FALSE) -> 21.901914 | AJ12: 1 | AK12: =T12*AJ12 -> 34.363636 | AL12: =IF(AND(AJ12=1,B12="QB"),AH12,0) -> 41.698086 | AM12: =V12/Team_Defense_Table[[#Totals],[Passing yds/att]]*'Fanduel Export'!Q12 -> 7.628949 | AN12: =AM12*AL12 -> 318.11257 | AO12: =IFERROR(IF(OR($B12="D",$B12="K"),0,VLOOKUP($P12,Receiving!$C:$T,7,FALSE)/VLOOKUP($P12,Receiving!$C:$T,5,FALSE)),0)*$AJ12 -> 0 | AP12: =SUMIF($J:$J,$J12,AO:AO) -> 40.582776 | AQ12: =AO12/AP12*AH12 -> 0 | AR12: =Y12*AJ12 -> 0 | AS12: =IFERROR(AR12/AO12*AQ12,0) -> 0 | AT12: =AA12/Team_Defense_Table[[#Totals],[Yards per completion]]*'Fanduel Export'!S12 -> 0 | AU12: =AS12*AT12 -> 0 | AV12: =AD12*AJ12 -> 0.81818182 | AW12: =SUMIF($J:$J,$J12,AV:AV) -> 30.380682 | AX12: =IFERROR(AV12/AW12*AI12,0) -> 0.58984022 | AY12: =AF12/Team_Defense_Table[[#Totals],[Rushing Y/A]]*R12 -> -0.30260229 | AZ12: =AY12*AX12 -> -0.178487 | BA12: =AN12/25+AU12/10+AZ12/10+AR12*0.5 -> 12.706654 | BB12: =BA12/(H12/1000) -> 1.5687227 | BC12: =AO12/(H12/1000) -> 0 | BD12: =D12 -> Drew Brees | BE12: =H12 -> 8100 | BF12: =B12 -> QB
A13: 47691-45889 | B13: WR | C13: Davante | D13: Davante Adams | E13: Adams | F13: 14.266666 | G13: 12 | H13: 8000 | I13: GB@MIN | J13: GB | K13: MIN | O13: =D13 -> Davante Adams | P13: =IFERROR(VLOOKUP(O:O,'Name Bridge'!A:B,2,FALSE),O:O) -> Davante Adams | Q13: =VLOOKUP($K13,'Defensive Stats'!$AC:$AH,2,FALSE) -> 6.21797 | R13: =VLOOKUP($K13,'Defensive Stats'!$AC:$AH,4,FALSE) -> 4.2772277 | S13: =VLOOKUP($K13,'Defensive Stats'!$AC:$AH,6,FALSE) -> 9.4847716 | T13: =IFERROR(VLOOKUP($P13,Passing!$C:$AF,9,FALSE)/VLOOKUP($P13,Passing!$C:$AF,5,FALSE),0) -> 0 | U13: =IFERROR(VLOOKUP($P13,Passing!$C:$AF,11,FALSE)/VLOOKUP($P13,Passing!$C:$AF,5,FALSE),0) -> 0 | V13: =IFERROR(VLOOKUP($P13,Passing!$C:$AF,18,FALSE),0) -> 0 | W13: =IFERROR(VLOOKUP($P13,Passing!$C:$AF,12,FALSE)/VLOOKUP($P13,Passing!$C:$AF,5,FALSE),0) -> 0 | X13: =IFERROR(IF(OR($B13="D",$B13="K"),0,VLOOKUP($P13,Receiving!$C:$T,7,FALSE)/VLOOKUP($P13,Receiving!$C:$T,5,FALSE)),0)*$AJ13 -> 10.583333 | Y13: =IFERROR(VLOOKUP($P13,Receiving!$C:$T,8,FALSE)/VLOOKUP($P13,Receiving!$C:$T,5,FALSE),0) -> 6.9166667 | Z13: =IFERROR(VLOOKUP($P13,Receiving!$C:$T,10,FALSE)/VLOOKUP($P13,Receiving!$C:$T,5,FALSE),0) -> 83.083333 | AA13: =IFERROR(VLOOKUP($P13,Receiving!$C:$T,11,FALSE),0) -> 12 | AB13: =IFERROR(VLOOKUP($P13,Receiving!$C:$T,14,FALSE),0) -> 58 | AC13: =IFERROR(VLOOKUP($P13,Receiving!$C:$T,11,FALSE)/VLOOKUP($P13,Receiving!$C:$T,5,FALSE),0) -> 1 | AD13: =IFERROR(VLOOKUP($P13,Rushing!$C:$P,7,FALSE)/VLOOKUP($P13,Rushing!$C:$P,5,FALSE),0) -> 0 | AE13: =IFERROR(VLOOKUP($P13,Rushing!$C:$P,8,FALSE)/VLOOKUP($P13,Rushing!$C:$P,5,FALSE),0) -> 0 | AF13: =IFERROR(VLOOKUP($P13,Rushing!$C:$P,12,FALSE),0) -> 0 | AG13: =IFERROR(VLOOKUP($P13,Rushing!$C:$P,9,FALSE)/VLOOKUP($P13,Rushing!$C:$P,5,FALSE),0) -> 0 | AH13: =VLOOKUP($J13,'Vegas Odds'!$B:$S,18,FALSE) -> 37.252589 | AI13: =VLOOKUP($J13,'Vegas Odds'!$B:$S,17,FALSE) -> 23.147411 | AJ13: 1 | AK13: =T13*AJ13 -> 0 | AL13: =IF(AND(AJ13=1,B13="QB"),AH13,0) -> 0 | AM13: =V13/Team_Defense_Table[[#Totals],[Passing yds/att]]*'Fanduel Export'!Q13 -> 0 | AN13: =AM13*AL13 -> 0 | AO13: =IFERROR(IF(OR($B13="D",$B13="K"),0,VLOOKUP($P13,Receiving!$C:$T,7,FALSE)/VLOOKUP($P13,Receiving!$C:$T,5,FALSE)),0)*$AJ13 -> 10.583333 | AP13: =SUMIF($J:$J,$J13,AO:AO) -> 34.582089 | AQ13: =AO13/AP13*AH13 -> 11.4006 | AR13: =Y13*AJ13 -> 6.9166667 | AS13: =IFERROR(AR13/AO13*AQ13,0) -> 7.450786 | AT13: =AA13/Team_Defense_Table[[#Totals],[Yards per completion]]*'Fanduel Export'!S13 -> 10.718751 | AU13: =AS13*AT13 -> 79.863122 | AV13: =AD13*AJ13 -> 0 | AW13: =SUMIF($J:$J,$J13,AV:AV) -> 28.472024 | AX13: =IFERROR(AV13/AW13*AI13,0) -> 0 | AY13: =AF13/Team_Defense_Table[[#Totals],[Rushing Y/A]]*R13 -> 0 | AZ13: =AY13*AX13 -> 0 | BA13: =AN13/25+AU13/10+AZ13/10+AR13*0.5 -> 11.444646 | BB13: =BA13/(H13/1000) -> 1.4305807 | BC13: =AO13/(H13/1000) -> 1.3229167 | BD13: =D13 -> Davante Adams | BE13: =H13 -> 8000 | BF13: =B13 -> WR
A14: 47691-39793 | B14: TE | C14: George | D14: George Kittle | E14: Kittle | F14: 12.857143 | G14: 14 | H14: 8000 | I14: ARI@SF | J14: SF | K14: ARI | O14: =D14 -> George Kittle | P14: =IFERROR(VLOOKUP(O:O,'Name Bridge'!A:B,2,FALSE),O:O) -> George Kittle | Q14: =VLOOKUP($K14,'Defensive Stats'!$AC:$AH,2,FALSE) -> 7.5041597 | R14: =VLOOKUP($K14,'Defensive Stats'!$AC:$AH,4,FALSE) -> 4.3781321 | S14: =VLOOKUP($K14,'Defensive Stats'!$AC:$AH,6,FALSE) -> 10.712589 | T14: =IFERROR(VLOOKUP($P14,Passing!$C:$AF,9,FALSE)/VLOOKUP($P14,Passing!$C:$AF,5,FALSE),0) -> 0 | U14: =IFERROR(VLOOKUP($P14,Passing!$C:$AF,11,FALSE)/VLOOKUP($P14,Passing!$C:$AF,5,FALSE),0) -> 0 | V14: =IFERROR(VLOOKUP($P14,Passing!$C:$AF,18,FALSE),0) -> 0 | W14: =IFERROR(VLOOKUP($P14,Passing!$C:$AF,12,FALSE)/VLOOKUP($P14,Passing!$C:$AF,5,FALSE),0) -> 0 | X14: =IFERROR(IF(OR($B14="D",$B14="K"),0,VLOOKUP($P14,Receiving!$C:$T,7,FALSE)/VLOOKUP($P14,Receiving!$C:$T,5,FALSE)),0)*$AJ14 -> 7.6428571 | Y14: =IFERROR(VLOOKUP($P14,Receiving!$C:$T,8,FALSE)/VLOOKUP($P14,Receiving!$C:$T,5,FALSE),0) -> 6.0714286 | Z14: =IFERROR(VLOOKUP($P14,Receiving!$C:$T,10,FALSE)/VLOOKUP($P14,Receiving!$C:$T,5,FALSE),0) -> 75.214286 | AA14: =IFERROR(VLOOKUP($P14,Receiving!$C:$T,11,FALSE),0) -> 12.4 | AB14: =IFERROR(VLOOKUP($P14,Receiving!$C:$T,14,FALSE),0) -> 61 | AC14: =IFERROR(VLOOKUP($P14,Receiving!$C:$T,11,FALSE)/VLOOKUP($P14,Receiving!$C:$T,5,FALSE),0) -> 0.88571429 | AD14: =IFERROR(VLOOKUP($P14,Rushing!$C:$P,7,FALSE)/VLOOKUP($P14,Rushing!$C:$P,5,FALSE),0) -> 0.35714286 | AE14: =IFERROR(VLOOKUP($P14,Rushing!$C:$P,8,FALSE)/VLOOKUP($P14,Rushing!$C:$P,5,FALSE),0) -> 1.5714286 | AF14: =IFERROR(VLOOKUP($P14,Rushing!$C:$P,12,FALSE),0) -> 4.4 | AG14: =IFERROR(VLOOKUP($P14,Rushing!$C:$P,9,FALSE)/VLOOKUP($P14,Rushing!$C:$P,5,FALSE),0) -> 0 | AH14: =VLOOKUP($J14,'Vegas Odds'!$B:$S,18,FALSE) -> 26.807585 | AI14: =VLOOKUP($J14,'Vegas Odds'!$B:$S,17,FALSE) -> 33.392415 | AJ14: 1 | AK14: =T14*AJ14 -> 0 | AL14: =IF(AND(AJ14=1,B14="QB"),AH14,0) -> 0 | AM14: =V14/Team_Defense_Table[[#Totals],[Passing yds/att]]*'Fanduel Export'!Q14 -> 0 | AN14: =AM14*AL14 -> 0 | AO14: =IFERROR(IF(OR($B14="D",$B14="K"),0,VLOOKUP($P14,Receiving!$C:$T,7,FALSE)/VLOOKUP($P14,Receiving!$C:$T,5,FALSE)),0)*$AJ14 -> 7.6428571 | AP14: =SUMIF($J:$J,$J14,AO:AO) -> 33.34026 | AQ14: =AO14/AP14*AH14 -> 6.1453193 | AR14: =Y14*AJ14 -> 6.0714286 | AS14: =IFERROR(AR14/AO14*AQ14,0) -> 4.8817957 | AT14: =AA14/Team_Defense_Table[[#Totals],[Yards per completion]]*'Fanduel Export'!S14 -> 12.509853 | AU14: =AS14*AT14 -> 61.070547 | AV14: =AD14*AJ14 -> 0.35714286 | AW14: =SUMIF($J:$J,$J14,AV:AV) -> 29.127327 | AX14: =IFERROR(AV14/AW14*AI14,0) -> 0.40943896 | AY14: =AF14/Team_Defense_Table[[#Totals],[Rushing Y/A]]*R14 -> 4.4669638 | AZ14: =AY14*AX14 -> 1.828949 | BA14: =AN14/25+AU14/10+AZ14/10+AR14*0.5 -> 9.3256639 | BB14: =BA14/(H14/1000) -> 1.165708 | BC14: =AO14/(H14/1000) -> 0.95535714 | BD14: =D14 -> George Kittle | BE14: =H14 -> 8000 | BF14: =B14 -> TE
A15: 47691-62239 | B15: QB | C15: Josh | D15: Josh Allen | E15: Allen | F15: 18.5975 | G15: 16 | H15: 7900 | I15: NYJ@BUF | J15: BUF | K15: NYJ | O15: =D15 -> Josh Allen | P15: =IFERROR(VLOOKUP(O:O,'Name Bridge'!A:B,2,FALSE),O:O) -> Josh Allen | Q15: =VLOOKUP($K15,'Defensive Stats'!$AC:$AH,2,FALSE) -> 6.4598291 | R15: =VLOOKUP($K15,'Defensive Stats'!$AC:$AH,4,FALSE) -> 3.3357314 | S15: =VLOOKUP($K15,'Defensive Stats'!$AC:$AH,6,FALSE) -> 10.410468 | T15: =IFERROR(VLOOKUP($P15,Passing!$C:$AF,9,FALSE)/VLOOKUP($P15,Passing!$C:$AF,5,FALSE),0) -> 28.8125 | U15: =IFERROR(VLOOKUP($P15,Passing!$C:$AF,11,FALSE)/VLOOKUP($P15,Passing!$C:$AF,5,FALSE),0) -> 193.0625 | V15: =IFERROR(VLOOKUP($P15,Passing!$C:$AF,18,FALSE),0) -> 6.7 | W15: =IFERROR(VLOOKUP($P15,Passing!$C:$AF,12,FALSE)/VLOOKUP($P15,Passing!$C:$AF,5,FALSE),0) -> 1.25 | X15: =IFERROR(IF(OR($B15="D",$B15="K"),0,VLOOKUP($P15,Receiving!$C:$T,7,FALSE)/VLOOKUP($P15,Receiving!$C:$T,5,FALSE)),0)*$AJ15 -> 0 | Y15: =IFERROR(VLOOKUP($P15,Receiving!$C:$T,8,FALSE)/VLOOKUP($P15,Receiving!$C:$T,5,FALSE),0) -> 0 | Z15: =IFERROR(VLOOKUP($P15,Receiving!$C:$T,10,FALSE)/VLOOKUP($P15,Receiving!$C:$T,5,FALSE),0) -> 0 | AA15: =IFERROR(VLOOKUP($P15,Receiving!$C:$T,11,FALSE),0) -> 0 | AB15: =IFERROR(VLOOKUP($P15,Receiving!$C:$T,14,FALSE),0) -> 0 | AC15: =IFERROR(VLOOKUP($P15,Receiving!$C:$T,11,FALSE)/VLOOKUP($P15,Receiving!$C:$T,5,FALSE),0) -> 0 | AD15: =IFERROR(VLOOKUP($P15,Rushing!$C:$P,7,FALSE)/VLOOKUP($P15,Rushing!$C:$P,5,FALSE),0) -> 6.8125 | AE15: =IFERROR(VLOOKUP($P15,Rushing!$C:$P,8,FALSE)/VLOOKUP($P15,Rushing!$C:$P,5,FALSE),0) -> 31.875 | AF15: =IFERROR(VLOOKUP($P15,Rushing!$C:$P,12,FALSE),0) -> 4.7 | AG15: =IFERROR(VLOOKUP($P15,Rushing!$C:$P,9,FALSE)/VLOOKUP($P15,Rushing!$C:$P,5,FALSE),0) -> 0.5625 | AH15: =VLOOKUP($J15,'Vegas Odds'!$B:$S,18,FALSE) -> 31.210567 | AI15: =VLOOKUP($J15,'Vegas Odds'!$B:$S,17,FALSE) -> 27.689433 | AJ15: 1 | AK15: =T15*AJ15 -> 28.8125 | AL15: =IF(AND(AJ15=1,B15="QB"),AH15,0) -> 31.210567 | AM15: =V15/Team_Defense_Table[[#Totals],[Passing yds/att]]*'Fanduel Export'!Q15 -> 6.4212084 | AN15: =AM15*AL15 -> 200.40956 | AO15: =IFERROR(IF(OR($B15="D",$B15="K"),0,VLOOKUP($P15,Receiving!$C:$T,7,FALSE)/VLOOKUP($P15,Receiving!$C:$T,5,FALSE)),0)*$AJ15 -> 0 | AP15: =SUMIF($J:$J,$J15,AO:AO) -> 43.80338 | AQ15: =AO15/AP15*AH15 -> 0 | AR15: =Y15*AJ15 -> 0 | AS15: =IFERROR(AR15/AO15*AQ15,0) -> 0 | AT15: =AA15/Team_Defense_Table[[#Totals],[Yards per completion]]*'Fanduel Export'!S15 -> 0 | AU15: =AS15*AT15 -> 0 | AV15: =AD15*AJ15 -> 6.8125 | AW15: =SUMIF($J:$J,$J15,AV:AV) -> 25.532284 | AX15: =IFERROR(AV15/AW15*AI15,0) -> 7.3880682 | AY15: =AF15/Team_Defense_Table[[#Totals],[Rushing Y/A]]*R15 -> 3.6354638 | AZ15: =AY15*AX15 -> 26.859055 | BA15: =AN15/25+AU15/10+AZ15/10+AR15*0.5 -> 10.702288 | BB15: =BA15/(H15/1000) -> 1.35472 | BC15: =AO15/(H15/1000) -> 0 | BD15: =D15 -> Josh Allen | BE15: =H15 -> 7900 | BF15: =B15 -> QB
A16: 47691-16606 | B16: WR | C16: DeAndre | D16: DeAndre Hopkins | E16: Hopkins | F16: 14.502666 | G16: 15 | H16: 7800 | I16: ARI@SF | J16: ARI | K16: SF | O16: =D16 -> DeAndre Hopkins | P16: =IFERROR(VLOOKUP(O:O,'Name Bridge'!A:B,2,FALSE),O:O) -> DeAndre Hopkins | Q16: =VLOOKUP($K16,'Defensive Stats'!$AC:$AH,2,FALSE) -> 5.2157996 | R16: =VLOOKUP($K16,'Defensive Stats'!$AC:$AH,4,FALSE) -> 4.4937656 | S16: =VLOOKUP($K16,'Defensive Stats'!$AC:$AH,6,FALSE) -> 8.5125786 | T16: =IFERROR(VLOOKUP($P16,Passing!$C:$AF,9,FALSE)/VLOOKUP($P16,Passing!$C:$AF,5,FALSE),0) -> 0.13333333 | U16: =IFERROR(VLOOKUP($P16,Passing!$C:$AF,11,FALSE)/VLOOKUP($P16,Passing!$C:$AF,5,FALSE),0) -> 0.4 | V16: =IFERROR(VLOOKUP($P16,Passing!$C:$AF,18,FALSE),0) -> 3.0 | W16: =IFERROR(VLOOKUP($P16,Passing!$C:$AF,12,FALSE)/VLOOKUP($P16,Passing!$C:$AF,5,FALSE),0) -> 0.066666667 | X16: =IFERROR(IF(OR($B16="D",$B16="K"),0,VLOOKUP($P16,Receiving!$C:$T,7,FALSE)/VLOOKUP($P16,Receiving!$C:$T,5,FALSE)),0)*$AJ16 -> 10 | Y16: =IFERROR(VLOOKUP($P16,Receiving!$C:$T,8,FALSE)/VLOOKUP($P16,Receiving!$C:$T,5,FALSE),0) -> 6.9333333 | Z16: =IFERROR(VLOOKUP($P16,Receiving!$C:$T,10,FALSE)/VLOOKUP($P16,Receiving!$C:$T,5,FALSE),0) -> 77.666667 | AA16: =IFERROR(VLOOKUP($P16,Receiving!$C:$T,11,FALSE),0) -> 11.2 | AB16: =IFERROR(VLOOKUP($P16,Receiving!$C:$T,14,FALSE),0) -> 43 | AC16: =IFERROR(VLOOKUP($P16,Receiving!$C:$T,11,FALSE)/VLOOKUP($P16,Receiving!$C:$T,5,FALSE),0) -> 0.74666667 | AD16: =IFERROR(VLOOKUP($P16,Rushing!$C:$P,7,FALSE)/VLOOKUP($P16,Rushing!$C:$P,5,FALSE),0) -> 0.13333333 | AE16: =IFERROR(VLOOKUP($P16,Rushing!$C:$P,8,FALSE)/VLOOKUP($P16,Rushing!$C:$P,5,FALSE),0) -> 1.2 | AF16: =IFERROR(VLOOKUP($P16,Rushing!$C:$P,12,FALSE),0) -> 9.0 | AG16: =IFERROR(VLOOKUP($P16,Rushing!$C:$P,9,FALSE)/VLOOKUP($P16,Rushing!$C:$P,5,FALSE),0) -> 0 | AH16: =VLOOKUP($J16,'Vegas Odds'!$B:$S,18,FALSE) -> 35.724841 | AI16: =VLOOKUP($J16,'Vegas Odds'!$B:$S,17,FALSE) -> 23.675159 | AJ16: 1 | AK16: =T16*AJ16 -> 0.13333333 | AL16: =IF(AND(AJ16=1,B16="QB"),AH16,0) -> 0 | AM16: =V16/Team_Defense_Table[[#Totals],[Passing yds/att]]*'Fanduel Export'!Q16 -> 2.3214701 | AN16: =AM16*AL16 -> 0 | AO16: =IFERROR(IF(OR($B16="D",$B16="K"),0,VLOOKUP($P16,Receiving!$C:$T,7,FALSE)/VLOOKUP($P16,Receiving!$C:$T,5,FALSE)),0)*$AJ16 -> 10 | AP16: =SUMIF($J:$J,$J16,AO:AO) -> 43.039806 | AQ16: =AO16/AP16*AH16 -> 8.3004187 | AR16: =Y16*AJ16 -> 6.9333333 | AS16: =IFERROR(AR16/AO16*AQ16,0) -> 5.754957 | AT16: =AA16/Team_Defense_Table[[#Totals],[Yards per completion]]*'Fanduel Export'!S16 -> 8.9787366 | AU16: =AS16*AT16 -> 51.672243 | AV16: =AD16*AJ16 -> 0.13333333 | AW16: =SUMIF($J:$J,$J16,AV:AV) -> 26.173306 | AX16: =IFERROR(AV16/AW16*AI16,0) -> 0.12060715 | AY16: =AF16/Team_Defense_Table[[#Totals],[Rushing Y/A]]*R16 -> 9.3782934 | AZ16: =AY16*AX16 -> 1.1310892 | BA16: =AN16/25+AU16/10+AZ16/10+AR16*0.5 -> 8.7469999 | BB16: =BA16/(H16/1000) -> 1.1214102 | BC16: =AO16/(H16/1000) -> 1.2820513 | BD16: =D16 -> DeAndre Hopkins | BE16: =H16 -> 7800 | BF16: =B16 -> WR
A17: 47691-6616 | B17: QB | C17: Matt | D17: Matt Ryan | E17: Ryan | F17: 18.756 | G17: 15 | H17: 7800 | I17: SEA@ATL | J17: ATL | K17: SEA | O17: =D17 -> Matt Ryan | P17: =IFERROR(VLOOKUP(O:O,'Name Bridge'!A:B,2,FALSE),O:O) -> Matt Ryan | Q17: =VLOOKUP($K17,'Defensive Stats'!$AC:$AH,2,FALSE) -> 7.0618729 | R17: =VLOOKUP($K17,'Defensive Stats'!$AC:$AH,4,FALSE) -> 4.8530928 | S17: =VLOOKUP($K17,'Defensive Stats'!$AC:$AH,6,FALSE) -> 11.02611 | T17: =IFERROR(VLOOKUP($P17,Passing!$C:$AF,9,FALSE)/VLOOKUP($P17,Passing!$C:$AF,5,FALSE),0) -> 41.066667 | U17: =IFERROR(VLOOKUP($P17,Passing!$C:$AF,11,FALSE)/VLOOKUP($P17,Passing!$C:$AF,5,FALSE),0) -> 297.73333 | V17: =IFERROR(VLOOKUP($P17,Passing!$C:$AF,18,FALSE),0) -> 7.3 | W17: =IFERROR(VLOOKUP($P17,Passing!$C:$AF,12,FALSE)/VLOOKUP($P17,Passing!$C:$AF,5,FALSE),0) -> 1.7333333 | X17: =IFERROR(IF(OR($B17="D",$B17="K"),0,VLOOKUP($P17,Receiving!$C:$T,7,FALSE)/VLOOKUP($P17,Receiving!$C:$T,5,FALSE)),0)*$AJ17 -> 0 | Y17: =IFERROR(VLOOKUP($P17,Receiving!$C:$T,8,FALSE)/VLOOKUP($P17,Receiving!$C:$T,5,FALSE),0) -> 0 | Z17: =IFERROR(VLOOKUP($P17,Receiving!$C:$T,10,FALSE)/VLOOKUP($P17,Receiving!$C:$T,5,FALSE),0) -> 0 | AA17: =IFERROR(VLOOKUP($P17,Receiving!$C:$T,11,FALSE),0) -> 0 | AB17: =IFERROR(VLOOKUP($P17,Receiving!$C:$T,14,FALSE),0) -> 0 | AC17: =IFERROR(VLOOKUP($P17,Receiving!$C:$T,11,FALSE)/VLOOKUP($P17,Receiving!$C:$T,5,FALSE),0) -> 0 | AD17: =IFERROR(VLOOKUP($P17,Rushing!$C:$P,7,FALSE)/VLOOKUP($P17,Rushing!$C:$P,5,FALSE),0) -> 2.2666667 | AE17: =IFERROR(VLOOKUP($P17,Rushing!$C:$P,8,FALSE)/VLOOKUP($P17,Rushing!$C:$P,5,FALSE),0) -> 9.8 | AF17: =IFERROR(VLOOKUP($P17,Rushing!$C:$P,12,FALSE),0) -> 4.3 | AG17: =IFERROR(VLOOKUP($P17,Rushing!$C:$P,9,FALSE)/VLOOKUP($P17,Rushing!$C:$P,5,FALSE),0) -> 0.066666667 | AH17: =VLOOKUP($J17,'Vegas Odds'!$B:$S,18,FALSE) -> 44.77407 | AI17: =VLOOKUP($J17,'Vegas Odds'!$B:$S,17,FALSE) -> 21.32593 | AJ17: 1 | AK17: =T17*AJ17 -> 41.066667 | AL17: =IF(AND(AJ17=1,B17="QB"),AH17,0) -> 44.77407 | AM17: =V17/Team_Defense_Table[[#Totals],[Passing yds/att]]*'Fanduel Export'!Q17 -> 7.6482785 | AN17: =AM17*AL17 -> 342.44456 | AO17: =IFERROR(IF(OR($B17="D",$B17="K"),0,VLOOKUP($P17,Receiving!$C:$T,7,FALSE)/VLOOKUP($P17,Receiving!$C:$T,5,FALSE)),0)*$AJ17 -> 0 | AP17: =SUMIF($J:$J,$J17,AO:AO) -> 36.576282 | AQ17: =AO17/AP17*AH17 -> 0 | AR17: =Y17*AJ17 -> 0 | AS17: =IFERROR(AR17/AO17*AQ17,0) -> 0 | AT17: =AA17/Team_Defense_Table[[#Totals],[Yards per completion]]*'Fanduel Export'!S17 -> 0 | AU17: =AS17*AT17 -> 0 | AV17: =AD17*AJ17 -> 2.2666667 | AW17: =SUMIF($J:$J,$J17,AV:AV) -> 30.87587 | AX17: =IFERROR(AV17/AW17*AI17,0) -> 1.5655842 | AY17: =AF17/Team_Defense_Table[[#Totals],[Rushing Y/A]]*R17 -> 4.8390258 | AZ17: =AY17*AX17 -> 7.5759024 | BA17: =AN17/25+AU17/10+AZ17/10+AR17*0.5 -> 14.455373 | BB17: =BA17/(H17/1000) -> 1.8532529 | BC17: =AO17/(H17/1000) -> 0 | BD17: =D17 -> Matt Ryan | BE17: =H17 -> 7800 | BF17: =B17 -> QB
A18: 47691-40442 | B18: RB | C18: Aaron | D18: Aaron Jones | E18: Jones | F18: 18.143749 | G18: 16 | H18: 7800 | I18: GB@MIN | J18: GB | K18: MIN | O18: =D18 -> Aaron Jones | P18: =IFERROR(VLOOKUP(O:O,'Name Bridge'!A:B,2,FALSE),O:O) -> Aaron Jones | Q18: =VLOOKUP($K18,'Defensive Stats'!$AC:$AH,2,FALSE) -> 6.21797 | R18: =VLOOKUP($K18,'Defensive Stats'!$AC:$AH,4,FALSE) -> 4.2772277 | S18: =VLOOKUP($K18,'Defensive Stats'!$AC:$AH,6,FALSE) -> 9.4847716 | T18: =IFERROR(VLOOKUP($P18,Passing!$C:$AF,9,FALSE)/VLOOKUP($P18,Passing!$C:$AF,5,FALSE),0) -> 0 | U18: =IFERROR(VLOOKUP($P18,Passing!$C:$AF,11,FALSE)/VLOOKUP($P18,Passing!$C:$AF,5,FALSE),0) -> 0 | V18: =IFERROR(VLOOKUP($P18,Passing!$C:$AF,18,FALSE),0) -> 0 | W18: =IFERROR(VLOOKUP($P18,Passing!$C:$AF,12,FALSE)/VLOOKUP($P18,Passing!$C:$AF,5,FALSE),0) -> 0 | X18: =IFERROR(IF(OR($B18="D",$B18="K"),0,VLOOKUP($P18,Receiving!$C:$T,7,FALSE)/VLOOKUP($P18,Receiving!$C:$T,5,FALSE)),0)*$AJ18 -> 4.25 | Y18: =IFERROR(VLOOKUP($P18,Receiving!$C:$T,8,FALSE)/VLOOKUP($P18,Receiving!$C:$T,5,FALSE),0) -> 3.0625 | Z18: =IFERROR(VLOOKUP($P18,Receiving!$C:$T,10,FALSE)/VLOOKUP($P18,Receiving!$C:$T,5,FALSE),0) -> 29.625 | AA18: =IFERROR(VLOOKUP($P18,Receiving!$C:$T,11,FALSE),0) -> 9.7 | AB18: =IFERROR(VLOOKUP($P18,Receiving!$C:$T,14,FALSE),0) -> 67 | AC18: =IFERROR(VLOOKUP($P18,Receiving!$C:$T,11,FALSE)/VLOOKUP($P18,Receiving!$C:$T,5,FALSE),0) -> 0.60625 | AD18: =IFERROR(VLOOKUP($P18,Rushing!$C:$P,7,FALSE)/VLOOKUP($P18,Rushing!$C:$P,5,FALSE),0) -> 14.75 | AE18: =IFERROR(VLOOKUP($P18,Rushing!$C:$P,8,FALSE)/VLOOKUP($P18,Rushing!$C:$P,5,FALSE),0) -> 67.75 | AF18: =IFERROR(VLOOKUP($P18,Rushing!$C:$P,12,FALSE),0) -> 4.6 | AG18: =IFERROR(VLOOKUP($P18,Rushing!$C:$P,9,FALSE)/VLOOKUP($P18,Rushing!$C:$P,5,FALSE),0) -> 1 | AH18: =VLOOKUP($J18,'Vegas Odds'!$B:$S,18,FALSE) -> 37.252589 | AI18: =VLOOKUP($J18,'Vegas Odds'!$B:$S,17,FALSE) -> 23.147411 | AJ18: 1 | AK18: =T18*AJ18 -> 0 | AL18: =IF(AND(AJ18=1,B18="QB"),AH18,0) -> 0 | AM18: =V18/Team_Defense_Table[[#Totals],[Passing yds/att]]*'Fanduel Export'!Q18 -> 0 | AN18: =AM18*AL18 -> 0 | AO18: =IFERROR(IF(OR($B18="D",$B18="K"),0,VLOOKUP($P18,Receiving!$C:$T,7,FALSE)/VLOOKUP($P18,Receiving!$C:$T,5,FALSE)),0)*$AJ18 -> 4.25 | AP18: =SUMIF($J:$J,$J18,AO:AO) -> 34.582089 | AQ18: =AO18/AP18*AH18 -> 4.5781938 | AR18: =Y18*AJ18 -> 3.0625 | AS18: =IFERROR(AR18/AO18*AQ18,0) -> 3.2989926 | AT18: =AA18/Team_Defense_Table[[#Totals],[Yards per completion]]*'Fanduel Export'!S18 -> 8.664324 | AU18: =AS18*AT18 -> 28.583541 | AV18: =AD18*AJ18 -> 14.75 | AW18: =SUMIF($J:$J,$J18,AV:AV) -> 28.472024 | AX18: =IFERROR(AV18/AW18*AI18,0) -> 11.991571 | AY18: =AF18/Team_Defense_Table[[#Totals],[Rushing Y/A]]*R18 -> 4.5623762 | AZ18: =AY18*AX18 -> 54.71006 | BA18: =AN18/25+AU18/10+AZ18/10+AR18*0.5 -> 9.8606101 | BB18: =BA18/(H18/1000) -> 1.2641808 | BC18: =AO18/(H18/1000) -> 0.54487179 | BD18: =D18 -> Aaron Jones | BE18: =H18 -> 7800 | BF18: =B18 -> RB
A19: 47691-80001 | B19: RB | C19: Austin | D19: Austin Ekeler | E19: Ekeler | F19: 16.4375 | G19: 16 | H19: 7700 | I19: LAC@CIN | J19: LAC | K19: CIN | O19: =D19 -> Austin Ekeler | P19: =IFERROR(VLOOKUP(O:O,'Name Bridge'!A:B,2,FALSE),O:O) -> Austin Ekeler | Q19: =VLOOKUP($K19,'Defensive Stats'!$AC:$AH,2,FALSE) -> 7.8496994 | R19: =VLOOKUP($K19,'Defensive Stats'!$AC:$AH,4,FALSE) -> 4.7261905 | S19: =VLOOKUP($K19,'Defensive Stats'!$AC:$AH,6,FALSE) -> 12.717532 | T19: =IFERROR(VLOOKUP($P19,Passing!$C:$AF,9,FALSE)/VLOOKUP($P19,Passing!$C:$AF,5,FALSE),0) -> 0 | U19: =IFERROR(VLOOKUP($P19,Passing!$C:$AF,11,FALSE)/VLOOKUP($P19,Passing!$C:$AF,5,FALSE),0) -> 0 | V19: =IFERROR(VLOOKUP($P19,Passing!$C:$AF,18,FALSE),0) -> 0 | W19: =IFERROR(VLOOKUP($P19,Passing!$C:$AF,12,FALSE)/VLOOKUP($P19,Passing!$C:$AF,5,FALSE),0) -> 0 | X19: =IFERROR(IF(OR($B19="D",$B19="K"),0,VLOOKUP($P19,Receiving!$C:$T,7,FALSE)/VLOOKUP($P19,Receiving!$C:$T,5,FALSE)),0)*$AJ19 -> 6.75 | Y19: =IFERROR(VLOOKUP($P19,Receiving!$C:$T,8,FALSE)/VLOOKUP($P19,Receiving!$C:$T,5,FALSE),0) -> 5.75 | Z19: =IFERROR(VLOOKUP($P19,Receiving!$C:$T,10,FALSE)/VLOOKUP($P19,Receiving!$C:$T,5,FALSE),0) -> 62.0625 | AA19: =IFERROR(VLOOKUP($P19,Receiving!$C:$T,11,FALSE),0) -> 10.8 | AB19: =IFERROR(VLOOKUP($P19,Receiving!$C:$T,14,FALSE),0) -> 84 | AC19: =IFERROR(VLOOKUP($P19,Receiving!$C:$T,11,FALSE)/VLOOKUP($P19,Receiving!$C:$T,5,FALSE),0) -> 0.675 | AD19: =IFERROR(VLOOKUP($P19,Rushing!$C:$P,7,FALSE)/VLOOKUP($P19,Rushing!$C:$P,5,FALSE),0) -> 8.25 | AE19: =IFERROR(VLOOKUP($P19,Rushing!$C:$P,8,FALSE)/VLOOKUP($P19,Rushing!$C:$P,5,FALSE),0) -> 34.8125 | AF19: =IFERROR(VLOOKUP($P19,Rushing!$C:$P,12,FALSE),0) -> 4.2 | AG19: =IFERROR(VLOOKUP($P19,Rushing!$C:$P,9,FALSE)/VLOOKUP($P19,Rushing!$C:$P,5,FALSE),0) -> 0.1875 | AH19: =VLOOKUP($J19,'Vegas Odds'!$B:$S,18,FALSE) -> 34.151747 | AI19: =VLOOKUP($J19,'Vegas Odds'!$B:$S,17,FALSE) -> 26.748253 | AJ19: 1 | AK19: =T19*AJ19 -> 0 | AL19: =IF(AND(AJ19=1,B19="QB"),AH19,0) -> 0 | AM19: =V19/Team_Defense_Table[[#Totals],[Passing yds/att]]*'Fanduel Export'!Q19 -> 0 | AN19: =AM19*AL19 -> 0 | AO19: =IFERROR(IF(OR($B19="D",$B19="K"),0,VLOOKUP($P19,Receiving!$C:$T,7,FALSE)/VLOOKUP($P19,Receiving!$C:$T,5,FALSE)),0)*$AJ19 -> 6.75 | AP19: =SUMIF($J:$J,$J19,AO:AO) -> 32.673214 | AQ19: =AO19/AP19*AH19 -> 7.0554518 | AR19: =Y19*AJ19 -> 5.75 | AS19: =IFERROR(AR19/AO19*AQ19,0) -> 6.0101997 | AT19: =AA19/Team_Defense_Table[[#Totals],[Yards per completion]]*'Fanduel Export'!S19 -> 12.934888 | AU19: =AS19*AT19 -> 77.741262 | AV19: =AD19*AJ19 -> 8.25 | AW19: =SUMIF($J:$J,$J19,AV:AV) -> 14.61131 | AX19: =IFERROR(AV19/AW19*AI19,0) -> 15.102896 | AY19: =AF19/Team_Defense_Table[[#Totals],[Rushing Y/A]]*R19 -> 4.6028986 | AZ19: =AY19*AX19 -> 69.517099 | BA19: =AN19/25+AU19/10+AZ19/10+AR19*0.5 -> 17.600836 | BB19: =BA19/(H19/1000) -> 2.2858229 | BC19: =AO19/(H19/1000) -> 0.87662338 | BD19: =D19 -> Austin Ekeler | BE19: =H19 -> 7700 | BF19: =B19 -> RB
A20: 47691-55635 | B20: WR | C20: Chris | D20: Chris Godwin | E20: Godwin | F20: 16.65 | G20: 14 | H20: 7700 | I20: TB@NO | J20: TB | K20: NO | O20: =D20 -> Chris Godwin | P20: =IFERROR(VLOOKUP(O:O,'Name Bridge'!A:B,2,FALSE),O:O) -> Chris Godwin | Q20: =VLOOKUP($K20,'Defensive Stats'!$AC:$AH,2,FALSE) -> 6.4145937 | R20: =VLOOKUP($K20,'Defensive Stats'!$AC:$AH,4,FALSE) -> 4.2347826 | S20: =VLOOKUP($K20,'Defensive Stats'!$AC:$AH,6,FALSE) -> 10.425876 | T20: =IFERROR(VLOOKUP($P20,Passing!$C:$AF,9,FALSE)/VLOOKUP($P20,Passing!$C:$AF,5,FALSE),0) -> 0 | U20: =IFERROR(VLOOKUP($P20,Passing!$C:$AF,11,FALSE)/VLOOKUP($P20,Passing!$C:$AF,5,FALSE),0) -> 0 | V20: =IFERROR(VLOOKUP($P20,Passing!$C:$AF,18,FALSE),0) -> 0 | W20: =IFERROR(VLOOKUP($P20,Passing!$C:$AF,12,FALSE)/VLOOKUP($P20,Passing!$C:$AF,5,FALSE),0) -> 0 | X20: =IFERROR(IF(OR($B20="D",$B20="K"),0,VLOOKUP($P20,Receiving!$C:$T,7,FALSE)/VLOOKUP($P20,Receiving!$C:$T,5,FALSE)),0)*$AJ20 -> 8.6428571 | Y20: =IFERROR(VLOOKUP($P20,Receiving!$C:$T,8,FALSE)/VLOOKUP($P20,Receiving!$C:$T,5,FALSE),0) -> 6.1428571 | Z20: =IFERROR(VLOOKUP($P20,Receiving!$C:$T,10,FALSE)/VLOOKUP($P20,Receiving!$C:$T,5,FALSE),0) -> 95.214286 | AA20: =IFERROR(VLOOKUP($P20,Receiving!$C:$T,11,FALSE),0) -> 15.5 | AB20: =IFERROR(VLOOKUP($P20,Receiving!$C:$T,14,FALSE),0) -> 71 | AC20: =IFERROR(VLOOKUP($P20,Receiving!$C:$T,11,FALSE)/VLOOKUP($P20,Receiving!$C:$T,5,FALSE),0) -> 1.1071429 | AD20: =IFERROR(VLOOKUP($P20,Rushing!$C:$P,7,FALSE)/VLOOKUP($P20,Rushing!$C:$P,5,FALSE),0) -> 0.071428571 | AE20: =IFERROR(VLOOKUP($P20,Rushing!$C:$P,8,FALSE)/VLOOKUP($P20,Rushing!$C:$P,5,FALSE),0) -> 0.57142857 | AF20: =IFERROR(VLOOKUP($P20,Rushing!$C:$P,12,FALSE),0) -> 8.0 | AG20: =IFERROR(VLOOKUP($P20,Rushing!$C:$P,9,FALSE)/VLOOKUP($P20,Rushing!$C:$P,5,FALSE),0) -> 0 | AH20: =VLOOKUP($J20,'Vegas Odds'!$B:$S,18,FALSE) -> 44.700092 | AI20: =VLOOKUP($J20,'Vegas Odds'!$B:$S,17,FALSE) -> 20.599908 | AJ20: 1 | AK20: =T20*AJ20 -> 0 | AL20: =IF(AND(AJ20=1,B20="QB"),AH20,0) -> 0 | AM20: =V20/Team_Defense_Table[[#Totals],[Passing yds/att]]*'Fanduel Export'!Q20 -> 0 | AN20: =AM20*AL20 -> 0 | AO20: =IFERROR(IF(OR($B20="D",$B20="K"),0,VLOOKUP($P20,Receiving!$C:$T,7,FALSE)/VLOOKUP($P20,Receiving!$C:$T,5,FALSE)),0)*$AJ20 -> 8.6428571 | AP20: =SUMIF($J:$J,$J20,AO:AO) -> 39.892781 | AQ20: =AO20/AP20*AH20 -> 9.6843716 | AR20: =Y20*AJ20 -> 6.1428571 | AS20: =IFERROR(AR20/AO20*AQ20,0) -> 6.8831071 | AT20: =AA20/Team_Defense_Table[[#Totals],[Yards per completion]]*'Fanduel Export'!S20 -> 15.218797 | AU20: =AS20*AT20 -> 104.75261 | AV20: =AD20*AJ20 -> 0.071428571 | AW20: =SUMIF($J:$J,$J20,AV:AV) -> 23.153159 | AX20: =IFERROR(AV20/AW20*AI20,0) -> 0.063551671 | AY20: =AF20/Team_Defense_Table[[#Totals],[Rushing Y/A]]*R20 -> 7.8558286 | AZ20: =AY20*AX20 -> 0.49925104 | BA20: =AN20/25+AU20/10+AZ20/10+AR20*0.5 -> 13.596615 | BB20: =BA20/(H20/1000) -> 1.7657941 | BC20: =AO20/(H20/1000) -> 1.122449 | BD20: =D20 -> Chris Godwin | BE20: =H20 -> 7700 | BF20: =B20 -> WR
A21: 47691-70324 | B21: QB | C21: Carson | D21: Carson Wentz | E21: Wentz | F21: 17.678749 | G21: 16 | H21: 7700 | I21: PHI@WAS | J21: PHI | K21: WAS | O21: =D21 -> Carson Wentz | P21: =IFERROR(VLOOKUP(O:O,'Name Bridge'!A:B,2,FALSE),O:O) -> Carson Wentz | Q21: =VLOOKUP($K21,'Defensive Stats'!$AC:$AH,2,FALSE) -> 7.0796296 | R21: =VLOOKUP($K21,'Defensive Stats'!$AC:$AH,4,FALSE) -> 4.7444219 | S21: =VLOOKUP($K21,'Defensive Stats'!$AC:$AH,6,FALSE) -> 10.304582 | T21: =IFERROR(VLOOKUP($P21,Passing!$C:$AF,9,FALSE)/VLOOKUP($P21,Passing!$C:$AF,5,FALSE),0) -> 37.9375 | U21: =IFERROR(VLOOKUP($P21,Passing!$C:$AF,11,FALSE)/VLOOKUP($P21,Passing!$C:$AF,5,FALSE),0) -> 252.4375 | V21: =IFERROR(VLOOKUP($P21,Passing!$C:$AF,18,FALSE),0) -> 6.7 | W21: =IFERROR(VLOOKUP($P21,Passing!$C:$AF,12,FALSE)/VLOOKUP($P21,Passing!$C:$AF,5,FALSE),0) -> 1.6875 | X21: =IFERROR(IF(OR($B21="D",$B21="K"),0,VLOOKUP($P21,Receiving!$C:$T,7,FALSE)/VLOOKUP($P21,Receiving!$C:$T,5,FALSE)),0)*$AJ21 -> 0 | Y21: =IFERROR(VLOOKUP($P21,Receiving!$C:$T,8,FALSE)/VLOOKUP($P21,Receiving!$C:$T,5,FALSE),0) -> 0 | Z21: =IFERROR(VLOOKUP($P21,Receiving!$C:$T,10,FALSE)/VLOOKUP($P21,Receiving!$C:$T,5,FALSE),0) -> 0 | AA21: =IFERROR(VLOOKUP($P21,Receiving!$C:$T,11,FALSE),0) -> 0 | AB21: =IFERROR(VLOOKUP($P21,Receiving!$C:$T,14,FALSE),0) -> 0 | AC21: =IFERROR(VLOOKUP($P21,Receiving!$C:$T,11,FALSE)/VLOOKUP($P21,Receiving!$C:$T,5,FALSE),0) -> 0 | AD21: =IFERROR(VLOOKUP($P21,Rushing!$C:$P,7,FALSE)/VLOOKUP($P21,Rushing!$C:$P,5,FALSE),0) -> 3.875 | AE21: =IFERROR(VLOOKUP($P21,Rushing!$C:$P,8,FALSE)/VLOOKUP($P21,Rushing!$C:$P,5,FALSE),0) -> 15.1875 | AF21: =IFERROR(VLOOKUP($P21,Rushing!$C:$P,12,FALSE),0) -> 3.9 | AG21: =IFERROR(VLOOKUP($P21,Rushing!$C:$P,9,FALSE)/VLOOKUP($P21,Rushing!$C:$P,5,FALSE),0) -> 0.0625 | AH21: =VLOOKUP($J21,'Vegas Odds'!$B:$S,18,FALSE) -> 29.28497 | AI21: =VLOOKUP($J21,'Vegas Odds'!$B:$S,17,FALSE) -> 32.61503 | AJ21: 1 | AK21: =T21*AJ21 -> 37.9375 | AL21: =IF(AND(AJ21=1,B21="QB"),AH21,0) -> 29.28497 | AM21: =V21/Team_Defense_Table[[#Totals],[Passing yds/att]]*'Fanduel Export'!Q21 -> 7.0373035 | AN21: =AM21*AL21 -> 206.08722 | AO21: =IFERROR(IF(OR($B21="D",$B21="K"),0,VLOOKUP($P21,Receiving!$C:$T,7,FALSE)/VLOOKUP($P21,Receiving!$C:$T,5,FALSE)),0)*$AJ21 -> 0 | AP21: =SUMIF($J:$J,$J21,AO:AO) -> 48.590422 | AQ21: =AO21/AP21*AH21 -> 0 | AR21: =Y21*AJ21 -> 0 | AS21: =IFERROR(AR21/AO21*AQ21,0) -> 0 | AT21: =AA21/Team_Defense_Table[[#Totals],[Yards per completion]]*'Fanduel Export'!S21 -> 0 | AU21: =AS21*AT21 -> 0 | AV21: =AD21*AJ21 -> 3.875 | AW21: =SUMIF($J:$J,$J21,AV:AV) -> 20.961923 | AX21: =IFERROR(AV21/AW21*AI21,0) -> 6.0291816 | AY21: =AF21/Team_Defense_Table[[#Totals],[Rushing Y/A]]*R21 -> 4.2906076 | AZ21: =AY21*AX21 -> 25.868853 | BA21: =AN21/25+AU21/10+AZ21/10+AR21*0.5 -> 10.830374 | BB21: =BA21/(H21/1000) -> 1.4065421 | BC21: =AO21/(H21/1000) -> 0 | BD21: =D21 -> Carson Wentz | BE21: =H21 -> 7700 | BF21: =B21 -> QB
A22: 47691-63484 | B22: QB | C22: Kyler | D22: Kyler Murray | E22: Murray | F22: 18.58 | G22: 16 | H22: 7700 | I22: ARI@SF | J22: ARI | K22: SF | O22: =D22 -> Kyler Murray | P22: =IFERROR(VLOOKUP(O:O,'Name Bridge'!A:B,2,FALSE),O:O) -> Kyler Murray | Q22: =VLOOKUP($K22,'Defensive Stats'!$AC:$AH,2,FALSE) -> 5.2157996 | R22: =VLOOKUP($K22,'Defensive Stats'!$AC:$AH,4,FALSE) -> 4.4937656 | S22: =VLOOKUP($K22,'Defensive Stats'!$AC:$AH,6,FALSE) -> 8.5125786 | T22: =IFERROR(VLOOKUP($P22,Passing!$C:$AF,9,FALSE)/VLOOKUP($P22,Passing!$C:$AF,5,FALSE),0) -> 33.875 | U22: =IFERROR(VLOOKUP($P22,Passing!$C:$AF,11,FALSE)/VLOOKUP($P22,Passing!$C:$AF,5,FALSE),0) -> 232.625 | V22: =IFERROR(VLOOKUP($P22,Passing!$C:$AF,18,FALSE),0) -> 6.9 | W22: =IFERROR(VLOOKUP($P22,Passing!$C:$AF,12,FALSE)/VLOOKUP($P22,Passing!$C:$AF,5,FALSE),0) -> 1.25 | X22: =IFERROR(IF(OR($B22="D",$B22="K"),0,VLOOKUP($P22,Receiving!$C:$T,7,FALSE)/VLOOKUP($P22,Receiving!$C:$T,5,FALSE)),0)*$AJ22 -> 0 | Y22: =IFERROR(VLOOKUP($P22,Receiving!$C:$T,8,FALSE)/VLOOKUP($P22,Receiving!$C:$T,5,FALSE),0) -> 0 | Z22: =IFERROR(VLOOKUP($P22,Receiving!$C:$T,10,FALSE)/VLOOKUP($P22,Receiving!$C:$T,5,FALSE),0) -> 0 | AA22: =IFERROR(VLOOKUP($P22,Receiving!$C:$T,11,FALSE),0) -> 0 | AB22: =IFERROR(VLOOKUP($P22,Receiving!$C:$T,14,FALSE),0) -> 0 | AC22: =IFERROR(VLOOKUP($P22,Receiving!$C:$T,11,FALSE)/VLOOKUP($P22,Receiving!$C:$T,5,FALSE),0) -> 0 | AD22: =IFERROR(VLOOKUP($P22,Rushing!$C:$P,7,FALSE)/VLOOKUP($P22,Rushing!$C:$P,5,FALSE),0) -> 5.8125 | AE22: =IFERROR(VLOOKUP($P22,Rushing!$C:$P,8,FALSE)/VLOOKUP($P22,Rushing!$C:$P,5,FALSE),0) -> 34 | AF22: =IFERROR(VLOOKUP($P22,Rushing!$C:$P,12,FALSE),0) -> 5.8 | AG22: =IFERROR(VLOOKUP($P22,Rushing!$C:$P,9,FALSE)/VLOOKUP($P22,Rushing!$C:$P,5,FALSE),0) -> 0.25 | AH22: =VLOOKUP($J22,'Vegas Odds'!$B:$S,18,FALSE) -> 35.724841 | AI22: =VLOOKUP($J22,'Vegas Odds'!$B:$S,17,FALSE) -> 23.675159 | AJ22: 1 | AK22: =T22*AJ22 -> 33.875 | AL22: =IF(AND(AJ22=1,B22="QB"),AH22,0) -> 35.724841 | AM22: =V22/Team_Defense_Table[[#Totals],[Passing yds/att]]*'Fanduel Export'!Q22 -> 5.3393812 | AN22: =AM22*AL22 -> 190.74854 | AO22: =IFERROR(IF(OR($B22="D",$B22="K"),0,VLOOKUP($P22,Receiving!$C:$T,7,FALSE)/VLOOKUP($P22,Receiving!$C:$T,5,FALSE)),0)*$AJ22 -> 0 | AP22: =SUMIF($J:$J,$J22,AO:AO) -> 43.039806 | AQ22: =AO22/AP22*AH22 -> 0 | AR22: =Y22*AJ22 -> 0 | AS22: =IFERROR(AR22/AO22*AQ22,0) -> 0 | AT22: =AA22/Team_Defense_Table[[#Totals],[Yards per completion]]*'Fanduel Export'!S22 -> 0 | AU22: =AS22*AT22 -> 0 | AV22: =AD22*AJ22 -> 5.8125 | AW22: =SUMIF($J:$J,$J22,AV:AV) -> 26.173306 | AX22: =IFERROR(AV22/AW22*AI22,0) -> 5.257718 | AY22: =AF22/Team_Defense_Table[[#Totals],[Rushing Y/A]]*R22 -> 6.0437891 | AZ22: =AY22*AX22 -> 31.776539 | BA22: =AN22/25+AU22/10+AZ22/10+AR22*0.5 -> 10.807596 | BB22: =BA22/(H22/1000) -> 1.4035838 | BC22: =AO22/(H22/1000) -> 0 | BD22: =D22 -> Kyler Murray | BE22: =H22 -> 7700 | BF22: =B22 -> QB
... A33: 47691-22038 | B33: QB | C33: Kirk | D33: Kirk Cousins | E33: Cousins | F33: 16.694667 | G33: 15 | H33: 7200 | I33: GB@MIN | J33: MIN | K33: GB | O33: =D33 -> Kirk Cousins | P33: =IFERROR(VLOOKUP(O:O,'Name Bridge'!A:B,2,FALSE),O:O) -> Kirk Cousins | Q33: =VLOOKUP($K33,'Defensive Stats'!$AC:$AH,2,FALSE) -> 6.8150183 | R33: =VLOOKUP($K33,'Defensive Stats'!$AC:$AH,4,FALSE) -> 4.6739659 | S33: =VLOOKUP($K33,'Defensive Stats'!$AC:$AH,6,FALSE) -> 11.41411 | T33: =IFERROR(VLOOKUP($P33,Passing!$C:$AF,9,FALSE)/VLOOKUP($P33,Passing!$C:$AF,5,FALSE),0) -> 29.6 | U33: =IFERROR(VLOOKUP($P33,Passing!$C:$AF,11,FALSE)/VLOOKUP($P33,Passing!$C:$AF,5,FALSE),0) -> 240.2 | V33: =IFERROR(VLOOKUP($P33,Passing!$C:$AF,18,FALSE),0) -> 8.1 | W33: =IFERROR(VLOOKUP($P33,Passing!$C:$AF,12,FALSE)/VLOOKUP($P33,Passing!$C:$AF,5,FALSE),0) -> 1.7333333 | X33: =IFERROR(IF(OR($B33="D",$B33="K"),0,VLOOKUP($P33,Receiving!$C:$T,7,FALSE)/VLOOKUP($P33,Receiving!$C:$T,5,FALSE)),0)*$AJ33 -> 0 | Y33: =IFERROR(VLOOKUP($P33,Receiving!$C:$T,8,FALSE)/VLOOKUP($P33,Receiving!$C:$T,5,FALSE),0) -> 0 | Z33: =IFERROR(VLOOKUP($P33,Receiving!$C:$T,10,FALSE)/VLOOKUP($P33,Receiving!$C:$T,5,FALSE),0) -> 0 | AA33: =IFERROR(VLOOKUP($P33,Receiving!$C:$T,11,FALSE),0) -> 0 | AB33: =IFERROR(VLOOKUP($P33,Receiving!$C:$T,14,FALSE),0) -> 0 | AC33: =IFERROR(VLOOKUP($P33,Receiving!$C:$T,11,FALSE)/VLOOKUP($P33,Receiving!$C:$T,5,FALSE),0) -> 0 | AD33: =IFERROR(VLOOKUP($P33,Rushing!$C:$P,7,FALSE)/VLOOKUP($P33,Rushing!$C:$P,5,FALSE),0) -> 2.0666667 | AE33: =IFERROR(VLOOKUP($P33,Rushing!$C:$P,8,FALSE)/VLOOKUP($P33,Rushing!$C:$P,5,FALSE),0) -> 4.2 | AF33: =IFERROR(VLOOKUP($P33,Rushing!$C:$P,12,FALSE),0) -> 2.0 | AG33: =IFERROR(VLOOKUP($P33,Rushing!$C:$P,9,FALSE)/VLOOKUP($P33,Rushing!$C:$P,5,FALSE),0) -> 0.066666667 | AH33: =VLOOKUP($J33,'Vegas Odds'!$B:$S,18,FALSE) -> 24.965897 | AI33: =VLOOKUP($J33,'Vegas Odds'!$B:$S,17,FALSE) -> 34.134103 | AJ33: 1 | AK33: =T33*AJ33 -> 29.6 | AL33: =IF(AND(AJ33=1,B33="QB"),AH33,0) -> 24.965897 | AM33: =V33/Team_Defense_Table[[#Totals],[Passing yds/att]]*'Fanduel Export'!Q33 -> 8.1897941 | AN33: =AM33*AL33 -> 204.46555 | AO33: =IFERROR(IF(OR($B33="D",$B33="K"),0,VLOOKUP($P33,Receiving!$C:$T,7,FALSE)/VLOOKUP($P33,Receiving!$C:$T,5,FALSE)),0)*$AJ33 -> 0 | AP33: =SUMIF($J:$J,$J33,AO:AO) -> 26.827244 | AQ33: =AO33/AP33*AH33 -> 0 | AR33: =Y33*AJ33 -> 0 | AS33: =IFERROR(AR33/AO33*AQ33,0) -> 0 | AT33: =AA33/Team_Defense_Table[[#Totals],[Yards per completion]]*'Fanduel Export'!S33 -> 0 | AU33: =AS33*AT33 -> 0 | AV33: =AD33*AJ33 -> 2.0666667 | AW33: =SUMIF($J:$J,$J33,AV:AV) -> 37.682784 | AX33: =IFERROR(AV33/AW33*AI33,0) -> 1.8720436 | AY33: =AF33/Team_Defense_Table[[#Totals],[Rushing Y/A]]*R33 -> 2.1676364 | AZ33: =AY33*AX33 -> 4.0579098 | BA33: =AN33/25+AU33/10+AZ33/10+AR33*0.5 -> 8.5844131 | BB33: =BA33/(H33/1000) -> 1.1922796 | BC33: =AO33/(H33/1000) -> 0 | BD33: =D33 -> Kirk Cousins | BE33: =H33 -> 7200 | BF33: =B33 -> QB
A34: 47691-64119 | B34: RB | C34: Chris | D34: Chris Carson | E34: Carson | F34: 14.273334 | G34: 15 | H34: 7200 | I34: SEA@ATL | J34: SEA | K34: ATL | L34: Q | M34: Hip | O34: =D34 -> Chris Carson | P34: =IFERROR(VLOOKUP(O:O,'Name Bridge'!A:B,2,FALSE),O:O) -> Chris Carson | Q34: =VLOOKUP($K34,'Defensive Stats'!$AC:$AH,2,FALSE) -> 7.3097015 | R34: =VLOOKUP($K34,'Defensive Stats'!$AC:$AH,4,FALSE) -> 4.216152 | S34: =VLOOKUP($K34,'Defensive Stats'!$AC:$AH,6,FALSE) -> 11.162393 | T34: =IFERROR(VLOOKUP($P34,Passing!$C:$AF,9,FALSE)/VLOOKUP($P34,Passing!$C:$AF,5,FALSE),0) -> 0 | U34: =IFERROR(VLOOKUP($P34,Passing!$C:$AF,11,FALSE)/VLOOKUP($P34,Passing!$C:$AF,5,FALSE),0) -> 0 | V34: =IFERROR(VLOOKUP($P34,Passing!$C:$AF,18,FALSE),0) -> 0 | W34: =IFERROR(VLOOKUP($P34,Passing!$C:$AF,12,FALSE)/VLOOKUP($P34,Passing!$C:$AF,5,FALSE),0) -> 0 | X34: =IFERROR(IF(OR($B34="D",$B34="K"),0,VLOOKUP($P34,Receiving!$C:$T,7,FALSE)/VLOOKUP($P34,Receiving!$C:$T,5,FALSE)),0)*$AJ34 -> 3.1333333 | Y34: =IFERROR(VLOOKUP($P34,Receiving!$C:$T,8,FALSE)/VLOOKUP($P34,Receiving!$C:$T,5,FALSE),0) -> 2.4666667 | Z34: =IFERROR(VLOOKUP($P34,Receiving!$C:$T,10,FALSE)/VLOOKUP($P34,Receiving!$C:$T,5,FALSE),0) -> 17.733333 | AA34: =IFERROR(VLOOKUP($P34,Receiving!$C:$T,11,FALSE),0) -> 7.2 | AB34: =IFERROR(VLOOKUP($P34,Receiving!$C:$T,14,FALSE),0) -> 21 | AC34: =IFERROR(VLOOKUP($P34,Receiving!$C:$T,11,FALSE)/VLOOKUP($P34,Receiving!$C:$T,5,FALSE),0) -> 0.48 | AD34: =IFERROR(VLOOKUP($P34,Rushing!$C:$P,7,FALSE)/VLOOKUP($P34,Rushing!$C:$P,5,FALSE),0) -> 18.533333 | AE34: =IFERROR(VLOOKUP($P34,Rushing!$C:$P,8,FALSE)/VLOOKUP($P34,Rushing!$C:$P,5,FALSE),0) -> 82 | AF34: =IFERROR(VLOOKUP($P34,Rushing!$C:$P,12,FALSE),0) -> 4.4 | AG34: =IFERROR(VLOOKUP($P34,Rushing!$C:$P,9,FALSE)/VLOOKUP($P34,Rushing!$C:$P,5,FALSE),0) -> 0.46666667 | AH34: =VLOOKUP($J34,'Vegas Odds'!$B:$S,18,FALSE) -> 34.284944 | AI34: =VLOOKUP($J34,'Vegas Odds'!$B:$S,17,FALSE) -> 30.315056 | AJ34: 1 | AK34: =T34*AJ34 -> 0 | AL34: =IF(AND(AJ34=1,B34="QB"),AH34,0) -> 0 | AM34: =V34/Team_Defense_Table[[#Totals],[Passing yds/att]]*'Fanduel Export'!Q34 -> 0 | AN34: =AM34*AL34 -> 0 | AO34: =IFERROR(IF(OR($B34="D",$B34="K"),0,VLOOKUP($P34,Receiving!$C:$T,7,FALSE)/VLOOKUP($P34,Receiving!$C:$T,5,FALSE)),0)*$AJ34 -> 3.1333333 | AP34: =SUMIF($J:$J,$J34,AO:AO) -> 34.263041 | AQ34: =AO34/AP34*AH34 -> 3.1353363 | AR34: =Y34*AJ34 -> 2.4666667 | AS34: =IFERROR(AR34/AO34*AQ34,0) -> 2.4682435 | AT34: =AA34/Team_Defense_Table[[#Totals],[Yards per completion]]*'Fanduel Export'!S34 -> 7.56878 | AU34: =AS34*AT34 -> 18.681592 | AV34: =AD34*AJ34 -> 18.533333 | AW34: =SUMIF($J:$J,$J34,AV:AV) -> 46.789286 | AX34: =IFERROR(AV34/AW34*AI34,0) -> 12.007857 | AY34: =AF34/Team_Defense_Table[[#Totals],[Rushing Y/A]]*R34 -> 4.3016971 | AZ34: =AY34*AX34 -> 51.654163 | BA34: =AN34/25+AU34/10+AZ34/10+AR34*0.5 -> 8.2669088 | BB34: =BA34/(H34/1000) -> 1.1481818 | BC34: =AO34/(H34/1000) -> 0.43518519 | BD34: =D34 -> Chris Carson | BE34: =H34 -> 7200 | BF34: =B34 -> RB
A35: 47691-28643 | B35: WR | C35: Allen | D35: Allen Robinson II | E35: Robinson II | F35: 12.86875 | G35: 16 | H35: 7200 | I35: CHI@DET | J35: CHI | K35: DET | O35: =D35 -> Allen Robinson II | P35: =IFERROR(VLOOKUP(O:O,'Name Bridge'!A:B,2,FALSE),O:O) -> Allen Robinson II | Q35: =VLOOKUP($K35,'Defensive Stats'!$AC:$AH,2,FALSE) -> 7.4484452 | R35: =VLOOKUP($K35,'Defensive Stats'!$AC:$AH,4,FALSE) -> 4.0769231 | S35: =VLOOKUP($K35,'Defensive Stats'!$AC:$AH,6,FALSE) -> 11.944882 | T35: =IFERROR(VLOOKUP($P35,Passing!$C:$AF,9,FALSE)/VLOOKUP($P35,Passing!$C:$AF,5,FALSE),0) -> 0 | U35: =IFERROR(VLOOKUP($P35,Passing!$C:$AF,11,FALSE)/VLOOKUP($P35,Passing!$C:$AF,5,FALSE),0) -> 0 | V35: =IFERROR(VLOOKUP($P35,Passing!$C:$AF,18,FALSE),0) -> 0 | W35: =IFERROR(VLOOKUP($P35,Passing!$C:$AF,12,FALSE)/VLOOKUP($P35,Passing!$C:$AF,5,FALSE),0) -> 0 | X35: =IFERROR(IF(OR($B35="D",$B35="K"),0,VLOOKUP($P35,Receiving!$C:$T,7,FALSE)/VLOOKUP($P35,Receiving!$C:$T,5,FALSE)),0)*$AJ35 -> 0 | Y35: =IFERROR(VLOOKUP($P35,Receiving!$C:$T,8,FALSE)/VLOOKUP($P35,Receiving!$C:$T,5,FALSE),0) -> 0 | Z35: =IFERROR(VLOOKUP($P35,Receiving!$C:$T,10,FALSE)/VLOOKUP($P35,Receiving!$C:$T,5,FALSE),0) -> 0 | AA35: =IFERROR(VLOOKUP($P35,Receiving!$C:$T,11,FALSE),0) -> 0 | AB35: =IFERROR(VLOOKUP($P35,Receiving!$C:$T,14,FALSE),0) -> 0 | AC35: =IFERROR(VLOOKUP($P35,Receiving!$C:$T,11,FALSE)/VLOOKUP($P35,Receiving!$C:$T,5,FALSE),0) -> 0 | AD35: =IFERROR(VLOOKUP($P35,Rushing!$C:$P,7,FALSE)/VLOOKUP($P35,Rushing!$C:$P,5,FALSE),0) -> 0 | AE35: =IFERROR(VLOOKUP($P35,Rushing!$C:$P,8,FALSE)/VLOOKUP($P35,Rushing!$C:$P,5,FALSE),0) -> 0 | AF35: =IFERROR(VLOOKUP($P35,Rushing!$C:$P,12,FALSE),0) -> 0 | AG35: =IFERROR(VLOOKUP($P35,Rushing!$C:$P,9,FALSE)/VLOOKUP($P35,Rushing!$C:$P,5,FALSE),0) -> 0 | AH35: =VLOOKUP($J35,'Vegas Odds'!$B:$S,18,FALSE) -> 39.087289 | AI35: =VLOOKUP($J35,'Vegas Odds'!$B:$S,17,FALSE) -> 21.912711 | AJ35: 1 | AK35: =T35*AJ35 -> 0 | AL35: =IF(AND(AJ35=1,B35="QB"),AH35,0) -> 0 | AM35: =V35/Team_Defense_Table[[#Totals],[Passing yds/att]]*'Fanduel Export'!Q35 -> 0 | AN35: =AM35*AL35 -> 0 | AO35: =IFERROR(IF(OR($B35="D",$B35="K"),0,VLOOKUP($P35,Receiving!$C:$T,7,FALSE)/VLOOKUP($P35,Receiving!$C:$T,5,FALSE)),0)*$AJ35 -> 0 | AP35: =SUMIF($J:$J,$J35,AO:AO) -> 29.935714 | AQ35: =AO35/AP35*AH35 -> 0 | AR35: =Y35*AJ35 -> 0 | AS35: =IFERROR(AR35/AO35*AQ35,0) -> 0 | AT35: =AA35/Team_Defense_Table[[#Totals],[Yards per completion]]*'Fanduel Export'!S35 -> 0 | AU35: =AS35*AT35 -> 0 | AV35: =AD35*AJ35 -> 0 | AW35: =SUMIF($J:$J,$J35,AV:AV) -> 24.985714 | AX35: =IFERROR(AV35/AW35*AI35,0) -> 0 | AY35: =AF35/Team_Defense_Table[[#Totals],[Rushing Y/A]]*R35 -> 0 | AZ35: =AY35*AX35 -> 0 | BA35: =AN35/25+AU35/10+AZ35/10+AR35*0.5 -> 0 | BB35: =BA35/(H35/1000) -> 0 | BC35: =AO35/(H35/1000) -> 0 | BD35: =D35 -> Allen Robinson II | BE35: =H35 -> 7200 | BF35: =B35 -> WR
A36: 47691-63043 | B36: WR | C36: DJ | D36: DJ Moore | E36: Moore | F36: 12.466667 | G36: 15 | H36: 7100 | I36: LV@CAR | J36: CAR | K36: LV | O36: =D36 -> DJ Moore | P36: =IFERROR(VLOOKUP(O:O,'Name Bridge'!A:B,2,FALSE),O:O) -> DJ Moore | Q36: =VLOOKUP($K36,'Defensive Stats'!$AC:$AH,2,FALSE) -> 7.8079848 | R36: =VLOOKUP($K36,'Defensive Stats'!$AC:$AH,4,FALSE) -> 3.8765432 | S36: =VLOOKUP($K36,'Defensive Stats'!$AC:$AH,6,FALSE) -> 12.186944 | T36: =IFERROR(VLOOKUP($P36,Passing!$C:$AF,9,FALSE)/VLOOKUP($P36,Passing!$C:$AF,5,FALSE),0) -> 0 | U36: =IFERROR(VLOOKUP($P36,Passing!$C:$AF,11,FALSE)/VLOOKUP($P36,Passing!$C:$AF,5,FALSE),0) -> 0 | V36: =IFERROR(VLOOKUP($P36,Passing!$C:$AF,18,FALSE),0) -> 0 | W36: =IFERROR(VLOOKUP($P36,Passing!$C:$AF,12,FALSE)/VLOOKUP($P36,Passing!$C:$AF,5,FALSE),0) -> 0 | X36: =IFERROR(IF(OR($B36="D",$B36="K"),0,VLOOKUP($P36,Receiving!$C:$T,7,FALSE)/VLOOKUP($P36,Receiving!$C:$T,5,FALSE)),0)*$AJ36 -> 0 | Y36: =IFERROR(VLOOKUP($P36,Receiving!$C:$T,8,FALSE)/VLOOKUP($P36,Receiving!$C:$T,5,FALSE),0) -> 0 | Z36: =IFERROR(VLOOKUP($P36,Receiving!$C:$T,10,FALSE)/VLOOKUP($P36,Receiving!$C:$T,5,FALSE),0) -> 0 | AA36: =IFERROR(VLOOKUP($P36,Receiving!$C:$T,11,FALSE),0) -> 0 | AB36: =IFERROR(VLOOKUP($P36,Receiving!$C:$T,14,FALSE),0) -> 0 | AC36: =IFERROR(VLOOKUP($P36,Receiving!$C:$T,11,FALSE)/VLOOKUP($P36,Receiving!$C:$T,5,FALSE),0) -> 0 | AD36: =IFERROR(VLOOKUP($P36,Rushing!$C:$P,7,FALSE)/VLOOKUP($P36,Rushing!$C:$P,5,FALSE),0) -> 0 | AE36: =IFERROR(VLOOKUP($P36,Rushing!$C:$P,8,FALSE)/VLOOKUP($P36,Rushing!$C:$P,5,FALSE),0) -> 0 | AF36: =IFERROR(VLOOKUP($P36,Rushing!$C:$P,12,FALSE),0) -> 0 | AG36: =IFERROR(VLOOKUP($P36,Rushing!$C:$P,9,FALSE)/VLOOKUP($P36,Rushing!$C:$P,5,FALSE),0) -> 0 | AH36: =VLOOKUP($J36,'Vegas Odds'!$B:$S,18,FALSE) -> 42.975625 | AI36: =VLOOKUP($J36,'Vegas Odds'!$B:$S,17,FALSE) -> 20.224375 | AJ36: 1 | AK36: =T36*AJ36 -> 0 | AL36: =IF(AND(AJ36=1,B36="QB"),AH36,0) -> 0 | AM36: =V36/Team_Defense_Table[[#Totals],[Passing yds/att]]*'Fanduel Export'!Q36 -> 0 | AN36: =AM36*AL36 -> 0 | AO36: =IFERROR(IF(OR($B36="D",$B36="K"),0,VLOOKUP($P36,Receiving!$C:$T,7,FALSE)/VLOOKUP($P36,Receiving!$C:$T,5,FALSE)),0)*$AJ36 -> 0 | AP36: =SUMIF($J:$J,$J36,AO:AO) -> 35.359295 | AQ36: =AO36/AP36*AH36 -> 0 | AR36: =Y36*AJ36 -> 0 | AS36: =IFERROR(AR36/AO36*AQ36,0) -> 0 | AT36: =AA36/Team_Defense_Table[[#Totals],[Yards per completion]]*'Fanduel Export'!S36 -> 0 | AU36: =AS36*AT36 -> 0 | AV36: =AD36*AJ36 -> 0 | AW36: =SUMIF($J:$J,$J36,AV:AV) -> 28.778312 | AX36: =IFERROR(AV36/AW36*AI36,0) -> 0 | AY36: =AF36/Team_Defense_Table[[#Totals],[Rushing Y/A]]*R36 -> 0 | AZ36: =AY36*AX36 -> 0 | BA36: =AN36/25+AU36/10+AZ36/10+AR36*0.5 -> 0 | BB36: =BA36/(H36/1000) -> 0 | BC36: =AO36/(H36/1000) -> 0 | BD36: =D36 -> DJ Moore | BE36: =H36 -> 7100 | BF36: =B36 -> WR
A37: 47691-30447 | B37: RB | C37: Todd | D37: Todd Gurley II | E37: Gurley II | F37: 13.593333 | G37: 15 | H37: 7100 | I37: SEA@ATL | J37: ATL | K37: SEA | O37: =D37 -> Todd Gurley II | P37: =IFERROR(VLOOKUP(O:O,'Name Bridge'!A:B,2,FALSE),O:O) -> Todd Gurley | Q37: =VLOOKUP($K37,'Defensive Stats'!$AC:$AH,2,FALSE) -> 7.0618729 | R37: =VLOOKUP($K37,'Defensive Stats'!$AC:$AH,4,FALSE) -> 4.8530928 | S37: =VLOOKUP($K37,'Defensive Stats'!$AC:$AH,6,FALSE) -> 11.02611 | T37: =IFERROR(VLOOKUP($P37,Passing!$C:$AF,9,FALSE)/VLOOKUP($P37,Passing!$C:$AF,5,FALSE),0) -> 0 | U37: =IFERROR(VLOOKUP($P37,Passing!$C:$AF,11,FALSE)/VLOOKUP($P37,Passing!$C:$AF,5,FALSE),0) -> 0 | V37: =IFERROR(VLOOKUP($P37,Passing!$C:$AF,18,FALSE),0) -> 0 | W37: =IFERROR(VLOOKUP($P37,Passing!$C:$AF,12,FALSE)/VLOOKUP($P37,Passing!$C:$AF,5,FALSE),0) -> 0 | X37: =IFERROR(IF(OR($B37="D",$B37="K"),0,VLOOKUP($P37,Receiving!$C:$T,7,FALSE)/VLOOKUP($P37,Receiving!$C:$T,5,FALSE)),0)*$AJ37 -> 3.2666667 | Y37: =IFERROR(VLOOKUP($P37,Receiving!$C:$T,8,FALSE)/VLOOKUP($P37,Receiving!$C:$T,5,FALSE),0) -> 2.0666667 | Z37: =IFERROR(VLOOKUP($P37,Receiving!$C:$T,10,FALSE)/VLOOKUP($P37,Receiving!$C:$T,5,FALSE),0) -> 13.8 | AA37: =IFERROR(VLOOKUP($P37,Receiving!$C:$T,11,FALSE),0) -> 6.7 | AB37: =IFERROR(VLOOKUP($P37,Receiving!$C:$T,14,FALSE),0) -> 23 | AC37: =IFERROR(VLOOKUP($P37,Receiving!$C:$T,11,FALSE)/VLOOKUP($P37,Receiving!$C:$T,5,FALSE),0) -> 0.44666667 | AD37: =IFERROR(VLOOKUP($P37,Rushing!$C:$P,7,FALSE)/VLOOKUP($P37,Rushing!$C:$P,5,FALSE),0) -> 14.866667 | AE37: =IFERROR(VLOOKUP($P37,Rushing!$C:$P,8,FALSE)/VLOOKUP($P37,Rushing!$C:$P,5,FALSE),0) -> 57.133333 | AF37: =IFERROR(VLOOKUP($P37,Rushing!$C:$P,12,FALSE),0) -> 3.8 | AG37: =IFERROR(VLOOKUP($P37,Rushing!$C:$P,9,FALSE)/VLOOKUP($P37,Rushing!$C:$P,5,FALSE),0) -> 0.8 | AH37: =VLOOKUP($J37,'Vegas Odds'!$B:$S,18,FALSE) -> 44.77407 | AI37: =VLOOKUP($J37,'Vegas Odds'!$B:$S,17,FALSE) -> 21.32593 | AJ37: 1 | AK37: =T37*AJ37 -> 0 | AL37: =IF(AND(AJ37=1,B37="QB"),AH37,0) -> 0 | AM37: =V37/Team_Defense_Table[[#Totals],[Passing yds/att]]*'Fanduel Export'!Q37 -> 0 | AN37: =AM37*AL37 -> 0 | AO37: =IFERROR(IF(OR($B37="D",$B37="K"),0,VLOOKUP($P37,Receiving!$C:$T,7,FALSE)/VLOOKUP($P37,Receiving!$C:$T,5,FALSE)),0)*$AJ37 -> 3.2666667 | AP37: =SUMIF($J:$J,$J37,AO:AO) -> 36.576282 | AQ37: =AO37/AP37*AH37 -> 3.9988199 | AR37: =Y37*AJ37 -> 2.0666667 | AS37: =IFERROR(AR37/AO37*AQ37,0) -> 2.5298656 | AT37: =AA37/Team_Defense_Table[[#Totals],[Yards per completion]]*'Fanduel Export'!S37 -> 6.9571791 | AU37: =AS37*AT37 -> 17.600728 | AV37: =AD37*AJ37 -> 14.866667 | AW37: =SUMIF($J:$J,$J37,AV:AV) -> 30.87587 | AX37: =IFERROR(AV37/AW37*AI37,0) -> 10.26839 | AY37: =AF37/Team_Defense_Table[[#Totals],[Rushing Y/A]]*R37 -> 4.2763484 | AZ37: =AY37*AX37 -> 43.911215 | BA37: =AN37/25+AU37/10+AZ37/10+AR37*0.5 -> 7.1845277 | BB37: =BA37/(H37/1000) -> 1.0119053 | BC37: =AO37/(H37/1000) -> 0.4600939 | BD37: =D37 -> Todd Gurley II | BE37: =H37 -> 7100 | BF37: =B37 -> RB
A38: 47691-7968 | B38: QB | C38: Philip | D38: Philip Rivers | E38: Rivers | F38: 15.96875 | G38: 16 | H38: 7100 | I38: IND@JAC | J38: IND | K38: JAC | O38: =D38 -> Philip Rivers | P38: =IFERROR(VLOOKUP(O:O,'Name Bridge'!A:B,2,FALSE),O:O) -> Philip Rivers | Q38: =VLOOKUP($K38,'Defensive Stats'!$AC:$AH,2,FALSE) -> 7.3075435 | R38: =VLOOKUP($K38,'Defensive Stats'!$AC:$AH,4,FALSE) -> 5.1241379 | S38: =VLOOKUP($K38,'Defensive Stats'!$AC:$AH,6,FALSE) -> 11.553517 | T38: =IFERROR(VLOOKUP($P38,Passing!$C:$AF,9,FALSE)/VLOOKUP($P38,Passing!$C:$AF,5,FALSE),0) -> 36.9375 | U38: =IFERROR(VLOOKUP($P38,Passing!$C:$AF,11,FALSE)/VLOOKUP($P38,Passing!$C:$AF,5,FALSE),0) -> 288.4375 | V38: =IFERROR(VLOOKUP($P38,Passing!$C:$AF,18,FALSE),0) -> 7.8 | W38: =IFERROR(VLOOKUP($P38,Passing!$C:$AF,12,FALSE)/VLOOKUP($P38,Passing!$C:$AF,5,FALSE),0) -> 1.4375 | X38: =IFERROR(IF(OR($B38="D",$B38="K"),0,VLOOKUP($P38,Receiving!$C:$T,7,FALSE)/VLOOKUP($P38,Receiving!$C:$T,5,FALSE)),0)*$AJ38 -> 0 | Y38: =IFERROR(VLOOKUP($P38,Receiving!$C:$T,8,FALSE)/VLOOKUP($P38,Receiving!$C:$T,5,FALSE),0) -> 0 | Z38: =IFERROR(VLOOKUP($P38,Receiving!$C:$T,10,FALSE)/VLOOKUP($P38,Receiving!$C:$T,5,FALSE),0) -> 0 | AA38: =IFERROR(VLOOKUP($P38,Receiving!$C:$T,11,FALSE),0) -> 0 | AB38: =IFERROR(VLOOKUP($P38,Receiving!$C:$T,14,FALSE),0) -> 0 | AC38: =IFERROR(VLOOKUP($P38,Receiving!$C:$T,11,FALSE)/VLOOKUP($P38,Receiving!$C:$T,5,FALSE),0) -> 0 | AD38: =IFERROR(VLOOKUP($P38,Rushing!$C:$P,7,FALSE)/VLOOKUP($P38,Rushing!$C:$P,5,FALSE),0) -> 0.75 | AE38: =IFERROR(VLOOKUP($P38,Rushing!$C:$P,8,FALSE)/VLOOKUP($P38,Rushing!$C:$P,5,FALSE),0) -> 1.8125 | AF38: =IFERROR(VLOOKUP($P38,Rushing!$C:$P,12,FALSE),0) -> 2.4 | AG38: =IFERROR(VLOOKUP($P38,Rushing!$C:$P,9,FALSE)/VLOOKUP($P38,Rushing!$C:$P,5,FALSE),0) -> 0 | AH38: =VLOOKUP($J38,'Vegas Odds'!$B:$S,18,FALSE) -> 24.832312 | AI38: =VLOOKUP($J38,'Vegas Odds'!$B:$S,17,FALSE) -> 36.767688 | AJ38: 1 | AK38: =T38*AJ38 -> 36.9375 | AL38: =IF(AND(AJ38=1,B38="QB"),AH38,0) -> 24.832312 | AM38: =V38/Team_Defense_Table[[#Totals],[Passing yds/att]]*'Fanduel Export'!Q38 -> 8.4564279 | AN38: =AM38*AL38 -> 209.99266 | AO38: =IFERROR(IF(OR($B38="D",$B38="K"),0,VLOOKUP($P38,Receiving!$C:$T,7,FALSE)/VLOOKUP($P38,Receiving!$C:$T,5,FALSE)),0)*$AJ38 -> 0 | AP38: =SUMIF($J:$J,$J38,AO:AO) -> 34.886584 | AQ38: =AO38/AP38*AH38 -> 0 | AR38: =Y38*AJ38 -> 0 | AS38: =IFERROR(AR38/AO38*AQ38,0) -> 0 | AT38: =AA38/Team_Defense_Table[[#Totals],[Yards per completion]]*'Fanduel Export'!S38 -> 0 | AU38: =AS38*AT38 -> 0 | AV38: =AD38*AJ38 -> 0.75 | AW38: =SUMIF($J:$J,$J38,AV:AV) -> 29.715476 | AX38: =IFERROR(AV38/AW38*AI38,0) -> 0.9279934 | AY38: =AF38/Team_Defense_Table[[#Totals],[Rushing Y/A]]*R38 -> 2.8516942 | AZ38: =AY38*AX38 -> 2.6463534 | BA38: =AN38/25+AU38/10+AZ38/10+AR38*0.5 -> 8.6643417 | BB38: =BA38/(H38/1000) -> 1.2203298 | BC38: =AO38/(H38/1000) -> 0 | BD38: =D38 -> Philip Rivers | BE38: =H38 -> 7100 | BF38: =B38 -> QB
A39: 47691-45859 | B39: QB | C39: Derek | D39: Derek Carr | E39: Carr | F39: 15.7725 | G39: 16 | H39: 7100 | I39: LV@CAR | J39: LV | K39: CAR | O39: =D39 -> Derek Carr | P39: =IFERROR(VLOOKUP(O:O,'Name Bridge'!A:B,2,FALSE),O:O) -> Derek Carr | Q39: =VLOOKUP($K39,'Defensive Stats'!$AC:$AH,2,FALSE) -> 6.7941176 | R39: =VLOOKUP($K39,'Defensive Stats'!$AC:$AH,4,FALSE) -> 5.1595506 | S39: =VLOOKUP($K39,'Defensive Stats'!$AC:$AH,6,FALSE) -> 10.651297 | T39: =IFERROR(VLOOKUP($P39,Passing!$C:$AF,9,FALSE)/VLOOKUP($P39,Passing!$C:$AF,5,FALSE),0) -> 32.0625 | U39: =IFERROR(VLOOKUP($P39,Passing!$C:$AF,11,FALSE)/VLOOKUP($P39,Passing!$C:$AF,5,FALSE),0) -> 253.375 | V39: =IFERROR(VLOOKUP($P39,Passing!$C:$AF,18,FALSE),0) -> 7.9 | W39: =IFERROR(VLOOKUP($P39,Passing!$C:$AF,12,FALSE)/VLOOKUP($P39,Passing!$C:$AF,5,FALSE),0) -> 1.3125 | X39: =IFERROR(IF(OR($B39="D",$B39="K"),0,VLOOKUP($P39,Receiving!$C:$T,7,FALSE)/VLOOKUP($P39,Receiving!$C:$T,5,FALSE)),0)*$AJ39 -> 0 | Y39: =IFERROR(VLOOKUP($P39,Receiving!$C:$T,8,FALSE)/VLOOKUP($P39,Receiving!$C:$T,5,FALSE),0) -> 0 | Z39: =IFERROR(VLOOKUP($P39,Receiving!$C:$T,10,FALSE)/VLOOKUP($P39,Receiving!$C:$T,5,FALSE),0) -> 0 | AA39: =IFERROR(VLOOKUP($P39,Receiving!$C:$T,11,FALSE),0) -> 0 | AB39: =IFERROR(VLOOKUP($P39,Receiving!$C:$T,14,FALSE),0) -> 0 | AC39: =IFERROR(VLOOKUP($P39,Receiving!$C:$T,11,FALSE)/VLOOKUP($P39,Receiving!$C:$T,5,FALSE),0) -> 0 | AD39: =IFERROR(VLOOKUP($P39,Rushing!$C:$P,7,FALSE)/VLOOKUP($P39,Rushing!$C:$P,5,FALSE),0) -> 1.6875 | AE39: =IFERROR(VLOOKUP($P39,Rushing!$C:$P,8,FALSE)/VLOOKUP($P39,Rushing!$C:$P,5,FALSE),0) -> 5.125 | AF39: =IFERROR(VLOOKUP($P39,Rushing!$C:$P,12,FALSE),0) -> 3.0 | AG39: =IFERROR(VLOOKUP($P39,Rushing!$C:$P,9,FALSE)/VLOOKUP($P39,Rushing!$C:$P,5,FALSE),0) -> 0.125 | AH39: =VLOOKUP($J39,'Vegas Odds'!$B:$S,18,FALSE) -> 29.094444 | AI39: =VLOOKUP($J39,'Vegas Odds'!$B:$S,17,FALSE) -> 32.205556 | AJ39: 1 | AK39: =T39*AJ39 -> 32.0625 | AL39: =IF(AND(AJ39=1,B39="QB"),AH39,0) -> 29.094444 | AM39: =V39/Team_Defense_Table[[#Totals],[Passing yds/att]]*'Fanduel Export'!Q39 -> 7.9630803 | AN39: =AM39*AL39 -> 231.68139 | AO39: =IFERROR(IF(OR($B39="D",$B39="K"),0,VLOOKUP($P39,Receiving!$C:$T,7,FALSE)/VLOOKUP($P39,Receiving!$C:$T,5,FALSE)),0)*$AJ39 -> 0 | AP39: =SUMIF($J:$J,$J39,AO:AO) -> 44.777285 | AQ39: =AO39/AP39*AH39 -> 0 | AR39: =Y39*AJ39 -> 0 | AS39: =IFERROR(AR39/AO39*AQ39,0) -> 0 | AT39: =AA39/Team_Defense_Table[[#Totals],[Yards per completion]]*'Fanduel Export'!S39 -> 0 | AU39: =AS39*AT39 -> 0 | AV39: =AD39*AJ39 -> 1.6875 | AW39: =SUMIF($J:$J,$J39,AV:AV) -> 27.354941 | AX39: =IFERROR(AV39/AW39*AI39,0) -> 1.9867298 | AY39: =AF39/Team_Defense_Table[[#Totals],[Rushing Y/A]]*R39 -> 3.5892526 | AZ39: =AY39*AX39 -> 7.1308751 | BA39: =AN39/25+AU39/10+AZ39/10+AR39*0.5 -> 9.9803431 | BB39: =BA39/(H39/1000) -> 1.4056821 | BC39: =AO39/(H39/1000) -> 0 | BD39: =D39 -> Derek Carr | BE39: =H39 -> 7100 | BF39: =B39 -> QB
A40: 47691-14377 | B40: QB | C40: Tyrod | D40: Tyrod Taylor | E40: Taylor | F40: 1.505 | G40: 4 | H40: 7000 | I40: LAC@CIN | J40: LAC | K40: CIN | O40: =D40 -> Tyrod Taylor | P40: =IFERROR(VLOOKUP(O:O,'Name Bridge'!A:B,2,FALSE),O:O) -> Tyrod Taylor | Q40: =VLOOKUP($K40,'Defensive Stats'!$AC:$AH,2,FALSE) -> 7.8496994 | R40: =VLOOKUP($K40,'Defensive Stats'!$AC:$AH,4,FALSE) -> 4.7261905 | S40: =VLOOKUP($K40,'Defensive Stats'!$AC:$AH,6,FALSE) -> 12.717532 | T40: =IFERROR(VLOOKUP($P40,Passing!$C:$AF,9,FALSE)/VLOOKUP($P40,Passing!$C:$AF,5,FALSE),0) -> 0.75 | U40: =IFERROR(VLOOKUP($P40,Passing!$C:$AF,11,FALSE)/VLOOKUP($P40,Passing!$C:$AF,5,FALSE),0) -> 4.125 | V40: =IFERROR(VLOOKUP($P40,Passing!$C:$AF,18,FALSE),0) -> 5.5 | W40: =IFERROR(VLOOKUP($P40,Passing!$C:$AF,12,FALSE)/VLOOKUP($P40,Passing!$C:$AF,5,FALSE),0) -> 0.125 | X40: =IFERROR(IF(OR($B40="D",$B40="K"),0,VLOOKUP($P40,Receiving!$C:$T,7,FALSE)/VLOOKUP($P40,Receiving!$C:$T,5,FALSE)),0)*$AJ40 -> 0 | Y40: =IFERROR(VLOOKUP($P40,Receiving!$C:$T,8,FALSE)/VLOOKUP($P40,Receiving!$C:$T,5,FALSE),0) -> 0 | Z40: =IFERROR(VLOOKUP($P40,Receiving!$C:$T,10,FALSE)/VLOOKUP($P40,Receiving!$C:$T,5,FALSE),0) -> 0 | AA40: =IFERROR(VLOOKUP($P40,Receiving!$C:$T,11,FALSE),0) -> 0 | AB40: =IFERROR(VLOOKUP($P40,Receiving!$C:$T,14,FALSE),0) -> 0 | AC40: =IFERROR(VLOOKUP($P40,Receiving!$C:$T,11,FALSE)/VLOOKUP($P40,Receiving!$C:$T,5,FALSE),0) -> 0 | AD40: =IFERROR(VLOOKUP($P40,Rushing!$C:$P,7,FALSE)/VLOOKUP($P40,Rushing!$C:$P,5,FALSE),0) -> 1.25 | AE40: =IFERROR(VLOOKUP($P40,Rushing!$C:$P,8,FALSE)/VLOOKUP($P40,Rushing!$C:$P,5,FALSE),0) -> 0.875 | AF40: =IFERROR(VLOOKUP($P40,Rushing!$C:$P,12,FALSE),0) -> 0.7 | AG40: =IFERROR(VLOOKUP($P40,Rushing!$C:$P,9,FALSE)/VLOOKUP($P40,Rushing!$C:$P,5,FALSE),0) -> 0 | AH40: =VLOOKUP($J40,'Vegas Odds'!$B:$S,18,FALSE) -> 34.151747 | AI40: =VLOOKUP($J40,'Vegas Odds'!$B:$S,17,FALSE) -> 26.748253 | AJ40: 1 | AK40: =T40*AJ40 -> 0.75 | AL40: =IF(AND(AJ40=1,B40="QB"),AH40,0) -> 34.151747 | AM40: =V40/Team_Defense_Table[[#Totals],[Passing yds/att]]*'Fanduel Export'!Q40 -> 6.4052584 | AN40: =AM40*AL40 -> 218.75076 | AO40: =IFERROR(IF(OR($B40="D",$B40="K"),0,VLOOKUP($P40,Receiving!$C:$T,7,FALSE)/VLOOKUP($P40,Receiving!$C:$T,5,FALSE)),0)*$AJ40 -> 0 | AP40: =SUMIF($J:$J,$J40,AO:AO) -> 32.673214 | AQ40: =AO40/AP40*AH40 -> 0 | AR40: =Y40*AJ40 -> 0 | AS40: =IFERROR(AR40/AO40*AQ40,0) -> 0 | AT40: =AA40/Team_Defense_Table[[#Totals],[Yards per completion]]*'Fanduel Export'!S40 -> 0 | AU40: =AS40*AT40 -> 0 | AV40: =AD40*AJ40 -> 1.25 | AW40: =SUMIF($J:$J,$J40,AV:AV) -> 14.61131 | AX40: =IFERROR(AV40/AW40*AI40,0) -> 2.2883176 | AY40: =AF40/Team_Defense_Table[[#Totals],[Rushing Y/A]]*R40 -> 0.76714976 | AZ40: =AY40*AX40 -> 1.7554823 | BA40: =AN40/25+AU40/10+AZ40/10+AR40*0.5 -> 8.9255787 | BB40: =BA40/(H40/1000) -> 1.2750827 | BC40: =AO40/(H40/1000) -> 0 | BD40: =D40 -> Tyrod Taylor | BE40: =H40 -> 7000 | BF40: =B40 -> QB
A41: 47691-41535 | B41: QB | C41: Baker | D41: Baker Mayfield | E41: Mayfield | F41: 15.63625 | G41: 16 | H41: 7000 | I41: CLE@BAL | J41: CLE | K41: BAL | O41: =D41 -> Baker Mayfield | P41: =IFERROR(VLOOKUP(O:O,'Name Bridge'!A:B,2,FALSE),O:O) -> Baker Mayfield | Q41: =VLOOKUP($K41,'Defensive Stats'!$AC:$AH,2,FALSE) -> 6.09375 | R41: =VLOOKUP($K41,'Defensive Stats'!$AC:$AH,4,FALSE) -> 4.3941176 | S41: =VLOOKUP($K41,'Defensive Stats'!$AC:$AH,6,FALSE) -> 10.424528 | T41: =IFERROR(VLOOKUP($P41,Passing!$C:$AF,9,FALSE)/VLOOKUP($P41,Passing!$C:$AF,5,FALSE),0) -> 33.375 | U41: =IFERROR(VLOOKUP($P41,Passing!$C:$AF,11,FALSE)/VLOOKUP($P41,Passing!$C:$AF,5,FALSE),0) -> 239.1875 | V41: =IFERROR(VLOOKUP($P41,Passing!$C:$AF,18,FALSE),0) -> 7.2 | W41: =IFERROR(VLOOKUP($P41,Passing!$C:$AF,12,FALSE)/VLOOKUP($P41,Passing!$C:$AF,5,FALSE),0) -> 1.375 | X41: =IFERROR(IF(OR($B41="D",$B41="K"),0,VLOOKUP($P41,Receiving!$C:$T,7,FALSE)/VLOOKUP($P41,Receiving!$C:$T,5,FALSE)),0)*$AJ41 -> 0 | Y41: =IFERROR(VLOOKUP($P41,Receiving!$C:$T,8,FALSE)/VLOOKUP($P41,Receiving!$C:$T,5,FALSE),0) -> 0 | Z41: =IFERROR(VLOOKUP($P41,Receiving!$C:$T,10,FALSE)/VLOOKUP($P41,Receiving!$C:$T,5,FALSE),0) -> 0 | AA41: =IFERROR(VLOOKUP($P41,Receiving!$C:$T,11,FALSE),0) -> 0 | AB41: =IFERROR(VLOOKUP($P41,Receiving!$C:$T,14,FALSE),0) -> 0 | AC41: =IFERROR(VLOOKUP($P41,Receiving!$C:$T,11,FALSE)/VLOOKUP($P41,Receiving!$C:$T,5,FALSE),0) -> 0 | AD41: =IFERROR(VLOOKUP($P41,Rushing!$C:$P,7,FALSE)/VLOOKUP($P41,Rushing!$C:$P,5,FALSE),0) -> 1.75 | AE41: =IFERROR(VLOOKUP($P41,Rushing!$C:$P,8,FALSE)/VLOOKUP($P41,Rushing!$C:$P,5,FALSE),0) -> 8.8125 | AF41: =IFERROR(VLOOKUP($P41,Rushing!$C:$P,12,FALSE),0) -> 5.0 | AG41: =IFERROR(VLOOKUP($P41,Rushing!$C:$P,9,FALSE)/VLOOKUP($P41,Rushing!$C:$P,5,FALSE),0) -> 0.1875 | AH41: =VLOOKUP($J41,'Vegas Odds'!$B:$S,18,FALSE) -> 39.317423 | AI41: =VLOOKUP($J41,'Vegas Odds'!$B:$S,17,FALSE) -> 20.682577 | AJ41: 1 | AK41: =T41*AJ41 -> 33.375 | AL41: =IF(AND(AJ41=1,B41="QB"),AH41,0) -> 39.317423 | AM41: =V41/Team_Defense_Table[[#Totals],[Passing yds/att]]*'Fanduel Export'!Q41 -> 6.5093567 | AN41: =AM41*AL41 -> 255.93113 | AO41: =IFERROR(IF(OR($B41="D",$B41="K"),0,VLOOKUP($P41,Receiving!$C:$T,7,FALSE)/VLOOKUP($P41,Receiving!$C:$T,5,FALSE)),0)*$AJ41 -> 0 | AP41: =SUMIF($J:$J,$J41,AO:AO) -> 34.054518 | AQ41: =AO41/AP41*AH41 -> 0 | AR41: =Y41*AJ41 -> 0 | AS41: =IFERROR(AR41/AO41*AQ41,0) -> 0 | AT41: =AA41/Team_Defense_Table[[#Totals],[Yards per completion]]*'Fanduel Export'!S41 -> 0 | AU41: =AS41*AT41 -> 0 | AV41: =AD41*AJ41 -> 1.75 | AW41: =SUMIF($J:$J,$J41,AV:AV) -> 28.633929 | AX41: =IFERROR(AV41/AW41*AI41,0) -> 1.2640427 | AY41: =AF41/Team_Defense_Table[[#Totals],[Rushing Y/A]]*R41 -> 5.0946292 | AZ41: =AY41*AX41 -> 6.439829 | BA41: =AN41/25+AU41/10+AZ41/10+AR41*0.5 -> 10.881228 | BB41: =BA41/(H41/1000) -> 1.5544612 | BC41: =AO41/(H41/1000) -> 0 | BD41: =D41 -> Baker Mayfield | BE41: =H41 -> 7000 | BF41: =B41 -> QB
A42: 47691-29253 | B42: WR | C42: Keenan | D42: Keenan Allen | E42: Allen | F42: 13.09375 | G42: 16 | H42: 7000 | I42: LAC@CIN | J42: LAC | K42: CIN | O42: =D42 -> Keenan Allen | P42: =IFERROR(VLOOKUP(O:O,'Name Bridge'!A:B,2,FALSE),O:O) -> Keenan Allen | Q42: =VLOOKUP($K42,'Defensive Stats'!$AC:$AH,2,FALSE) -> 7.8496994 | R42: =VLOOKUP($K42,'Defensive Stats'!$AC:$AH,4,FALSE) -> 4.7261905 | S42: =VLOOKUP($K42,'Defensive Stats'!$AC:$AH,6,FALSE) -> 12.717532 | T42: =IFERROR(VLOOKUP($P42,Passing!$C:$AF,9,FALSE)/VLOOKUP($P42,Passing!$C:$AF,5,FALSE),0) -> 0 | U42: =IFERROR(VLOOKUP($P42,Passing!$C:$AF,11,FALSE)/VLOOKUP($P42,Passing!$C:$AF,5,FALSE),0) -> 0 | V42: =IFERROR(VLOOKUP($P42,Passing!$C:$AF,18,FALSE),0) -> 0 | W42: =IFERROR(VLOOKUP($P42,Passing!$C:$AF,12,FALSE)/VLOOKUP($P42,Passing!$C:$AF,5,FALSE),0) -> 0 | X42: =IFERROR(IF(OR($B42="D",$B42="K"),0,VLOOKUP($P42,Receiving!$C:$T,7,FALSE)/VLOOKUP($P42,Receiving!$C:$T,5,FALSE)),0)*$AJ42 -> 9.3125 | Y42: =IFERROR(VLOOKUP($P42,Receiving!$C:$T,8,FALSE)/VLOOKUP($P42,Receiving!$C:$T,5,FALSE),0) -> 6.5 | Z42: =IFERROR(VLOOKUP($P42,Receiving!$C:$T,10,FALSE)/VLOOKUP($P42,Receiving!$C:$T,5,FALSE),0) -> 74.9375 | AA42: =IFERROR(VLOOKUP($P42,Receiving!$C:$T,11,FALSE),0) -> 11.5 | AB42: =IFERROR(VLOOKUP($P42,Receiving!$C:$T,14,FALSE),0) -> 45 | AC42: =IFERROR(VLOOKUP($P42,Receiving!$C:$T,11,FALSE)/VLOOKUP($P42,Receiving!$C:$T,5,FALSE),0) -> 0.71875 | AD42: =IFERROR(VLOOKUP($P42,Rushing!$C:$P,7,FALSE)/VLOOKUP($P42,Rushing!$C:$P,5,FALSE),0) -> 0.1875 | AE42: =IFERROR(VLOOKUP($P42,Rushing!$C:$P,8,FALSE)/VLOOKUP($P42,Rushing!$C:$P,5,FALSE),0) -> 1 | AF42: =IFERROR(VLOOKUP($P42,Rushing!$C:$P,12,FALSE),0) -> 5.3 | AG42: =IFERROR(VLOOKUP($P42,Rushing!$C:$P,9,FALSE)/VLOOKUP($P42,Rushing!$C:$P,5,FALSE),0) -> 0 | AH42: =VLOOKUP($J42,'Vegas Odds'!$B:$S,18,FALSE) -> 34.151747 | AI42: =VLOOKUP($J42,'Vegas Odds'!$B:$S,17,FALSE) -> 26.748253 | AJ42: 1 | AK42: =T42*AJ42 -> 0 | AL42: =IF(AND(AJ42=1,B42="QB"),AH42,0) -> 0 | AM42: =V42/Team_Defense_Table[[#Totals],[Passing yds/att]]*'Fanduel Export'!Q42 -> 0 | AN42: =AM42*AL42 -> 0 | AO42: =IFERROR(IF(OR($B42="D",$B42="K"),0,VLOOKUP($P42,Receiving!$C:$T,7,FALSE)/VLOOKUP($P42,Receiving!$C:$T,5,FALSE)),0)*$AJ42 -> 9.3125 | AP42: =SUMIF($J:$J,$J42,AO:AO) -> 32.673214 | AQ42: =AO42/AP42*AH42 -> 9.7339104 | AR42: =Y42*AJ42 -> 6.5 | AS42: =IFERROR(AR42/AO42*AQ42,0) -> 6.7941388 | AT42: =AA42/Team_Defense_Table[[#Totals],[Yards per completion]]*'Fanduel Export'!S42 -> 13.773261 | AU42: =AS42*AT42 -> 93.577445 | AV42: =AD42*AJ42 -> 0.1875 | AW42: =SUMIF($J:$J,$J42,AV:AV) -> 14.61131 | AX42: =IFERROR(AV42/AW42*AI42,0) -> 0.34324764 | AY42: =AF42/Team_Defense_Table[[#Totals],[Rushing Y/A]]*R42 -> 5.8084196 | AZ42: =AY42*AX42 -> 1.9937263 | BA42: =AN42/25+AU42/10+AZ42/10+AR42*0.5 -> 12.807117 | BB42: =BA42/(H42/1000) -> 1.8295882 | BC42: =AO42/(H42/1000) -> 1.3303571 | BD42: =D42 -> Keenan Allen | BE42: =H42 -> 7000 | BF42: =B42 -> WR
A43: 47691-14211 | B43: RB | C43: Mark | D43: Mark Ingram II | E43: Ingram II | F43: 15.3 | G43: 15 | H43: 7000 | I43: CLE@BAL | J43: BAL | K43: CLE | O43: =D43 -> Mark Ingram II | P43: =IFERROR(VLOOKUP(O:O,'Name Bridge'!A:B,2,FALSE),O:O) -> Mark Ingram II | Q43: =VLOOKUP($K43,'Defensive Stats'!$AC:$AH,2,FALSE) -> 6.7641326 | R43: =VLOOKUP($K43,'Defensive Stats'!$AC:$AH,4,FALSE) -> 5 | S43: =VLOOKUP($K43,'Defensive Stats'!$AC:$AH,6,FALSE) -> 10.91195 | T43: =IFERROR(VLOOKUP($P43,Passing!$C:$AF,9,FALSE)/VLOOKUP($P43,Passing!$C:$AF,5,FALSE),0) -> 0 | U43: =IFERROR(VLOOKUP($P43,Passing!$C:$AF,11,FALSE)/VLOOKUP($P43,Passing!$C:$AF,5,FALSE),0) -> 0 | V43: =IFERROR(VLOOKUP($P43,Passing!$C:$AF,18,FALSE),0) -> 0 | W43: =IFERROR(VLOOKUP($P43,Passing!$C:$AF,12,FALSE)/VLOOKUP($P43,Passing!$C:$AF,5,FALSE),0) -> 0 | X43: =IFERROR(IF(OR($B43="D",$B43="K"),0,VLOOKUP($P43,Receiving!$C:$T,7,FALSE)/VLOOKUP($P43,Receiving!$C:$T,5,FALSE)),0)*$AJ43 -> 0 | Y43: =IFERROR(VLOOKUP($P43,Receiving!$C:$T,8,FALSE)/VLOOKUP($P43,Receiving!$C:$T,5,FALSE),0) -> 0 | Z43: =IFERROR(VLOOKUP($P43,Receiving!$C:$T,10,FALSE)/VLOOKUP($P43,Receiving!$C:$T,5,FALSE),0) -> 0 | AA43: =IFERROR(VLOOKUP($P43,Receiving!$C:$T,11,FALSE),0) -> 0 | AB43: =IFERROR(VLOOKUP($P43,Receiving!$C:$T,14,FALSE),0) -> 0 | AC43: =IFERROR(VLOOKUP($P43,Receiving!$C:$T,11,FALSE)/VLOOKUP($P43,Receiving!$C:$T,5,FALSE),0) -> 0 | AD43: =IFERROR(VLOOKUP($P43,Rushing!$C:$P,7,FALSE)/VLOOKUP($P43,Rushing!$C:$P,5,FALSE),0) -> 0 | AE43: =IFERROR(VLOOKUP($P43,Rushing!$C:$P,8,FALSE)/VLOOKUP($P43,Rushing!$C:$P,5,FALSE),0) -> 0 | AF43: =IFERROR(VLOOKUP($P43,Rushing!$C:$P,12,FALSE),0) -> 0 | AG43: =IFERROR(VLOOKUP($P43,Rushing!$C:$P,9,FALSE)/VLOOKUP($P43,Rushing!$C:$P,5,FALSE),0) -> 0 | AH43: =VLOOKUP($J43,'Vegas Odds'!$B:$S,18,FALSE) -> 12.779864 | AI43: =VLOOKUP($J43,'Vegas Odds'!$B:$S,17,FALSE) -> 50.520136 | AJ43: 1 | AK43: =T43*AJ43 -> 0 | AL43: =IF(AND(AJ43=1,B43="QB"),AH43,0) -> 0 | AM43: =V43/Team_Defense_Table[[#Totals],[Passing yds/att]]*'Fanduel Export'!Q43 -> 0 | AN43: =AM43*AL43 -> 0 | AO43: =IFERROR(IF(OR($B43="D",$B43="K"),0,VLOOKUP($P43,Receiving!$C:$T,7,FALSE)/VLOOKUP($P43,Receiving!$C:$T,5,FALSE)),0)*$AJ43 -> 0 | AP43: =SUMIF($J:$J,$J43,AO:AO) -> 19.229762 | AQ43: =AO43/AP43*AH43 -> 0 | AR43: =Y43*AJ43 -> 0 | AS43: =IFERROR(AR43/AO43*AQ43,0) -> 0 | AT43: =AA43/Team_Defense_Table[[#Totals],[Yards per completion]]*'Fanduel Export'!S43 -> 0 | AU43: =AS43*AT43 -> 0 | AV43: =AD43*AJ43 -> 0 | AW43: =SUMIF($J:$J,$J43,AV:AV) -> 27.742262 | AX43: =IFERROR(AV43/AW43*AI43,0) -> 0 | AY43: =AF43/Team_Defense_Table[[#Totals],[Rushing Y/A]]*R43 -> 0 | AZ43: =AY43*AX43 -> 0 | BA43: =AN43/25+AU43/10+AZ43/10+AR43*0.5 -> 0 | BB43: =BA43/(H43/1000) -> 0 | BC43: =AO43/(H43/1000) -> 0 | BD43: =D43 -> Mark Ingram II | BE43: =H43 -> 7000 | BF43: =B43 -> RB
A44: 47691-31360 | B44: WR | C44: Odell | D44: Odell Beckham Jr. | E44: Beckham Jr. | F44: 10.26875 | G44: 16 | H44: 6900 | I44: CLE@BAL | J44: CLE | K44: BAL | O44: =D44 -> Odell Beckham Jr. | P44: =IFERROR(VLOOKUP(O:O,'Name Bridge'!A:B,2,FALSE),O:O) -> Odell Beckham | Q44: =VLOOKUP($K44,'Defensive Stats'!$AC:$AH,2,FALSE) -> 6.09375 | R44: =VLOOKUP($K44,'Defensive Stats'!$AC:$AH,4,FALSE) -> 4.3941176 | S44: =VLOOKUP($K44,'Defensive Stats'!$AC:$AH,6,FALSE) -> 10.424528 | T44: =IFERROR(VLOOKUP($P44,Passing!$C:$AF,9,FALSE)/VLOOKUP($P44,Passing!$C:$AF,5,FALSE),0) -> 0 | U44: =IFERROR(VLOOKUP($P44,Passing!$C:$AF,11,FALSE)/VLOOKUP($P44,Passing!$C:$AF,5,FALSE),0) -> 0 | V44: =IFERROR(VLOOKUP($P44,Passing!$C:$AF,18,FALSE),0) -> 0 | W44: =IFERROR(VLOOKUP($P44,Passing!$C:$AF,12,FALSE)/VLOOKUP($P44,Passing!$C:$AF,5,FALSE),0) -> 0 | X44: =IFERROR(IF(OR($B44="D",$B44="K"),0,VLOOKUP($P44,Receiving!$C:$T,7,FALSE)/VLOOKUP($P44,Receiving!$C:$T,5,FALSE)),0)*$AJ44 -> 0 | Y44: =IFERROR(VLOOKUP($P44,Receiving!$C:$T,8,FALSE)/VLOOKUP($P44,Receiving!$C:$T,5,FALSE),0) -> 0 | Z44: =IFERROR(VLOOKUP($P44,Receiving!$C:$T,10,FALSE)/VLOOKUP($P44,Receiving!$C:$T,5,FALSE),0) -> 0 | AA44: =IFERROR(VLOOKUP($P44,Receiving!$C:$T,11,FALSE),0) -> 0 | AB44: =IFERROR(VLOOKUP($P44,Receiving!$C:$T,14,FALSE),0) -> 0 | AC44: =IFERROR(VLOOKUP($P44,Receiving!$C:$T,11,FALSE)/VLOOKUP($P44,Receiving!$C:$T,5,FALSE),0) -> 0 | AD44: =IFERROR(VLOOKUP($P44,Rushing!$C:$P,7,FALSE)/VLOOKUP($P44,Rushing!$C:$P,5,FALSE),0) -> 0 | AE44: =IFERROR(VLOOKUP($P44,Rushing!$C:$P,8,FALSE)/VLOOKUP($P44,Rushing!$C:$P,5,FALSE),0) -> 0 | AF44: =IFERROR(VLOOKUP($P44,Rushing!$C:$P,12,FALSE),0) -> 0 | AG44: =IFERROR(VLOOKUP($P44,Rushing!$C:$P,9,FALSE)/VLOOKUP($P44,Rushing!$C:$P,5,FALSE),0) -> 0 | AH44: =VLOOKUP($J44,'Vegas Odds'!$B:$S,18,FALSE) -> 39.317423 | AI44: =VLOOKUP($J44,'Vegas Odds'!$B:$S,17,FALSE) -> 20.682577 | AJ44: 1 | AK44: =T44*AJ44 -> 0 | AL44: =IF(AND(AJ44=1,B44="QB"),AH44,0) -> 0 | AM44: =V44/Team_Defense_Table[[#Totals],[Passing yds/att]]*'Fanduel Export'!Q44 -> 0 | AN44: =AM44*AL44 -> 0 | AO44: =IFERROR(IF(OR($B44="D",$B44="K"),0,VLOOKUP($P44,Receiving!$C:$T,7,FALSE)/VLOOKUP($P44,Receiving!$C:$T,5,FALSE)),0)*$AJ44 -> 0 | AP44: =SUMIF($J:$J,$J44,AO:AO) -> 34.054518 | AQ44: =AO44/AP44*AH44 -> 0 | AR44: =Y44*AJ44 -> 0 | AS44: =IFERROR(AR44/AO44*AQ44,0) -> 0 | AT44: =AA44/Team_Defense_Table[[#Totals],[Yards per completion]]*'Fanduel Export'!S44 -> 0 | AU44: =AS44*AT44 -> 0 | AV44: =AD44*AJ44 -> 0 | AW44: =SUMIF($J:$J,$J44,AV:AV) -> 28.633929 | AX44: =IFERROR(AV44/AW44*AI44,0) -> 0 | AY44: =AF44/Team_Defense_Table[[#Totals],[Rushing Y/A]]*R44 -> 0 | AZ44: =AY44*AX44 -> 0 | BA44: =AN44/25+AU44/10+AZ44/10+AR44*0.5 -> 0 | BB44: =BA44/(H44/1000) -> 0 | BC44: =AO44/(H44/1000) -> 0 | BD44: =D44 -> Odell Beckham Jr. | BE44: =H44 -> 6900 | BF44: =B44 -> WR
A45: 47691-52922 | B45: RB | C45: Leonard | D45: Leonard Fournette | E45: Fournette | F45: 14.76 | G45: 15 | H45: 6900 | I45: IND@JAC | J45: JAC | K45: IND | O45: =D45 -> Leonard Fournette | P45: =IFERROR(VLOOKUP(O:O,'Name Bridge'!A:B,2,FALSE),O:O) -> Leonard Fournette | Q45: =VLOOKUP($K45,'Defensive Stats'!$AC:$AH,2,FALSE) -> 7.0854093 | R45: =VLOOKUP($K45,'Defensive Stats'!$AC:$AH,4,FALSE) -> 4.0913838 | S45: =VLOOKUP($K45,'Defensive Stats'!$AC:$AH,6,FALSE) -> 10.106599 | T45: =IFERROR(VLOOKUP($P45,Passing!$C:$AF,9,FALSE)/VLOOKUP($P45,Passing!$C:$AF,5,FALSE),0) -> 0 | U45: =IFERROR(VLOOKUP($P45,Passing!$C:$AF,11,FALSE)/VLOOKUP($P45,Passing!$C:$AF,5,FALSE),0) -> 0 | V45: =IFERROR(VLOOKUP($P45,Passing!$C:$AF,18,FALSE),0) -> 0 | W45: =IFERROR(VLOOKUP($P45,Passing!$C:$AF,12,FALSE)/VLOOKUP($P45,Passing!$C:$AF,5,FALSE),0) -> 0 | X45: =IFERROR(IF(OR($B45="D",$B45="K"),0,VLOOKUP($P45,Receiving!$C:$T,7,FALSE)/VLOOKUP($P45,Receiving!$C:$T,5,FALSE)),0)*$AJ45 -> 6.6666667 | Y45: =IFERROR(VLOOKUP($P45,Receiving!$C:$T,8,FALSE)/VLOOKUP($P45,Receiving!$C:$T,5,FALSE),0) -> 5.0666667 | Z45: =IFERROR(VLOOKUP($P45,Receiving!$C:$T,10,FALSE)/VLOOKUP($P45,Receiving!$C:$T,5,FALSE),0) -> 34.8 | AA45: =IFERROR(VLOOKUP($P45,Receiving!$C:$T,11,FALSE),0) -> 6.9 | AB45: =IFERROR(VLOOKUP($P45,Receiving!$C:$T,14,FALSE),0) -> 27 | AC45: =IFERROR(VLOOKUP($P45,Receiving!$C:$T,11,FALSE)/VLOOKUP($P45,Receiving!$C:$T,5,FALSE),0) -> 0.46 | AD45: =IFERROR(VLOOKUP($P45,Rushing!$C:$P,7,FALSE)/VLOOKUP($P45,Rushing!$C:$P,5,FALSE),0) -> 17.666667 | AE45: =IFERROR(VLOOKUP($P45,Rushing!$C:$P,8,FALSE)/VLOOKUP($P45,Rushing!$C:$P,5,FALSE),0) -> 76.8 | AF45: =IFERROR(VLOOKUP($P45,Rushing!$C:$P,12,FALSE),0) -> 4.3 | AG45: =IFERROR(VLOOKUP($P45,Rushing!$C:$P,9,FALSE)/VLOOKUP($P45,Rushing!$C:$P,5,FALSE),0) -> 0.2 | AH45: =VLOOKUP($J45,'Vegas Odds'!$B:$S,18,FALSE) -> 43.022921 | AI45: =VLOOKUP($J45,'Vegas Odds'!$B:$S,17,FALSE) -> 18.377079 | AJ45: 1 | AK45: =T45*AJ45 -> 0 | AL45: =IF(AND(AJ45=1,B45="QB"),AH45,0) -> 0 | AM45: =V45/Team_Defense_Table[[#Totals],[Passing yds/att]]*'Fanduel Export'!Q45 -> 0 | AN45: =AM45*AL45 -> 0 | AO45: =IFERROR(IF(OR($B45="D",$B45="K"),0,VLOOKUP($P45,Receiving!$C:$T,7,FALSE)/VLOOKUP($P45,Receiving!$C:$T,5,FALSE)),0)*$AJ45 -> 6.6666667 | AP45: =SUMIF($J:$J,$J45,AO:AO) -> 39.601299 | AQ45: =AO45/AP45*AH45 -> 7.2426784 | AR45: =Y45*AJ45 -> 5.0666667 | AS45: =IFERROR(AR45/AO45*AQ45,0) -> 5.5044356 | AT45: =AA45/Team_Defense_Table[[#Totals],[Yards per completion]]*'Fanduel Export'!S45 -> 6.5673505 | AU45: =AS45*AT45 -> 36.149558 | AV45: =AD45*AJ45 -> 17.666667 | AW45: =SUMIF($J:$J,$J45,AV:AV) -> 30.299351 | AX45: =IFERROR(AV45/AW45*AI45,0) -> 10.715138 | AY45: =AF45/Team_Defense_Table[[#Totals],[Rushing Y/A]]*R45 -> 4.0795247 | AZ45: =AY45*AX45 -> 43.712672 | BA45: =AN45/25+AU45/10+AZ45/10+AR45*0.5 -> 10.519556 | BB45: =BA45/(H45/1000) -> 1.5245734 | BC45: =AO45/(H45/1000) -> 0.96618357 | BD45: =D45 -> Leonard Fournette | BE45: =H45 -> 6900 | BF45: =B45 -> RB
A46: 47691-38628 | B46: QB | C46: Mitchell | D46: Mitchell Trubisky | E46: Trubisky | F46: 14.188 | G46: 15 | H46: 6900 | I46: CHI@DET | J46: CHI | K46: DET | O46: =D46 -> Mitchell Trubisky | P46: =IFERROR(VLOOKUP(O:O,'Name Bridge'!A:B,2,FALSE),O:O) -> Mitchell Trubisky | Q46: =VLOOKUP($K46,'Defensive Stats'!$AC:$AH,2,FALSE) -> 7.4484452 | R46: =VLOOKUP($K46,'Defensive Stats'!$AC:$AH,4,FALSE) -> 4.0769231 | S46: =VLOOKUP($K46,'Defensive Stats'!$AC:$AH,6,FALSE) -> 11.944882 | T46: =IFERROR(VLOOKUP($P46,Passing!$C:$AF,9,FALSE)/VLOOKUP($P46,Passing!$C:$AF,5,FALSE),0) -> 34.4 | U46: =IFERROR(VLOOKUP($P46,Passing!$C:$AF,11,FALSE)/VLOOKUP($P46,Passing!$C:$AF,5,FALSE),0) -> 209.2 | V46: =IFERROR(VLOOKUP($P46,Passing!$C:$AF,18,FALSE),0) -> 6.1 | W46: =IFERROR(VLOOKUP($P46,Passing!$C:$AF,12,FALSE)/VLOOKUP($P46,Passing!$C:$AF,5,FALSE),0) -> 1.1333333 | X46: =IFERROR(IF(OR($B46="D",$B46="K"),0,VLOOKUP($P46,Receiving!$C:$T,7,FALSE)/VLOOKUP($P46,Receiving!$C:$T,5,FALSE)),0)*$AJ46 -> 0 | Y46: =IFERROR(VLOOKUP($P46,Receiving!$C:$T,8,FALSE)/VLOOKUP($P46,Receiving!$C:$T,5,FALSE),0) -> 0 | Z46: =IFERROR(VLOOKUP($P46,Receiving!$C:$T,10,FALSE)/VLOOKUP($P46,Receiving!$C:$T,5,FALSE),0) -> 0 | AA46: =IFERROR(VLOOKUP($P46,Receiving!$C:$T,11,FALSE),0) -> 0 | AB46: =IFERROR(VLOOKUP($P46,Receiving!$C:$T,14,FALSE),0) -> 0 | AC46: =IFERROR(VLOOKUP($P46,Receiving!$C:$T,11,FALSE)/VLOOKUP($P46,Receiving!$C:$T,5,FALSE),0) -> 0 | AD46: =IFERROR(VLOOKUP($P46,Rushing!$C:$P,7,FALSE)/VLOOKUP($P46,Rushing!$C:$P,5,FALSE),0) -> 3.2 | AE46: =IFERROR(VLOOKUP($P46,Rushing!$C:$P,8,FALSE)/VLOOKUP($P46,Rushing!$C:$P,5,FALSE),0) -> 12.866667 | AF46: =IFERROR(VLOOKUP($P46,Rushing!$C:$P,12,FALSE),0) -> 4.0 | AG46: =IFERROR(VLOOKUP($P46,Rushing!$C:$P,9,FALSE)/VLOOKUP($P46,Rushing!$C:$P,5,FALSE),0) -> 0.13333333 | AH46: =VLOOKUP($J46,'Vegas Odds'!$B:$S,18,FALSE) -> 39.087289 | AI46: =VLOOKUP($J46,'Vegas Odds'!$B:$S,17,FALSE) -> 21.912711 | AJ46: 1 | AK46: =T46*AJ46 -> 34.4 | AL46: =IF(AND(AJ46=1,B46="QB"),AH46,0) -> 39.087289 | AM46: =V46/Team_Defense_Table[[#Totals],[Passing yds/att]]*'Fanduel Export'!Q46 -> 6.7408769 | AN46: =AM46*AL46 -> 263.48261 | AO46: =IFERROR(IF(OR($B46="D",$B46="K"),0,VLOOKUP($P46,Receiving!$C:$T,7,FALSE)/VLOOKUP($P46,Receiving!$C:$T,5,FALSE)),0)*$AJ46 -> 0 | AP46: =SUMIF($J:$J,$J46,AO:AO) -> 29.935714 | AQ46: =AO46/AP46*AH46 -> 0 | AR46: =Y46*AJ46 -> 0 | AS46: =IFERROR(AR46/AO46*AQ46,0) -> 0 | AT46: =AA46/Team_Defense_Table[[#Totals],[Yards per completion]]*'Fanduel Export'!S46 -> 0 | AU46: =AS46*AT46 -> 0 | AV46: =AD46*AJ46 -> 3.2 | AW46: =SUMIF($J:$J,$J46,AV:AV) -> 24.985714 | AX46: =IFERROR(AV46/AW46*AI46,0) -> 2.8064306 | AY46: =AF46/Team_Defense_Table[[#Totals],[Rushing Y/A]]*R46 -> 3.7814939 | AZ46: =AY46*AX46 -> 10.6125 | BA46: =AN46/25+AU46/10+AZ46/10+AR46*0.5 -> 11.600554 | BB46: =BA46/(H46/1000) -> 1.6812398 | BC46: =AO46/(H46/1000) -> 0 | BD46: =D46 -> Mitchell Trubisky | BE46: =H46 -> 6900 | BF46: =B46 -> QB
... A66: 47691-7659 | B66: QB | C66: Ryan | D66: Ryan Fitzpatrick | E66: Fitzpatrick | F66: 16.964 | G66: 15 | H66: 6400 | I66: MIA@NE | J66: MIA | K66: NE | O66: =D66 -> Ryan Fitzpatrick | P66: =IFERROR(VLOOKUP(O:O,'Name Bridge'!A:B,2,FALSE),O:O) -> Ryan Fitzpatrick | Q66: =VLOOKUP($K66,'Defensive Stats'!$AC:$AH,2,FALSE) -> 5.3843284 | R66: =VLOOKUP($K66,'Defensive Stats'!$AC:$AH,4,FALSE) -> 4.1863014 | S66: =VLOOKUP($K66,'Defensive Stats'!$AC:$AH,6,FALSE) -> 9.5247525 | T66: =IFERROR(VLOOKUP($P66,Passing!$C:$AF,9,FALSE)/VLOOKUP($P66,Passing!$C:$AF,5,FALSE),0) -> 33.466667 | U66: =IFERROR(VLOOKUP($P66,Passing!$C:$AF,11,FALSE)/VLOOKUP($P66,Passing!$C:$AF,5,FALSE),0) -> 235.26667 | V66: =IFERROR(VLOOKUP($P66,Passing!$C:$AF,18,FALSE),0) -> 7.0 | W66: =IFERROR(VLOOKUP($P66,Passing!$C:$AF,12,FALSE)/VLOOKUP($P66,Passing!$C:$AF,5,FALSE),0) -> 1.3333333 | X66: =IFERROR(IF(OR($B66="D",$B66="K"),0,VLOOKUP($P66,Receiving!$C:$T,7,FALSE)/VLOOKUP($P66,Receiving!$C:$T,5,FALSE)),0)*$AJ66 -> 0 | Y66: =IFERROR(VLOOKUP($P66,Receiving!$C:$T,8,FALSE)/VLOOKUP($P66,Receiving!$C:$T,5,FALSE),0) -> 0 | Z66: =IFERROR(VLOOKUP($P66,Receiving!$C:$T,10,FALSE)/VLOOKUP($P66,Receiving!$C:$T,5,FALSE),0) -> 0 | AA66: =IFERROR(VLOOKUP($P66,Receiving!$C:$T,11,FALSE),0) -> 0 | AB66: =IFERROR(VLOOKUP($P66,Receiving!$C:$T,14,FALSE),0) -> 0 | AC66: =IFERROR(VLOOKUP($P66,Receiving!$C:$T,11,FALSE)/VLOOKUP($P66,Receiving!$C:$T,5,FALSE),0) -> 0 | AD66: =IFERROR(VLOOKUP($P66,Rushing!$C:$P,7,FALSE)/VLOOKUP($P66,Rushing!$C:$P,5,FALSE),0) -> 3.6 | AE66: =IFERROR(VLOOKUP($P66,Rushing!$C:$P,8,FALSE)/VLOOKUP($P66,Rushing!$C:$P,5,FALSE),0) -> 16.2 | AF66: =IFERROR(VLOOKUP($P66,Rushing!$C:$P,12,FALSE),0) -> 4.5 | AG66: =IFERROR(VLOOKUP($P66,Rushing!$C:$P,9,FALSE)/VLOOKUP($P66,Rushing!$C:$P,5,FALSE),0) -> 0.26666667 | AH66: =VLOOKUP($J66,'Vegas Odds'!$B:$S,18,FALSE) -> 42.492175 | AI66: =VLOOKUP($J66,'Vegas Odds'!$B:$S,17,FALSE) -> 20.507825 | AJ66: 1 | AK66: =T66*AJ66 -> 33.466667 | AL66: =IF(AND(AJ66=1,B66="QB"),AH66,0) -> 42.492175 | AM66: =V66/Team_Defense_Table[[#Totals],[Passing yds/att]]*'Fanduel Export'!Q66 -> 5.5917857 | AN66: =AM66*AL66 -> 237.60713 | AO66: =IFERROR(IF(OR($B66="D",$B66="K"),0,VLOOKUP($P66,Receiving!$C:$T,7,FALSE)/VLOOKUP($P66,Receiving!$C:$T,5,FALSE)),0)*$AJ66 -> 0 | AP66: =SUMIF($J:$J,$J66,AO:AO) -> 49.607967 | AQ66: =AO66/AP66*AH66 -> 0 | AR66: =Y66*AJ66 -> 0 | AS66: =IFERROR(AR66/AO66*AQ66,0) -> 0 | AT66: =AA66/Team_Defense_Table[[#Totals],[Yards per completion]]*'Fanduel Export'!S66 -> 0 | AU66: =AS66*AT66 -> 0 | AV66: =AD66*AJ66 -> 3.6 | AW66: =SUMIF($J:$J,$J66,AV:AV) -> 42.314011 | AX66: =IFERROR(AV66/AW66*AI66,0) -> 1.7447689 | AY66: =AF66/Team_Defense_Table[[#Totals],[Rushing Y/A]]*R66 -> 4.3683145 | AZ66: =AY66*AX66 -> 7.6216993 | BA66: =AN66/25+AU66/10+AZ66/10+AR66*0.5 -> 10.266455 | BB66: =BA66/(H66/1000) -> 1.6041336 | BC66: =AO66/(H66/1000) -> 0 | BD66: =D66 -> Ryan Fitzpatrick | BE66: =H66 -> 6400 | BF66: =B66 -> QB
A67: 47691-22031 | B67: WR | C67: T.Y. | D67: T.Y. Hilton | E67: Hilton | F67: 10.26 | G67: 10 | H67: 6400 | I67: IND@JAC | J67: IND | K67: JAC | L67: O | M67: Hamstring | O67: =D67 -> T.Y. Hilton | P67: =IFERROR(VLOOKUP(O:O,'Name Bridge'!A:B,2,FALSE),O:O) -> T.Y. Hilton | Q67: =VLOOKUP($K67,'Defensive Stats'!$AC:$AH,2,FALSE) -> 7.3075435 | R67: =VLOOKUP($K67,'Defensive Stats'!$AC:$AH,4,FALSE) -> 5.1241379 | S67: =VLOOKUP($K67,'Defensive Stats'!$AC:$AH,6,FALSE) -> 11.553517 | T67: =IFERROR(VLOOKUP($P67,Passing!$C:$AF,9,FALSE)/VLOOKUP($P67,Passing!$C:$AF,5,FALSE),0) -> 0 | U67: =IFERROR(VLOOKUP($P67,Passing!$C:$AF,11,FALSE)/VLOOKUP($P67,Passing!$C:$AF,5,FALSE),0) -> 0 | V67: =IFERROR(VLOOKUP($P67,Passing!$C:$AF,18,FALSE),0) -> 0 | W67: =IFERROR(VLOOKUP($P67,Passing!$C:$AF,12,FALSE)/VLOOKUP($P67,Passing!$C:$AF,5,FALSE),0) -> 0 | X67: =IFERROR(IF(OR($B67="D",$B67="K"),0,VLOOKUP($P67,Receiving!$C:$T,7,FALSE)/VLOOKUP($P67,Receiving!$C:$T,5,FALSE)),0)*$AJ67 -> 6.8 | Y67: =IFERROR(VLOOKUP($P67,Receiving!$C:$T,8,FALSE)/VLOOKUP($P67,Receiving!$C:$T,5,FALSE),0) -> 4.5 | Z67: =IFERROR(VLOOKUP($P67,Receiving!$C:$T,10,FALSE)/VLOOKUP($P67,Receiving!$C:$T,5,FALSE),0) -> 50.1 | AA67: =IFERROR(VLOOKUP($P67,Receiving!$C:$T,11,FALSE),0) -> 11.1 | AB67: =IFERROR(VLOOKUP($P67,Receiving!$C:$T,14,FALSE),0) -> 35 | AC67: =IFERROR(VLOOKUP($P67,Receiving!$C:$T,11,FALSE)/VLOOKUP($P67,Receiving!$C:$T,5,FALSE),0) -> 1.11 | AD67: =IFERROR(VLOOKUP($P67,Rushing!$C:$P,7,FALSE)/VLOOKUP($P67,Rushing!$C:$P,5,FALSE),0) -> 0 | AE67: =IFERROR(VLOOKUP($P67,Rushing!$C:$P,8,FALSE)/VLOOKUP($P67,Rushing!$C:$P,5,FALSE),0) -> 0 | AF67: =IFERROR(VLOOKUP($P67,Rushing!$C:$P,12,FALSE),0) -> 0 | AG67: =IFERROR(VLOOKUP($P67,Rushing!$C:$P,9,FALSE)/VLOOKUP($P67,Rushing!$C:$P,5,FALSE),0) -> 0 | AH67: =VLOOKUP($J67,'Vegas Odds'!$B:$S,18,FALSE) -> 24.832312 | AI67: =VLOOKUP($J67,'Vegas Odds'!$B:$S,17,FALSE) -> 36.767688 | AJ67: 1 | AK67: =T67*AJ67 -> 0 | AL67: =IF(AND(AJ67=1,B67="QB"),AH67,0) -> 0 | AM67: =V67/Team_Defense_Table[[#Totals],[Passing yds/att]]*'Fanduel Export'!Q67 -> 0 | AN67: =AM67*AL67 -> 0 | AO67: =IFERROR(IF(OR($B67="D",$B67="K"),0,VLOOKUP($P67,Receiving!$C:$T,7,FALSE)/VLOOKUP($P67,Receiving!$C:$T,5,FALSE)),0)*$AJ67 -> 6.8 | AP67: =SUMIF($J:$J,$J67,AO:AO) -> 34.886584 | AQ67: =AO67/AP67*AH67 -> 4.8402481 | AR67: =Y67*AJ67 -> 4.5 | AS67: =IFERROR(AR67/AO67*AQ67,0) -> 3.2031054 | AT67: =AA67/Team_Defense_Table[[#Totals],[Yards per completion]]*'Fanduel Export'!S67 -> 12.077394 | AU67: =AS67*AT67 -> 38.685167 | AV67: =AD67*AJ67 -> 0 | AW67: =SUMIF($J:$J,$J67,AV:AV) -> 29.715476 | AX67: =IFERROR(AV67/AW67*AI67,0) -> 0 | AY67: =AF67/Team_Defense_Table[[#Totals],[Rushing Y/A]]*R67 -> 0 | AZ67: =AY67*AX67 -> 0 | BA67: =AN67/25+AU67/10+AZ67/10+AR67*0.5 -> 6.1185167 | BB67: =BA67/(H67/1000) -> 0.95601823 | BC67: =AO67/(H67/1000) -> 1.0625 | BD67: =D67 -> T.Y. Hilton | BE67: =H67 -> 6400 | BF67: =B67 -> WR
A68: 47691-22027 | B68: QB | C68: Nick | D68: Nick Foles | E68: Foles | F68: 9.9350004 | G68: 4 | H68: 6300 | I68: CHI@DET | J68: CHI | K68: DET | O68: =D68 -> Nick Foles | P68: =IFERROR(VLOOKUP(O:O,'Name Bridge'!A:B,2,FALSE),O:O) -> Nick Foles | Q68: =VLOOKUP($K68,'Defensive Stats'!$AC:$AH,2,FALSE) -> 7.4484452 | R68: =VLOOKUP($K68,'Defensive Stats'!$AC:$AH,4,FALSE) -> 4.0769231 | S68: =VLOOKUP($K68,'Defensive Stats'!$AC:$AH,6,FALSE) -> 11.944882 | T68: =IFERROR(VLOOKUP($P68,Passing!$C:$AF,9,FALSE)/VLOOKUP($P68,Passing!$C:$AF,5,FALSE),0) -> 29.25 | U68: =IFERROR(VLOOKUP($P68,Passing!$C:$AF,11,FALSE)/VLOOKUP($P68,Passing!$C:$AF,5,FALSE),0) -> 184 | V68: =IFERROR(VLOOKUP($P68,Passing!$C:$AF,18,FALSE),0) -> 6.3 | W68: =IFERROR(VLOOKUP($P68,Passing!$C:$AF,12,FALSE)/VLOOKUP($P68,Passing!$C:$AF,5,FALSE),0) -> 0.75 | X68: =IFERROR(IF(OR($B68="D",$B68="K"),0,VLOOKUP($P68,Receiving!$C:$T,7,FALSE)/VLOOKUP($P68,Receiving!$C:$T,5,FALSE)),0)*$AJ68 -> 0 | Y68: =IFERROR(VLOOKUP($P68,Receiving!$C:$T,8,FALSE)/VLOOKUP($P68,Receiving!$C:$T,5,FALSE),0) -> 0 | Z68: =IFERROR(VLOOKUP($P68,Receiving!$C:$T,10,FALSE)/VLOOKUP($P68,Receiving!$C:$T,5,FALSE),0) -> 0 | AA68: =IFERROR(VLOOKUP($P68,Receiving!$C:$T,11,FALSE),0) -> 0 | AB68: =IFERROR(VLOOKUP($P68,Receiving!$C:$T,14,FALSE),0) -> 0 | AC68: =IFERROR(VLOOKUP($P68,Receiving!$C:$T,11,FALSE)/VLOOKUP($P68,Receiving!$C:$T,5,FALSE),0) -> 0 | AD68: =IFERROR(VLOOKUP($P68,Rushing!$C:$P,7,FALSE)/VLOOKUP($P68,Rushing!$C:$P,5,FALSE),0) -> 1 | AE68: =IFERROR(VLOOKUP($P68,Rushing!$C:$P,8,FALSE)/VLOOKUP($P68,Rushing!$C:$P,5,FALSE),0) -> 5.75 | AF68: =IFERROR(VLOOKUP($P68,Rushing!$C:$P,12,FALSE),0) -> 5.8 | AG68: =IFERROR(VLOOKUP($P68,Rushing!$C:$P,9,FALSE)/VLOOKUP($P68,Rushing!$C:$P,5,FALSE),0) -> 0 | AH68: =VLOOKUP($J68,'Vegas Odds'!$B:$S,18,FALSE) -> 39.087289 | AI68: =VLOOKUP($J68,'Vegas Odds'!$B:$S,17,FALSE) -> 21.912711 | AJ68: 1 | AK68: =T68*AJ68 -> 29.25 | AL68: =IF(AND(AJ68=1,B68="QB"),AH68,0) -> 39.087289 | AM68: =V68/Team_Defense_Table[[#Totals],[Passing yds/att]]*'Fanduel Export'!Q68 -> 6.9618893 | AN68: =AM68*AL68 -> 272.12138 | AO68: =IFERROR(IF(OR($B68="D",$B68="K"),0,VLOOKUP($P68,Receiving!$C:$T,7,FALSE)/VLOOKUP($P68,Receiving!$C:$T,5,FALSE)),0)*$AJ68 -> 0 | AP68: =SUMIF($J:$J,$J68,AO:AO) -> 29.935714 | AQ68: =AO68/AP68*AH68 -> 0 | AR68: =Y68*AJ68 -> 0 | AS68: =IFERROR(AR68/AO68*AQ68,0) -> 0 | AT68: =AA68/Team_Defense_Table[[#Totals],[Yards per completion]]*'Fanduel Export'!S68 -> 0 | AU68: =AS68*AT68 -> 0 | AV68: =AD68*AJ68 -> 1 | AW68: =SUMIF($J:$J,$J68,AV:AV) -> 24.985714 | AX68: =IFERROR(AV68/AW68*AI68,0) -> 0.87700957 | AY68: =AF68/Team_Defense_Table[[#Totals],[Rushing Y/A]]*R68 -> 5.4831661 | AZ68: =AY68*AX68 -> 4.8087891 | BA68: =AN68/25+AU68/10+AZ68/10+AR68*0.5 -> 11.365734 | BB68: =BA68/(H68/1000) -> 1.8040848 | BC68: =AO68/(H68/1000) -> 0 | BD68: =D68 -> Nick Foles | BE68: =H68 -> 6300 | BF68: =B68 -> QB
